Workbook

Sheet Sommaire
A1: FICHES TECHNIQUES – MENU ANNUEL EHPAD / FAM
A2: Cliquer sur le nom d'une fiche pour l'ouvrir. Modes : CBT – cuisson de nuit (four vapeur 12-18 h) ; Sous vide basse température ; Cuisson traditionnelle ; Préparation froide.
A3: Sur chaque fiche : saisir le nombre de portions à produire (B24) et, si besoin, le grammage (B23) et les prix unitaires (colonne E) ; les quantités de production (colonne C) et les coûts se recalculent.
A5: Catégorie | B5: Fiche | C5: Mode de cuisson | D5: Titre de la fiche | E5: Nb de fois au menu 2026
A6: Entrée | B6: Salade verte | C6: Préparation froide | D6: Salade verte | E6: 92
A7: Entrée | B7: Potage de légumes | C7: CBT – cuisson de nuit | D7: Potage de légumes cuisson de nuit | E7: 44
A8: Entrée | B8: Potage de féculents | C8: CBT – cuisson de nuit | D8: Potage de féculents cuisson de nuit | E8: 14
A9: Entrée | B9: Taboulé | C9: Préparation froide | D9: Taboulé | E9: 38
A10: Entrée | B10: Feuilleté | C10: Cuisson traditionnelle | D10: Feuilleté | E10: 29
A11: Entrée | B11: Salade d'endives | C11: Préparation froide | D11: Salade d'endives | E11: 21
A12: Entrée | B12: Salade d'endives aux noix | C12: Préparation froide | D12: Salade d'endives aux noix | E12: 2
A13: Entrée | B13: Endives au bleu et aux noix | C13: Préparation froide | D13: Endives au bleu et aux noix | E13: 2
A14: Entrée | B14: Salade de riz | C14: Préparation froide | D14: Salade de riz | E14: 20
A15: Entrée | B15: Betteraves vinaigrette | C15: Sous vide basse température | D15: Betteraves vinaigrette sous vide basse température | E15: 35
A16: Entrée | B16: Salade de betteraves et maïs | C16: Sous vide basse température | D16: Salade de betteraves et maïs sous vide basse température | E16: 4
A17: Entrée | B17: Salade mexicaine | C17: Préparation froide | D17: Salade mexicaine | E17: 14
... A279: Dessert | B279: Tarte aux framboises | C279: Cuisson traditionnelle | D279: Tarte aux framboises | E279: 1
A280: Autres fiches du chef | B280: Joue de boeuf | C280: CBT – fiche originale du chef | D280: Joue de bœuf aubergine et chorizo cuisson de nuit
A281: Autres fiches du chef | B281: Haricots rouges | C281: CBT – fiche originale du chef | D281: Haricots Rouges Chili cuisson de nuit
A282: Autres fiches du chef | B282: Chili-viande à part | C282: CBT – fiche originale du chef | D282: Haricots Rouges - Chili- viande à part cuisson de nuit
A283: Autres fiches du chef | B283: COCO-Catalans | C283: CBT – fiche originale du chef | D283: Coco Catalans cuisson de nuit
A284: Autres fiches du chef | B284: Pois Chiches | C284: CBT – fiche originale du chef | D284: Pois chiches cuisson de nuit

Sheet Paramètres
A1: PARAMÈTRES DE PRODUCTION
A2: Nombre de portions de la recette de base | B2: 70 | C2: Les quantités de la colonne B de chaque fiche sont calculées pour ce nombre de portions.
A3: Effectif maison de retraite (EHPAD) | B3: 70 | C3: À CONFIRMER – valeur provisoire, à saisir.
A4: Effectif FAM | B4: 40 | C4: Saisi d'après les indications du chef.
A5: Nombre de portions à produire (total) | B5: =B3+B4 -> 110 | C5: Utilisé par défaut en B24 de chaque fiche (modifiable fiche par fiche).
A7: Cellules jaunes = à saisir. Le total se recalcule automatiquement.

Sheet Cadencier
A1: CADENCIER – CATALOGUE DES PRODUITS
A2: Prix de base = estimation grossiste collectivité 2026 (HT, par unité d'achat), à remplacer par vos prix facture. Saisir le prix facture (colonne G, jaune), la date et le fournisseur : le prix retenu (J) bascule automatiquement sur le prix facture et met à jour toutes les fiches.
A4: Code | B4: Famille | C4: Produit | D4: Unité | E4: Conditionnement | F4: Prix de base estimé HT (€/unité) | G4: Prix facture HT (€/unité) | H4: Date facture | I4: Fournisseur | J4: Prix retenu (€/unité) | K4: Nb de fiches | L4: Observations
A5: VIA-001 | B5: Viandes | C5: Agneau haché 15 % MG | D5: Kg | E5: barquette 2,5 kg | F5: 12.5 | J5: =IF(G5<>"",G5,F5) -> 12.5 | K5: 2
A6: VIA-002 | B6: Viandes | C6: Boulettes de bœuf crues surgelées 30 g | D6: Kg | E6: carton 5 kg | F6: 8.5 | J6: =IF(G6<>"",G6,F6) -> 8.5 | K6: 1
A7: VIA-003 | B7: Viandes | C7: Brochettes de bœuf 100 g | D7: Kg | E7: barquette 5 kg (50 pièces) | F7: 14 | J7: =IF(G7<>"",G7,F7) -> 14 | K7: 1
A8: VIA-004 | B8: Viandes | C8: Bœuf haché 15 % MG frais | D8: Kg | E8: barquette 2,5 kg | F8: 9.5 | J8: =IF(G8<>"",G8,F8) -> 9.5 | K8: 9
A9: VIA-005 | B9: Viandes | C9: Bœuf haché 15 % MG surgelé | D9: Kg | E9: sachet 2,5 kg | F9: 8.5 | J9: =IF(G9<>"",G9,F9) -> 8.5 | K9: 1
A10: VIA-006 | B10: Viandes | C10: Cuisses de lapin surgelées 180 g | D10: Kg | E10: carton 5 kg | F10: 9.5 | J10: =IF(G10<>"",G10,F10) -> 9.5 | K10: 1
A11: VIA-007 | B11: Viandes | C11: Égrené de bœuf | D11: Kg | E11: sachet 2,5 kg | F11: 8 | J11: =IF(G11<>"",G11,F11) -> 8 | K11: 0
A12: VIA-008 | B12: Viandes | C12: Escalopes de porc 110 g | D12: Kg | E12: barquette 5 kg | F12: 8 | J12: =IF(G12<>"",G12,F12) -> 8 | K12: 1
A13: VIA-009 | B13: Viandes | C13: Escalopes de veau 110 g | D13: Kg | E13: barquette 5 kg | F13: 18 | J13: =IF(G13<>"",G13,F13) -> 18 | K13: 1
A14: VIA-010 | B14: Viandes | C14: Filet mignon de porc paré | D14: Kg | E14: sous vide 5 kg | F14: 9.5 | J14: =IF(G14<>"",G14,F14) -> 9.5 | K14: 1
A15: VIA-011 | B15: Viandes | C15: Gigot d'agneau désossé ficelé | D15: Kg | E15: sous vide 2-2,5 kg | F15: 15.5 | J15: =IF(G15<>"",G15,F15) -> 15.5 | K15: 1
A16: VIA-012 | B16: Viandes | C16: Joue de bœuf parée | D16: Kg | E16: sous vide 3 kg | F16: 10.5 | J16: =IF(G16<>"",G16,F16) -> 10.5 | K16: 0
... A132: BOF-025 | B132: Produits laitiers et œufs (BOF) | C132: Tome fraîche de l'Aubrac | D132: Kg | E132: pièce 2 kg | F132: 12 | J132: =IF(G132<>"",G132,F132) -> 12 | K132: 1
A133: BOF-026 | B133: Produits laitiers et œufs (BOF) | C133: Œufs coquille calibre moyen | D133: Kg | E133: plateau 30 x 6 (≈ 0.18 €/pièce) | F133: 3 | J133: =IF(G133<>"",G133,F133) -> 3 | K133: 1 | L133: Prix converti au kg sur la base de 60 g par pièce
A134: BOF-027 | B134: Produits laitiers et œufs (BOF) | C134: Œufs durs écalés pasteurisés | D134: Kg | E134: seau 75 pièces (≈ 0.28 €/pièce) | F134: 5.6 | J134: =IF(G134<>"",G134,F134) -> 5.6 | K134: 12 | L134: Prix converti au kg sur la base de 50 g par pièce
A135: BOF-028 | B135: Produits laitiers et œufs (BOF) | C135: Œufs entiers liquides pasteurisés | D135: L | E135: brique 1 L x 6 | F135: 3.8 | J135: =IF(G135<>"",G135,F135) -> 3.8 | K135: 21
A136: BOF-029 | B136: Produits laitiers et œufs (BOF) | C136: Yaourt nature | D136: Kg | E136: seau 5 kg | F136: 2.5 | J136: =IF(G136<>"",G136,F136) -> 2.5 | K136: 1
A137: FLF-001 | B137: Fruits et légumes frais | C137: Ail frais | D137: Kg | E137: filet 1 kg | F137: 6 | J137: =IF(G137<>"",G137,F137) -> 6 | K137: 0
A138: FLF-002 | B138: Fruits et légumes frais | C138: Ananas frais | D138: Kg | E138: carton 8 pièces (≈ 2.80 €/pièce) | F138: 1.87 | J138: =IF(G138<>"",G138,F138) -> 1.87 | K138: 1 | L138: Prix converti au kg sur la base de 1500 g par pièce
A139: FLF-003 | B139: Fruits et légumes frais | C139: Asperges blanches fraîches épluchées | D139: Kg | E139: botte 1 kg | F139: 9 | J139: =IF(G139<>"",G139,F139) -> 9 | K139: 1
A140: FLF-004 | B140: Fruits et légumes frais | C140: Aubergines fraîches | D140: Kg | E140: colis 5 kg | F140: 2.6 | J140: =IF(G140<>"",G140,F140) -> 2.6 | K140: 2
A141: FLF-005 | B141: Fruits et légumes frais | C141: Avocats | D141: Kg | E141: colis 12 pièces (≈ 1.10 €/pièce) | F141: 5.5 | J141: =IF(G141<>"",G141,F141) -> 5.5 | K141: 1 | L141: Prix converti au kg sur la base de 200 g par pièce
A142: FLF-006 | B142: Fruits et légumes frais | C142: Bananes | D142: Kg | E142: carton 18 kg | F142: 1.6 | J142: =IF(G142<>"",G142,F142) -> 1.6 | K142: 1
A143: FLF-007 | B143: Fruits et légumes frais | C143: Basilic frais (botte) | D143: Kg | E143: botte (≈ 1.60 €/pièce) | F143: 32 | J143: =IF(G143<>"",G143,F143) -> 32 | K143: 2 | L143: Prix converti au kg sur la base de 50 g par pièce
A144: FLF-008 | B144: Fruits et légumes frais | C144: Betteraves rouges crues | D144: Kg | E144: sac 5 kg | F144: 1.4 | J144: =IF(G144<>"",G144,F144) -> 1.4 | K144: 2
A145: FLF-009 | B145: Fruits et légumes frais | C145: Carottes bâtonnets 4ème gamme | D145: Kg | E145: sachet 2,5 kg | F145: 3.2 | J145: =IF(G145<>"",G145,F145) -> 3.2 | K145: 1
A146: FLF-010 | B146: Fruits et légumes frais | C146: Carottes fraîches | D146: Kg | E146: sac 10 kg | F146: 1 | J146: =IF(G146<>"",G146,F146) -> 1 | K146: 3
A147: FLF-011 | B147: Fruits et légumes frais | C147: Carottes râpées 4ème gamme | D147: Kg | E147: sachet 2,5 kg | F147: 3.2 | J147: =IF(G147<>"",G147,F147) -> 3.2 | K147: 2
A148: FLF-012 | B148: Fruits et légumes frais | C148: Céleri-rave (boule) | D148: Kg | E148: colis 10 kg | F148: 1.6 | J148: =IF(G148<>"",G148,F148) -> 1.6 | K148: 1
A149: FLF-013 | B149: Fruits et légumes frais | C149: Céleri-rave râpé 4ème gamme | D149: Kg | E149: sachet 2,5 kg | F149: 3.5 | J149: =IF(G149<>"",G149,F149) -> 3.5 | K149: 1
A150: FLF-014 | B150: Fruits et légumes frais | C150: Chou blanc | D150: Kg | E150: colis 10 kg | F150: 1 | J150: =IF(G150<>"",G150,F150) -> 1 | K150: 1
A151: FLF-015 | B151: Fruits et légumes frais | C151: Chou chinois | D151: Kg | E151: colis 8 kg | F151: 1.9 | J151: =IF(G151<>"",G151,F151) -> 1.9 | K151: 1
A152: FLF-016 | B152: Fruits et légumes frais | C152: Chou rouge râpé 4ème gamme | D152: Kg | E152: sachet 2,5 kg | F152: 3.2 | J152: =IF(G152<>"",G152,F152) -> 3.2 | K152: 1
A153: FLF-017 | B153: Fruits et légumes frais | C153: Chou vert frisé | D153: Kg | E153: colis 10 kg | F153: 1.3 | J153: =IF(G153<>"",G153,F153) -> 1.3 | K153: 1
A154: FLF-018 | B154: Fruits et légumes frais | C154: Citrons jaunes | D154: Kg | E154: colis 10 kg | F154: 2.2 | J154: =IF(G154<>"",G154,F154) -> 2.2 | K154: 13
A155: FLF-019 | B155: Fruits et légumes frais | C155: Citrons verts | D155: Kg | E155: colis 4,5 kg | F155: 3.5 | J155: =IF(G155<>"",G155,F155) -> 3.5 | K155: 1
A156: FLF-020 | B156: Fruits et légumes frais | C156: Concombres | D156: Kg | E156: colis 12 pièces (≈ 0.90 €/pièce) | F156: 2.25 | J156: =IF(G156<>"",G156,F156) -> 2.25 | K156: 5 | L156: Prix converti au kg sur la base de 400 g par pièce
A157: FLF-021 | B157: Fruits et légumes frais | C157: Coriandre fraîche (botte) | D157: Kg | E157: botte (≈ 1.50 €/pièce) | F157: 30 | J157: =IF(G157<>"",G157,F157) -> 30 | K157: 2 | L157: Prix converti au kg sur la base de 50 g par pièce
A158: FLF-022 | B158: Fruits et légumes frais | C158: Courgettes fraîches | D158: Kg | E158: colis 10 kg | F158: 2 | J158: =IF(G158<>"",G158,F158) -> 2 | K158: 2
A159: FLF-023 | B159: Fruits et légumes frais | C159: Endives | D159: Kg | E159: colis 5 kg | F159: 2.6 | J159: =IF(G159<>"",G159,F159) -> 2.6 | K159: 4
A160: FLF-024 | B160: Fruits et légumes frais | C160: Fenouil | D160: Kg | E160: colis 5 kg | F160: 2.8 | J160: =IF(G160<>"",G160,F160) -> 2.8 | K160: 0
A161: FLF-025 | B161: Fruits et légumes frais | C161: Gingembre frais | D161: Kg | E161: colis 1 kg | F161: 6.5 | J161: =IF(G161<>"",G161,F161) -> 6.5 | K161: 3
A162: FLF-026 | B162: Fruits et légumes frais | C162: Kiwis | D162: Kg | E162: plateau 4 kg | F162: 2.8 | J162: =IF(G162<>"",G162,F162) -> 2.8 | K162: 1
A163: FLF-027 | B163: Fruits et légumes frais | C163: Mâche 4ème gamme | D163: Kg | E163: sachet 500 g | F163: 9.5 | J163: =IF(G163<>"",G163,F163) -> 9.5 | K163: 3
A164: FLF-028 | B164: Fruits et légumes frais | C164: Melon charentais | D164: Kg | E164: colis 10 pièces (≈ 1.80 €/pièce) | F164: 1.8 | J164: =IF(G164<>"",G164,F164) -> 1.8 | K164: 1 | L164: Prix converti au kg sur la base de 1000 g par pièce
A165: FLF-029 | B165: Fruits et légumes frais | C165: Menthe fraîche (botte) | D165: Kg | E165: botte (≈ 1.50 €/pièce) | F165: 30 | J165: =IF(G165<>"",G165,F165) -> 30 | K165: 6 | L165: Prix converti au kg sur la base de 50 g par pièce
A166: FLF-030 | B166: Fruits et légumes frais | C166: Mesclun / salade mélangée 4ème gamme | D166: Kg | E166: sachet 1 kg | F166: 7 | J166: =IF(G166<>"",G166,F166) -> 7 | K166: 3
A167: FLF-031 | B167: Fruits et légumes frais | C167: Oignons épluchés 4ème gamme | D167: Kg | E167: sachet 2,5 kg | F167: 2.5 | J167: =IF(G167<>"",G167,F167) -> 2.5 | K167: 0
A168: FLF-032 | B168: Fruits et légumes frais | C168: Oignons jaunes frais | D168: Kg | E168: sac 10 kg | F168: 1 | J168: =IF(G168<>"",G168,F168) -> 1 | K168: 0
A169: FLF-033 | B169: Fruits et légumes frais | C169: Oignons rouges | D169: Kg | E169: sac 5 kg | F169: 1.8 | J169: =IF(G169<>"",G169,F169) -> 1.8 | K169: 8
A170: FLF-034 | B170: Fruits et légumes frais | C170: Oranges | D170: Kg | E170: colis 10 kg | F170: 1.6 | J170: =IF(G170<>"",G170,F170) -> 1.6 | K170: 3
A171: FLF-035 | B171: Fruits et légumes frais | C171: Pamplemousse rose | D171: Kg | E171: colis 20 pièces (≈ 0.90 €/pièce) | F171: 2.25 | J171: =IF(G171<>"",G171,F171) -> 2.25 | K171: 1 | L171: Prix converti au kg sur la base de 400 g par pièce
A172: FLF-036 | B172: Fruits et légumes frais | C172: Panais | D172: Kg | E172: colis 5 kg | F172: 2.5 | J172: =IF(G172<>"",G172,F172) -> 2.5 | K172: 0
A173: FLF-037 | B173: Fruits et légumes frais | C173: Pastèque | D173: Kg | E173: pièce 5-7 kg | F173: 1.1 | J173: =IF(G173<>"",G173,F173) -> 1.1 | K173: 1
A174: FLF-038 | B174: Fruits et légumes frais | C174: Poireaux frais | D174: Kg | E174: colis 10 kg | F174: 2 | J174: =IF(G174<>"",G174,F174) -> 2 | K174: 1
A175: FLF-039 | B175: Fruits et légumes frais | C175: Poires | D175: Kg | E175: plateau 7 kg | F175: 2.4 | J175: =IF(G175<>"",G175,F175) -> 2.4 | K175: 2
A176: FLF-040 | B176: Fruits et légumes frais | C176: Poivrons rouges et verts frais | D176: Kg | E176: colis 5 kg | F176: 3 | J176: =IF(G176<>"",G176,F176) -> 3 | K176: 1
A177: FLF-041 | B177: Fruits et légumes frais | C177: Pommes (Golden / Granny) | D177: Kg | E177: plateau 13 kg | F177: 1.7 | J177: =IF(G177<>"",G177,F177) -> 1.7 | K177: 7
A178: FLF-042 | B178: Fruits et légumes frais | C178: Pommes de terre à farcir calibre 60/70 | D178: Kg | E178: sac 10 kg | F178: 1.2 | J178: =IF(G178<>"",G178,F178) -> 1.2 | K178: 1
A179: FLF-043 | B179: Fruits et légumes frais | C179: Pommes de terre cubes 4ème gamme sous vide | D179: Kg | E179: sachet 5 kg | F179: 2.2 | J179: =IF(G179<>"",G179,F179) -> 2.2 | K179: 9
A180: FLF-044 | B180: Fruits et légumes frais | C180: Pommes de terre entières épluchées 4ème gamme sous vide | D180: Kg | E180: sachet 5 kg | F180: 2 | J180: =IF(G180<>"",G180,F180) -> 2 | K180: 10
A181: FLF-045 | B181: Fruits et légumes frais | C181: Pommes de terre lamelles / rondelles 4ème gamme sous vide | D181: Kg | E181: sachet 5 kg | F181: 2.2 | J181: =IF(G181<>"",G181,F181) -> 2.2 | K181: 4
A182: FLF-046 | B182: Fruits et légumes frais | C182: Pommes de terre râpées 4ème gamme | D182: Kg | E182: sachet 2,5 kg | F182: 2.6 | J182: =IF(G182<>"",G182,F182) -> 2.6 | K182: 1
A183: FLF-047 | B183: Fruits et légumes frais | C183: Potimarron | D183: Kg | E183: colis 10 kg | F183: 2 | J183: =IF(G183<>"",G183,F183) -> 2 | K183: 0
A184: FLF-048 | B184: Fruits et légumes frais | C184: Radis | D184: Kg | E184: botte (≈ 1.00 €/pièce) | F184: 3.33 | J184: =IF(G184<>"",G184,F184) -> 3.33 | K184: 1 | L184: Prix converti au kg sur la base de 300 g par pièce
A185: FLF-049 | B185: Fruits et légumes frais | C185: Raisin | D185: Kg | E185: plateau 5 kg | F185: 3.5 | J185: =IF(G185<>"",G185,F185) -> 3.5 | K185: 1
A186: FLF-050 | B186: Fruits et légumes frais | C186: Roquette / jeunes pousses 4ème gamme | D186: Kg | E186: sachet 500 g | F186: 10 | J186: =IF(G186<>"",G186,F186) -> 10 | K186: 1
A187: FLF-051 | B187: Fruits et légumes frais | C187: Salade frisée | D187: Kg | E187: colis 6 pièces (≈ 1.80 €/pièce) | F187: 3.6 | J187: =IF(G187<>"",G187,F187) -> 3.6 | K187: 8 | L187: Prix converti au kg sur la base de 500 g par pièce
A188: FLF-052 | B188: Fruits et légumes frais | C188: Salade iceberg | D188: Kg | E188: colis 10 pièces (≈ 1.30 €/pièce) | F188: 2.6 | J188: =IF(G188<>"",G188,F188) -> 2.6 | K188: 2 | L188: Prix converti au kg sur la base de 500 g par pièce
A189: FLF-053 | B189: Fruits et légumes frais | C189: Salade verte 4ème gamme (batavia / laitue / frisée) | D189: Kg | E189: sachet 1 kg | F189: 5.5 | J189: =IF(G189<>"",G189,F189) -> 5.5 | K189: 14
A190: FLF-054 | B190: Fruits et légumes frais | C190: Tomates cerises | D190: Kg | E190: barquette 500 g x 8 | F190: 4.5 | J190: =IF(G190<>"",G190,F190) -> 4.5 | K190: 6
A191: FLF-055 | B191: Fruits et légumes frais | C191: Tomates rondes fraîches calibre 67/82 | D191: Kg | E191: colis 6 kg | F191: 2.4 | J191: =IF(G191<>"",G191,F191) -> 2.4 | K191: 17
A192: SUR-001 | B192: Surgelés | C192: Ail surgelé | D192: Kg | E192: sachet 1 kg | F192: 5.5 | J192: =IF(G192<>"",G192,F192) -> 5.5 | K192: 83
A193: SUR-002 | B193: Surgelés | C193: Aneth ciselé surgelé | D193: Kg | E193: sachet 250 g | F193: 14 | J193: =IF(G193<>"",G193,F193) -> 14 | K193: 3
A194: SUR-003 | B194: Surgelés | C194: Asperges vertes surgelées | D194: Kg | E194: sachet 1 kg | F194: 7.5 | J194: =IF(G194<>"",G194,F194) -> 7.5 | K194: 1
A195: SUR-004 | B195: Surgelés | C195: Aubergines cubes surgelées | D195: Kg | E195: sachet 2,5 kg | F195: 2.8 | J195: =IF(G195<>"",G195,F195) -> 2.8 | K195: 1
A196: SUR-005 | B196: Surgelés | C196: Aubergines tranches grillées surgelées | D196: Kg | E196: sachet 1 kg | F196: 5.5 | J196: =IF(G196<>"",G196,F196) -> 5.5 | K196: 1
A197: SUR-006 | B197: Surgelés | C197: Basilic ciselé surgelé | D197: Kg | E197: sachet 250 g | F197: 12 | J197: =IF(G197<>"",G197,F197) -> 12 | K197: 8
A198: SUR-007 | B198: Surgelés | C198: Brocolis fleurettes surgelés | D198: Kg | E198: sachet 2,5 kg | F198: 2.3 | J198: =IF(G198<>"",G198,F198) -> 2.3 | K198: 4
A199: SUR-008 | B199: Surgelés | C199: Brunoise de légumes surgelée | D199: Kg | E199: sachet 2,5 kg | F199: 4 | J199: =IF(G199<>"",G199,F199) -> 4 | K199: 3
A200: SUR-009 | B200: Surgelés | C200: Carottes bâtonnets surgelées | D200: Kg | E200: sachet 2,5 kg | F200: 2.2 | J200: =IF(G200<>"",G200,F200) -> 2.2 | K200: 1
... A222: SUR-031 | B222: Surgelés | C222: Estragon ciselé surgelé | D222: Kg | E222: sachet 250 g | F222: 14 | J222: =IF(G222<>"",G222,F222) -> 14 | K222: 2
A223: SUR-032 | B223: Surgelés | C223: Feuilletés jambon fromage surgelés 90 g | D223: Kg | E223: carton 40 pièces (≈ 0.75 €/pièce) | F223: 8.33 | J223: =IF(G223<>"",G223,F223) -> 8.33 | K223: 1 | L223: Prix converti au kg sur la base de 90 g par pièce
A224: SUR-033 | B224: Surgelés | C224: Fonds d'artichauts surgelés | D224: Kg | E224: sachet 1 kg | F224: 8 | J224: =IF(G224<>"",G224,F224) -> 8 | K224: 1
A225: SUR-034 | B225: Surgelés | C225: Framboises IQF surgelées | D225: Kg | E225: sachet 1 kg | F225: 9 | J225: =IF(G225<>"",G225,F225) -> 9 | K225: 1
A226: SUR-035 | B226: Surgelés | C226: Frites de patate douce surgelées | D226: Kg | E226: sachet 2,5 kg | F226: 3.5 | J226: =IF(G226<>"",G226,F226) -> 3.5 | K226: 1
A227: SUR-036 | B227: Surgelés | C227: Frites précuites surgelées spécial four | D227: Kg | E227: sachet 2,5 kg | F227: 2 | J227: =IF(G227<>"",G227,F227) -> 2 | K227: 1
A228: SUR-037 | B228: Surgelés | C228: Fruits rouges IQF surgelés | D228: Kg | E228: sachet 1 kg | F228: 6.5 | J228: =IF(G228<>"",G228,F228) -> 6.5 | K228: 1
A229: SUR-038 | B229: Surgelés | C229: Haricots beurre surgelés | D229: Kg | E229: sachet 2,5 kg | F229: 2.6 | J229: =IF(G229<>"",G229,F229) -> 2.6 | K229: 2
A230: SUR-039 | B230: Surgelés | C230: Haricots plats coupés surgelés | D230: Kg | E230: sachet 2,5 kg | F230: 2.6 | J230: =IF(G230<>"",G230,F230) -> 2.6 | K230: 1
A231: SUR-040 | B231: Surgelés | C231: Haricots verts extra-fins surgelés | D231: Kg | E231: sachet 2,5 kg | F231: 2.8 | J231: =IF(G231<>"",G231,F231) -> 2.8 | K231: 2
A232: SUR-041 | B232: Surgelés | C232: Haricots verts surgelés | D232: Kg | E232: sachet 2,5 kg | F232: 2.2 | J232: =IF(G232<>"",G232,F232) -> 2.2 | K232: 2
A233: SUR-042 | B233: Surgelés | C233: Jardinière de légumes surgelée | D233: Kg | E233: sachet 2,5 kg | F233: 2.4 | J233: =IF(G233<>"",G233,F233) -> 2.4 | K233: 1
A234: SUR-043 | B234: Surgelés | C234: Julienne de légumes asiatiques surgelée | D234: Kg | E234: sachet 2,5 kg | F234: 3.2 | J234: =IF(G234<>"",G234,F234) -> 3.2 | K234: 1
A235: SUR-044 | B235: Surgelés | C235: Légumes pour couscous surgelés | D235: Kg | E235: sachet 2,5 kg | F235: 2.6 | J235: =IF(G235<>"",G235,F235) -> 2.6 | K235: 1
... A248: SUR-057 | B248: Surgelés | C248: Petits pois surgelés | D248: Kg | E248: sachet 2,5 kg | F248: 2.3 | J248: =IF(G248<>"",G248,F248) -> 2.3 | K248: 5
A249: SUR-058 | B249: Surgelés | C249: Pizzas surgelées 400 g | D249: Kg | E249: carton 10 pièces (≈ 2.60 €/pièce) | F249: 6.5 | J249: =IF(G249<>"",G249,F249) -> 6.5 | K249: 1 | L249: Prix converti au kg sur la base de 400 g par pièce
...

Sheet Correspondance
A1: Correspondance entre les intitulés utilisés dans les fiches et les produits du cadencier (le prix est repris du cadencier par formule). Modifier le code (colonne B) pour rattacher un intitulé à un autre produit.
A2: Intitulé dans les fiches | B2: Code produit | C2: Produit du cadencier | D2: Prix retenu (€/unité)
A3: Agneau ou bœuf haché | B3: VIA-001 | C3: =IFERROR(INDEX(Cadencier!$C$5:$C$441,MATCH(B3,Cadencier!$A$5:$A$441,0)),"code inconnu") -> Agneau haché 15 % MG | D3: =IFERROR(INDEX(Cadencier!$J$5:$J$441,MATCH(B3,Cadencier!$A$5:$A$441,0)),0) -> 12.5
A4: Aiguillettes de poulet | B4: VOL-001 | C4: =IFERROR(INDEX(Cadencier!$C$5:$C$441,MATCH(B4,Cadencier!$A$5:$A$441,0)),"code inconnu") -> Aiguillettes de poulet | D4: =IFERROR(INDEX(Cadencier!$J$5:$J$441,MATCH(B4,Cadencier!$A$5:$A$441,0)),0) -> 10.5
A5: Ail | B5: FLF-001 | C5: =IFERROR(INDEX(Cadencier!$C$5:$C$441,MATCH(B5,Cadencier!$A$5:$A$441,0)),"code inconnu") -> Ail frais | D5: =IFERROR(INDEX(Cadencier!$J$5:$J$441,MATCH(B5,Cadencier!$A$5:$A$441,0)),0) -> 6
A6: Ail surgelé | B6: SUR-001 | C6: =IFERROR(INDEX(Cadencier!$C$5:$C$441,MATCH(B6,Cadencier!$A$5:$A$441,0)),"code inconnu") -> Ail surgelé | D6: =IFERROR(INDEX(Cadencier!$J$5:$J$441,MATCH(B6,Cadencier!$A$5:$A$441,0)),0) -> 5.5
A7: Ananas frais (ou 4ème gamme) | B7: FLF-002 | C7: =IFERROR(INDEX(Cadencier!$C$5:$C$441,MATCH(B7,Cadencier!$A$5:$A$441,0)),"code inconnu") -> Ananas frais | D7: =IFERROR(INDEX(Cadencier!$J$5:$J$441,MATCH(B7,Cadencier!$A$5:$A$441,0)),0) -> 1.87
A8: Anchois en filets (ou pâte d'anchois) | B8: CON-001 | C8: =IFERROR(INDEX(Cadencier!$C$5:$C$441,MATCH(B8,Cadencier!$A$5:$A$441,0)),"code inconnu") -> Anchois en filets (à l'huile) | D8: =IFERROR(INDEX(Cadencier!$J$5:$J$441,MATCH(B8,Cadencier!$A$5:$A$441,0)),0) -> 22
A9: Andouillettes AAAAA 150 g (environ 65 pièces) | B9: CHA-001 | C9: =IFERROR(INDEX(Cadencier!$C$5:$C$441,MATCH(B9,Cadencier!$A$5:$A$441,0)),"code inconnu") -> Andouillettes AAAAA 150 g | D9: =IFERROR(INDEX(Cadencier!$J$5:$J$441,MATCH(B9,Cadencier!$A$5:$A$441,0)),0) -> 11
A10: Aneth ciselé surgelé | B10: SUR-002 | C10: =IFERROR(INDEX(Cadencier!$C$5:$C$441,MATCH(B10,Cadencier!$A$5:$A$441,0)),"code inconnu") -> Aneth ciselé surgelé | D10: =IFERROR(INDEX(Cadencier!$J$5:$J$441,MATCH(B10,Cadencier!$A$5:$A$441,0)),0) -> 14
A11: Aneth PM | B11: SUR-002 | C11: =IFERROR(INDEX(Cadencier!$C$5:$C$441,MATCH(B11,Cadencier!$A$5:$A$441,0)),"code inconnu") -> Aneth ciselé surgelé | D11: =IFERROR(INDEX(Cadencier!$J$5:$J$441,MATCH(B11,Cadencier!$A$5:$A$441,0)),0) -> 14
A12: Aneth surgelé | B12: SUR-002 | C12: =IFERROR(INDEX(Cadencier!$C$5:$C$441,MATCH(B12,Cadencier!$A$5:$A$441,0)),"code inconnu") -> Aneth ciselé surgelé | D12: =IFERROR(INDEX(Cadencier!$J$5:$J$441,MATCH(B12,Cadencier!$A$5:$A$441,0)),0) -> 14
A13: Anneaux de calamar surgelés | B13: POI-001 | C13: =IFERROR(INDEX(Cadencier!$C$5:$C$441,MATCH(B13,Cadencier!$A$5:$A$441,0)),"code inconnu") -> Anneaux de calamar surgelés | D13: =IFERROR(INDEX(Cadencier!$J$5:$J$441,MATCH(B13,Cadencier!$A$5:$A$441,0)),0) -> 8.5
A14: Anneaux ou lanières de calamars surgelés | B14: POI-001 | C14: =IFERROR(INDEX(Cadencier!$C$5:$C$441,MATCH(B14,Cadencier!$A$5:$A$441,0)),"code inconnu") -> Anneaux de calamar surgelés | D14: =IFERROR(INDEX(Cadencier!$J$5:$J$441,MATCH(B14,Cadencier!$A$5:$A$441,0)),0) -> 8.5
... A753: Œufs liquides pasteurisés | B753: BOF-028 | C753: =IFERROR(INDEX(Cadencier!$C$5:$C$441,MATCH(B753,Cadencier!$A$5:$A$441,0)),"code inconnu") -> Œufs entiers liquides pasteurisés | D753: =IFERROR(INDEX(Cadencier!$J$5:$J$441,MATCH(B753,Cadencier!$A$5:$A$441,0)),0) -> 3.8

Sheet Menu → fiches
A1: Semaine | B1: Jour | C1: Service | D1: Entrée (menu) | E1: Fiche entrée | F1: Plat (menu) | G1: Fiche plat | H1: Garniture (menu) | I1: Fiche garniture | J1: Dessert (menu) | K1: Fiche dessert
A2: semaine 1 | B2: Lundi | C2: Midi | D2: Taboulé | E2: Taboulé | F2: Paupiette de volaile | G2: Paupiette de volaille | H2: Choux fleur | I2: Chou-fleur persillé | J2: Fruit
A3: semaine 1 | B3: Lundi | C3: Soir | D3: Mache | E3: Salade de mâche | F3: Jambon Blanc | G3: Jambon blanc | H3: pomme de terre rissolées | I3: Pommes de terre rissolées | J3: Fruit
A4: semaine 1 | B4: Mardi | C4: Midi | D4: Poireau en salade | E4: Poireaux vinaigrette | F4: tartiflette | G4: Tartiflette | J4: Dessert
A5: semaine 1 | B5: Mardi | C5: Soir | D5: Potage de Légumes | E5: Potage de légumes | F5: œuf mayonnaise | G5: Œuf mayonnaise | H5: salsifi | I5: Salsifis | J5: Fruit
A6: semaine 1 | B6: Mercredi | C6: Midi | D6: Salade de lentille | E6: Salade de lentilles | F6: Suprême de volaille | G6: Suprême de volaille | H6: Haricots verts | I6: Salade de haricots verts | J6: Fruit
A7: semaine 1 | B7: Mercredi | C7: Soir | D7: Velouté de cépes chataigne | E7: Velouté de cèpes et châtaignes | F7: Croustade escargots | G7: Croustade d'escargots | H7: Duo de carottes | I7: Carottes Vichy | J7: Entremets croustillant chocolat | K7: Entremets croustillant chocolat
A8: semaine 1 | B8: Jeudi | C8: Midi | D8: salade périgoudine | E8: Salade périgourdine | F8: Filet mignon au cidre | G8: Filet mignon de porc au cidre | H8: Risotto | I8: Risotto | J8: Entremet vanille Fruit rouge | K8: Entremets vanille fruits rouges
A9: semaine 1 | B9: Jeudi | C9: Soir | D9: Soupe de poisson | E9: Soupe de poisson | F9: Feuilleté | G9: Feuilleté | H9: Crumble de légumes | I9: Crumble de légumes | J9: Fruit
A10: semaine 1 | B10: Vendredi | C10: Midi | D10: Paté aux olives | E10: Pâté aux olives | F10: Pavé de poisson | G10: Pavé de poisson sauce beurre blanc | H10: Riz | I10: Riz pilaf | J10: Fruit
A11: semaine 1 | B11: Vendredi | C11: Soir | D11: Terrine de légumes | E11: Terrine de légumes | F11: Qunelle de volaille | G11: Quenelles de volaille sauce | H11: carottes | I11: Carottes Vichy | J11: Fruit
A12: semaine 1 | B12: Samedi | C12: Midi | D12: salade de Pâtess | E12: Salade de pâtes | F12: Roti de porc | G12: Rôti de porc | H12: Choux rpmanesco | I12: Chou romanesco | J12: Fruit
A13: semaine 1 | B13: Samedi | C13: Soir | D13: Potage de Légumes | E13: Potage de légumes | F13: lasagne au bœuf | G13: Lasagnes au bœuf | J13: Fruit
A14: semaine 1 | B14: Dimanche | C14: Midi | D14: salade verte | E14: Salade verte | F14: escalope milanaise | G14: Escalope viennoise | H14: semoule | I14: Semoule | J14: Dessert
A15: semaine 1 | B15: Dimanche | C15: Soir | D15: carottes rapées | E15: Carottes râpées | F15: dos de colin meunière | G15: Dos de colin meunière | H15: rapé de pomme de terre | I15: Râpé de pommes de terre | J15: Fruit
A16: semaine 2 | B16: Lundi | C16: Midi | D16: Salade verte | E16: Salade verte | F16: Sauté de Lapin | G16: Sauté de lapin | H16: Choux de Bruxelles | I16: Choux de Bruxelles | J16: Fruit
A17: semaine 2 | B17: Lundi | C17: Soir | D17: Salade de Perles | E17: Salade de perles | F17: Endives au Jambon | G17: Endives au jambon | J17: Fruit
A18: semaine 2 | B18: Mardi | C18: Midi | D18: Salade Coleslow | E18: Coleslaw | F18: Croziflette | G18: Croziflette | J18: Dessert
A19: semaine 2 | B19: Mardi | C19: Soir | D19: Potage de Légumes | E19: Potage de légumes | F19: Chipolatas | G19: Chipolatas | H19: Haricots blanc | I19: Haricots blancs | J19: Fruit
A20: semaine 2 | B20: Mercredi | C20: Midi | D20: Taboulé | E20: Taboulé | F20: Escalope dinde | G20: Escalope de dinde | H20: gratin de potimarron | I20: Gratin de potimarron | J20: Fruit
A21: semaine 2 | B21: Mercredi | C21: Soir | D21: Macédoine de Légumes | E21: Macédoine mayonnaise | F21: Raviolis | G21: Raviolis | J21: Fruit
A22: semaine 2 | B22: Jeudi | C22: Midi | D22: Salade de Chou Chinois | E22: Salade de chou chinois | F22: Saucisse | G22: Saucisse de Toulouse | H22: Aligot | I22: Aligot | J22: Fruit
A23: semaine 2 | B23: Jeudi | C23: Soir | D23: Potage de Féculents | E23: Potage de féculents | F23: Œuf béchamel | G23: Œufs durs sauce béchamel | H23: Haricots beurre | I23: Haricots beurre | J23: Fruit
A24: semaine 2 | B24: Vendredi | C24: Midi | D24: Mousse de Canard | E24: Mousse de canard | F24: Saumon | G24: Pavé de saumon | H24: Chou Romanesco | I24: Chou romanesco | J24: Fruit
A25: semaine 2 | B25: Vendredi | C25: Soir | D25: Salade d'endives | E25: Salade d'endives | F25: Chili con carne | G25: Chili con carne | J25: Fruit
A26: semaine 2 | B26: Samedi | C26: Midi | D26: Carottes Rapées | E26: Carottes râpées | F26: Flecque | G26: Flammekueche | J26: Fruit
A27: semaine 2 | B27: Samedi | C27: Soir | D27: Potage de Légumes | E27: Potage de légumes | F27: Pates Carbonara | G27: Pâtes carbonara | J27: Fruit
A28: semaine 2 | B28: Dimanche | C28: Midi | D28: Salade verte | E28: Salade verte | F28: Rôti de Veau | G28: Rôti de veau | H28: Lentilles | I28: Lentilles | J28: Dessert
A29: semaine 2 | B29: Dimanche | C29: Soir | D29: Salade de Riz | E29: Salade de riz | F29: maquereaux | G29: Maquereaux à la moutarde | H29: Poelée de légumes | I29: Poêlée de légumes | J29: Fruit
A30: semaine 3 | B30: Lundi | C30: Midi | D30: Tranche de Jambon Cru | E30: Jambon cru | F30: Pavé de Poisson | G30: Pavé de poisson sauce beurre blanc | H30: Epinards à la crème | I30: Épinards à la crème | J30: Fruit
A31: semaine 3 | B31: Lundi | C31: Soir | D31: Poireaux vinaigrette | E31: Poireaux vinaigrette | F31: Escalope viennoise | G31: Escalope viennoise | H31: Riz | I31: Riz pilaf | J31: Fruit
A32: semaine 3 | B32: Mardi | C32: Midi | D32: Avocat | E32: Avocat vinaigrette ou mayonnaise | F32: Pot au feu | G32: Pot-au-feu | J32: Dessert
A33: semaine 3 | B33: Mardi | C33: Soir | D33: Potage de Légumes | E33: Potage de légumes | F33: Pâtess Bolognaise | G33: Pâtes bolognaise | J33: Fruit
A34: semaine 3 | B34: Mercredi | C34: Midi | D34: Feuilleté | E34: Feuilleté | F34: Sûprèmes de Volaille | G34: Suprême de volaille | H34: Petit Pois | I34: Petits pois | J34: Fruit
A35: semaine 3 | B35: Mercredi | C35: Soir | D35: Taboulé | E35: Taboulé | F35: Langue de Bœuf Sauce Piquante | G35: Langue de bœuf sauce piquante | H35: Côtes de Blette | I35: Côtes de blettes | J35: Fruit
A36: semaine 3 | B36: Jeudi | C36: Midi | D36: Salade d'Endives | E36: Salade d'endives | F36: Choucroute | G36: Choucroute garnie | J36: Fruit
A37: semaine 3 | B37: Jeudi | C37: Soir | D37: Potage de Féculents | E37: Potage de féculents | F37: Mortadelle | G37: Mortadelle | H37: Carottes Persillées | I37: Carottes Vichy | J37: Fruit
A38: semaine 3 | B38: Vendredi | C38: Midi | D38: Salade Mexicaine | E38: Salade mexicaine | F38: Gratin de poisson | G38: Gratin de poisson | H38: Haricots vert | I38: Haricots verts | J38: Fruit
A39: semaine 3 | B39: Vendredi | C39: Soir | D39: Salade verte | E39: Salade verte | F39: Quiche | G39: Quiche lorraine | H39: Pâtess | I39: Pâtes au beurre | J39: Fruit
A40: semaine 3 | B40: Samedi | C40: Midi | D40: Pamplemousse | E40: Pamplemousse | F40: Escalope de Veau | G40: Escalope de veau | H40: Pomme de Terre boulangère | I40: Pommes de terre boulangère | J40: Fruit
A41: semaine 3 | B41: Samedi | C41: Soir | D41: Potage de Légumes | E41: Potage de légumes | F41: Nugget's poulet | G41: Nuggets de poulet | H41: Salsifis | I41: Salsifis | J41: Fruit
A42: semaine 3 | B42: Dimanche | C42: Midi | D42: Salade verte | E42: Salade verte | F42: Paupiette de Volaille | G42: Paupiette de volaille | H42: Riz | I42: Riz pilaf | J42: Dessert
A43: semaine 3 | B43: Dimanche | C43: Soir | D43: Betteraves | E43: Betteraves vinaigrette | F43: Jambon Blanc | G43: Jambon blanc | H43: Pomme de terre Duchesse | I43: Pommes duchesse | J43: Fruit
A44: semaine 4 | B44: Lundi | C44: Midi | D44: Feuilleté | E44: Feuilleté | F44: Escalope de Porc | G44: Escalope de porc | H44: Petit Pois/Carotte | I44: Petits pois carottes | J44: Fruit
A45: semaine 4 | B45: Lundi | C45: Soir | D45: Salade Verte | E45: Salade verte | F45: omelette | G45: Omelette | H45: Pomme de terre sautées | I45: Pommes de terre rissolées | J45: Fruit
A46: semaine 4 | B46: Mardi | C46: Midi | D46: Salade de Chou Chinois | E46: Salade de chou chinois | F46: Steack de bœuf | G46: Steak de bœuf | H46: Gratin dauphinois | I46: Gratin dauphinois | J46: Dessert
A47: semaine 4 | B47: Mardi | C47: Soir | D47: Potage de Légumes | E47: Potage de légumes | F47: roti de dinde | G47: Rôti de dinde | H47: Riz | I47: Riz pilaf | J47: Fruit
A48: semaine 4 | B48: Mercredi | C48: Midi | D48: Avocat | E48: Avocat vinaigrette ou mayonnaise | F48: Tripoux | G48: Tripoux | H48: Semoule | I48: Semoule | J48: Fruit
A49: semaine 4 | B49: Mercredi | C49: Soir | D49: Salade de pois chiche | E49: Salade de pois chiches | F49: Pizza | G49: Pizza | H49: Salade Verte | I49: Salade verte | J49: Fruit
A50: semaine 4 | B50: Jeudi | C50: Midi | D50: Salade de Riz | E50: Salade de riz | F50: Chou Farçi | G50: Chou farci | J50: Fruit
A51: semaine 4 | B51: Jeudi | C51: Soir | D51: Potage de legumes | E51: Potage de légumes | F51: Hachis Parmentier | G51: Hachis parmentier | J51: Fruit
A52: semaine 4 | B52: Vendredi | C52: Midi | D52: rosette | E52: Rosette | F52: Dos de Cabillaud | G52: Dos de cabillaud | H52: Fondue de Poireaux | I52: Fondue de poireaux | J52: Fruit
A53: semaine 4 | B53: Vendredi | C53: Soir | D53: Salade d'Endives | E53: Salade d'endives | F53: boulettes | G53: Boulettes de bœuf sauce tomate | H53: perles | I53: Perles | J53: Fruit
A54: semaine 4 | B54: Samedi | C54: Midi | D54: celeri rémoulade | E54: Céleri rémoulade | F54: Navarin | G54: Navarin d'agneau | H54: Flageolets | I54: Flageolets | J54: Fruit
A55: semaine 4 | B55: Samedi | C55: Soir | D55: Potage de Légumes | E55: Potage de légumes | F55: Paté de campagne | G55: Pâté de campagne | H55: Brocolis | I55: Brocolis | J55: Fruit
A56: semaine 4 | B56: Dimanche | C56: Midi | D56: feuilleté | E56: Feuilleté | F56: cuisse de poulet | G56: Cuisse de poulet rôtie | H56: haricots vert | I56: Haricots verts | J56: Dessert
A57: semaine 4 | B57: Dimanche | C57: Soir | D57: salade chou fleur | E57: Salade de chou-fleur | F57: Dos de colin Bordelaise | G57: Dos de colin bordelaise | H57: pomme dauphine | I57: Pommes dauphine | J57: Fruit
A58: semaine 5 | B58: Lundi | C58: Midi | D58: Pâté en Croûte | E58: Pâté en croûte | F58: Rôti de Veau | G58: Rôti de veau | H58: Chou de Bruxelles | I58: Choux de Bruxelles | J58: Fruit
A59: semaine 5 | B59: Lundi | C59: Soir | D59: Poireaux en Vinaigrette | E59: Poireaux vinaigrette | F59: Poisson Pané | G59: Poisson pané | H59: Pomme de Terre Rissolées | I59: Pommes de terre rissolées | J59: Fruit
A60: semaine 5 | B60: Mardi | C60: Midi | D60: Salade Verte | E60: Salade verte | F60: Hamburger | G60: Hamburger | H60: Frites | I60: Frites | J60: Dessert
A61: semaine 5 | B61: Mardi | C61: Soir | D61: Potage de Légumes | E61: Potage de légumes | F61: Aiguillettes de Poulet aux Cèpes | G61: Aiguillettes de poulet aux cèpes | H61: Carottes | I61: Carottes Vichy | J61: Fruit
A62: semaine 5 | B62: Mercredi | C62: Midi | D62: Pizza | E62: Pizza | F62: poisson | G62: Pavé de poisson sauce beurre blanc | H62: haricots Plat | I62: Haricots plats | J62: Fruit
A63: semaine 5 | B63: Mercredi | C63: Soir | D63: Salade de Lentilles | E63: Salade de lentilles | F63: Boudin Noir | G63: Boudin noir aux pommes | H63: Pommes Caramélisées | I63: Pommes caramélisées | J63: Fruit
A64: semaine 5 | B64: Jeudi | C64: Midi | D64: Salade d'Endives | E64: Salade d'endives | F64: Cassoulet | G64: Cassoulet | J64: Fruit
A65: semaine 5 | B65: Jeudi | C65: Soir | D65: Potage de Féculents | E65: Potage de féculents | F65: Epinards Florentine | G65: Œufs à la florentine | J65: Fruit
A66: semaine 5 | B66: Vendredi | C66: Midi | D66: Salade Haricots Beurre | E66: Salade de haricots beurre | F66: Parmentier de poisson | G66: Parmentier de poisson | J66: Fruit
A67: semaine 5 | B67: Vendredi | C67: Soir | D67: Salade Verte | E67: Salade verte | F67: flammenkueche | G67: Flammekueche | H67: macédoine | I67: Macédoine de légumes au beurre | J67: Fruit
A68: semaine 5 | B68: Samedi | C68: Midi | D68: Terrine de Campagne | E68: Pâté de campagne | F68: Sauté de Dinde | G68: Sauté de volaille | H68: Petit Pois | I68: Petits pois | J68: Fruit
A69: semaine 5 | B69: Samedi | C69: Soir | D69: Potage de Légumes | E69: Potage de légumes | F69: jambonnette | G69: Jambonnette de volaille | H69: Rostis | I69: Rösti | J69: Fruit
A70: semaine 5 | B70: Dimanche | C70: Midi | D70: Salade de Betteraves | E70: Betteraves vinaigrette | F70: Rosbeef | G70: Rôti de bœuf | H70: Riz | I70: Riz pilaf | J70: Dessert
A71: semaine 5 | B71: Dimanche | C71: Soir | D71: Salade Coleslow | E71: Coleslaw | F71: Pâtess au chorizo | G71: Pâtes au chorizo | J71: Fruit
A72: semaine 6 | B72: Lundi | C72: Midi | D72: Taboulé | E72: Taboulé | F72: Paupiette de Volaille | G72: Paupiette de volaille | H72: Gratin de Chou Fleur | I72: Gratin de chou-fleur | J72: Fruit
A73: semaine 6 | B73: Lundi | C73: Soir | D73: Salade d'Endives | E73: Salade d'endives | F73: Jambon Blanc | G73: Jambon blanc | H73: Pomme de Terre Rissolées | I73: Pommes de terre rissolées | J73: Fruit
A74: semaine 6 | B74: Mardi | C74: Midi | D74: Salade verte | E74: Salade verte | F74: crêpe salé | G74: Crêpe salée jambon fromage | J74: Crêpe sucré | K74: Crêpes sucrées
A75: semaine 6 | B75: Mardi | C75: Soir | D75: Potage de Légumes | E75: Potage de légumes | F75: Œuf Mayonnaise | G75: Œuf mayonnaise | H75: Salsifis | I75: Salsifis | J75: Fruit
A76: semaine 6 | B76: Mercredi | C76: Midi | D76: Salade de Lentilles | E76: Salade de lentilles | F76: Sauté de Veau | G76: Sauté de veau | H76: Haricot Vert | I76: Haricots verts | J76: Fruit
A77: semaine 6 | B77: Mercredi | C77: Soir | D77: Salade de Betteraves | E77: Betteraves vinaigrette | F77: Andouillette | G77: Andouillette | H77: Pâtess | I77: Pâtes au beurre | J77: Fruit
A78: semaine 6 | B78: Jeudi | C78: Midi | D78: Paté aux olives | E78: Pâté aux olives | F78: tête de veau | G78: Tête de veau sauce gribiche | H78: P De Terre vapeur | I78: Pommes de terre vapeur | J78: Fruit
A79: semaine 6 | B79: Jeudi | C79: Soir | D79: Potage de Féculents | E79: Potage de féculents | F79: Cordon Bleu | G79: Cordon bleu | H79: Chou Brocolis | I79: Brocolis | J79: Fruit
A80: semaine 6 | B80: Vendredi | C80: Midi | D80: Avocat | E80: Avocat vinaigrette ou mayonnaise | F80: Pavé de Poisson | G80: Pavé de poisson sauce beurre blanc | H80: Riz | I80: Riz pilaf | J80: Fruit
A81: semaine 6 | B81: Vendredi | C81: Soir | D81: Terrine de Légumes | E81: Terrine de légumes | F81: Quenelle de Volailles | G81: Quenelles de volaille sauce | H81: carottes | I81: Carottes Vichy | J81: Fruit
A82: semaine 6 | B82: Samedi | C82: Midi | D82: Salade de Pâtess | E82: Salade de pâtes | F82: roti de Porc | G82: Rôti de porc | H82: Chou romanesco | I82: Chou romanesco | J82: Fruit
A83: semaine 6 | B83: Samedi | C83: Soir | D83: Potage de Légumes | E83: Potage de légumes | F83: Lasagne au Bœuf | G83: Lasagnes au bœuf | J83: Fruit
A84: semaine 6 | B84: Dimanche | C84: Midi | D84: salade verte | E84: Salade verte | F84: Daube | G84: Daube de bœuf | H84: semoule | I84: Semoule | J84: Dessert
A85: semaine 6 | B85: Dimanche | C85: Soir | D85: Carottes Rapées | E85: Carottes râpées | F85: Dos de Colin Meunière | G85: Dos de colin meunière | H85: Rapé de Pomme de Terre | I85: Râpé de pommes de terre | J85: Fruit
A86: semaine 7 | B86: Lundi | C86: Midi | D86: Salade verte | E86: Salade verte | F86: Sauté de Lapin | G86: Sauté de lapin | H86: Choux de Bruxelles | I86: Choux de Bruxelles | J86: Fruit
A87: semaine 7 | B87: Lundi | C87: Soir | D87: Salade de Perles | E87: Salade de perles | F87: Endives au Jambon | G87: Endives au jambon | J87: Fruit
A88: semaine 7 | B88: Mardi | C88: Midi | D88: Salade Coleslow | E88: Coleslaw | F88: Croziflette | G88: Croziflette | J88: Dessert
A89: semaine 7 | B89: Mardi | C89: Soir | D89: Potage de Légumes | E89: Potage de légumes | F89: Chipolatas | G89: Chipolatas | H89: Haricots blanc | I89: Haricots blancs | J89: Fruit
A90: semaine 7 | B90: Mercredi | C90: Midi | D90: Taboulé | E90: Taboulé | F90: Escalope dinde | G90: Escalope de dinde | H90: gratin de potimarron | I90: Gratin de potimarron | J90: Fruit
A91: semaine 7 | B91: Mercredi | C91: Soir | D91: Macédoine de Légumes | E91: Macédoine mayonnaise | F91: Raviolis | G91: Raviolis | J91: Fruit
A92: semaine 7 | B92: Jeudi | C92: Midi | D92: Salade de Chou Chinois | E92: Salade de chou chinois | F92: Saucisse | G92: Saucisse de Toulouse | H92: Aligot | I92: Aligot | J92: Fruit
A93: semaine 7 | B93: Jeudi | C93: Soir | D93: Potage de Féculents | E93: Potage de féculents | F93: Œuf béchamel | G93: Œufs durs sauce béchamel | H93: Haricots beurre | I93: Haricots beurre | J93: Fruit
A94: semaine 7 | B94: Vendredi | C94: Midi | D94: Mousse de Canard | E94: Mousse de canard | F94: Saumon | G94: Pavé de saumon | H94: Chou Romanesco | I94: Chou romanesco | J94: Fruit
A95: semaine 7 | B95: Vendredi | C95: Soir | D95: Salade d'endives | E95: Salade d'endives | F95: Chili con carne | G95: Chili con carne | J95: Fruit
A96: semaine 7 | B96: Samedi | C96: Midi | D96: Carottes Rapées | E96: Carottes râpées | F96: Flecque | G96: Flammekueche | J96: Fruit
A97: semaine 7 | B97: Samedi | C97: Soir | D97: Potage de Légumes | E97: Potage de légumes | F97: Pates Carbonara | G97: Pâtes carbonara | J97: Fruit
A98: semaine 7 | B98: Dimanche | C98: Midi | D98: Salade verte | E98: Salade verte | F98: Rôti de Veau | G98: Rôti de veau | H98: Lentilles | I98: Lentilles | J98: Dessert
A99: semaine 7 | B99: Dimanche | C99: Soir | D99: Salade de Riz | E99: Salade de riz | F99: maquereaux | G99: Maquereaux à la moutarde | H99: Poelée de légumes | I99: Poêlée de légumes | J99: Fruit
A100: semaine 8 | B100: Lundi | C100: Midi | D100: Tranche de Jambon Cru | E100: Jambon cru | F100: Pavé de Poisson | G100: Pavé de poisson sauce beurre blanc | H100: Epinards à la crème | I100: Épinards à la crème | J100: Fruit
...

Sheet T° cuisson de nuit
A1: Cuisson longues (12H00 à 18H00)
A2: Vapeur ou thermoplongeur
B3: Produits | C3: Remarques
A4: 95°C | B4: Agrumes | C4: Sirop à 15 (1kg de sucre pour 0,5L eau) - Temps de cuisson des agrumes sous vide 5H00 minimum à 18H00
B5: Légumineuses
A6: 88°C | B6: Tête de veau
B7: Langue de Bœuf
B8: Pied de porc - veau
A9: 85°C | B9: Sauté de bœuf
B10: Sauté de mouton
B11: Ratatouille
B12: Legumes tajine
B13: Aubergines
B14: Cuisse de poule
B15: Paleron de bœuf
A16: 74°C | B16: Osso Bucco
B17: Blanquette de veau | C17: Débuter la cuisson à 85°C pendant 2H00
A18: 72°C | B18: Souris d'agneau | C18: Possibilité à 68°C
B19: Cuisses de canard entière | C19: Possibilité à 68°C
B20: Sauté d'agneau
A21: 70C | B21: Paleron de veau
A22: 65°C | B22: Rôti de veau bas carré
B23: Echine de porc | C23: Débuter cuisson par un pic (80°C ambiance -72°C à cœur)
A24: 62°C | B24: Ballotines de canard
B25: Ballotines épaules d'agneau | C25: A 65°C si un peu ferme

Sheet E-Salade verte
A1: Salade verte | E1: VP Théorique minimum | G1: Préparation froide Bac gastro + film, 0/+3°C Vinaigrette à part
E2: Liaison froide 0/+3°C
A3: Produits | B3: Qté recette base | C3: Qté production | D3: U | E3: PU | F3: Total €
A4: Salade verte (batavia, laitue ou frisée) | B4: 4.66 | C4: =B4/B$22*B$24 -> 7.3215497 | D4: Kg | E4: =IFERROR(INDEX(Correspondance!$D$2:$D$3000,MATCH(A4,Correspondance!$A$2:$A$3000,0)),0) -> 5.5 | F4: =C4*E4 -> 40.268523 | G4: Mode opératoire : Effeuiller et parer les salades, éliminer les feuilles abîmées et le trognon Décontamination : trempage 5 min en eau + désinfectant agréé, rinçage abondant à l'eau claire Essorer soigneusement, couper grossièrement Vinaigrette : délayer moutarde, sel, poivre, vinaigre, monter à l'huile, ajouter échalotes et ciboulette Conditionner la salade en bacs gastro filmés, vinaigrette à part en pot fermé Stocker à 0/+3°C, assaisonner au dernier moment au service Service en liaison froide, consommation dans les 24h
A5: Huile de tournesol | B5: 0.559 | C5: =B5/B$22*B$24 -> 0.87827174 | D5: L | E5: =IFERROR(INDEX(Correspondance!$D$2:$D$3000,MATCH(A5,Correspondance!$A$2:$A$3000,0)),0) -> 2.2 | F5: =C5*E5 -> 1.9321978
A6: Vinaigre de vin | B6: 0.186 | C6: =B6/B$22*B$24 -> 0.29223353 | D6: L | E6: =IFERROR(INDEX(Correspondance!$D$2:$D$3000,MATCH(A6,Correspondance!$A$2:$A$3000,0)),0) -> 1.5 | F6: =C6*E6 -> 0.43835029
A7: Moutarde de Dijon | B7: 0.075 | C7: =B7/B$22*B$24 -> 0.1178361 | D7: Kg | E7: =IFERROR(INDEX(Correspondance!$D$2:$D$3000,MATCH(A7,Correspondance!$A$2:$A$3000,0)),0) -> 9 | F7: =C7*E7 -> 1.0605249
A8: Échalotes ciselées surgelées | B8: 0.093 | C8: =B8/B$22*B$24 -> 0.14611676 | D8: Kg | E8: =IFERROR(INDEX(Correspondance!$D$2:$D$3000,MATCH(A8,Correspondance!$A$2:$A$3000,0)),0) -> 4.5 | F8: =C8*E8 -> 0.65752544
A9: Sel fin | B9: 0.028 | C9: =B9/B$22*B$24 -> 0.043992144 | D9: Kg | E9: =IFERROR(INDEX(Correspondance!$D$2:$D$3000,MATCH(A9,Correspondance!$A$2:$A$3000,0)),0) -> 2 | F9: =C9*E9 -> 0.087984289
A10: Poivre PM | C10: =B10/B$22*B$24 -> 0 | D10: Kg | E10: =IFERROR(INDEX(Correspondance!$D$2:$D$3000,MATCH(A10,Correspondance!$A$2:$A$3000,0)),0) -> 18 | F10: =C10*E10 -> 0
A11: Ciboulette ciselée PM | C11: =B11/B$22*B$24 -> 0 | D11: Kg | E11: =IFERROR(INDEX(Correspondance!$D$2:$D$3000,MATCH(A11,Correspondance!$A$2:$A$3000,0)),0) -> 13 | F11: =C11*E11 -> 0
C12: =B12/B$22*B$24 -> 0 | E12: =IFERROR(INDEX(Correspondance!$D$2:$D$3000,MATCH(A12,Correspondance!$A$2:$A$3000,0)),0) -> 0 | F12: =C12*E12 -> 0
C13: =B13/B$22*B$24 -> 0 | E13: =IFERROR(INDEX(Correspondance!$D$2:$D$3000,MATCH(A13,Correspondance!$A$2:$A$3000,0)),0) -> 0 | F13: =C13*E13 -> 0
C14: =B14/B$22*B$24 -> 0 | E14: =IFERROR(INDEX(Correspondance!$D$2:$D$3000,MATCH(A14,Correspondance!$A$2:$A$3000,0)),0) -> 0 | F14: =C14*E14 -> 0
C15: =B15/B$22*B$24 -> 0 | E15: =IFERROR(INDEX(Correspondance!$D$2:$D$3000,MATCH(A15,Correspondance!$A$2:$A$3000,0)),0) -> 0 | F15: =C15*E15 -> 0
C16: =B16/B$22*B$24 -> 0 | E16: =IFERROR(INDEX(Correspondance!$D$2:$D$3000,MATCH(A16,Correspondance!$A$2:$A$3000,0)),0) -> 0 | F16: =C16*E16 -> 0
C17: =B17/B$22*B$24 -> 0 | E17: =IFERROR(INDEX(Correspondance!$D$2:$D$3000,MATCH(A17,Correspondance!$A$2:$A$3000,0)),0) -> 0 | F17: =C17*E17 -> 0
C18: =B18/B$22*B$24 -> 0 | E18: =IFERROR(INDEX(Correspondance!$D$2:$D$3000,MATCH(A18,Correspondance!$A$2:$A$3000,0)),0) -> 0 | F18: =C18*E18 -> 0
F19: =SUM(F4:F18) -> 44.445106
A20: Prix unitaire portion | B20: =F19/B24 -> 0.40404642
A21: Poids total ou ingrédient principal | B21: =SUM(B3:B18) -> 5.601
A22: Nombre portions recette base | B22: =B21/B23 -> 70.0125
A23: Poids net portions | B23: 0.08 | C23: Possibilité de saisir le grammage
A24: Nombre portions à produire | B24: =Paramètres!$B$5 -> 110 | C24: Effectif EHPAD + FAM (feuille Paramètres) – possibilité de saisir un autre nombre

Sheet E-Potage de légumes
A1: Potage de légumes cuisson de nuit | E1: VP Théorique minimum | G1: Cuisson 85°C four vapeur Bac gastro 1/1 avec couvercles sans trou Ou sauteuse fonction mijotage (compatible cuisson de nuit)
E2: > à 10 000
A3: Produits | B3: Qté recette base | C3: Qté production | D3: U | E3: PU | F3: Total €
A4: Poireaux rondelles surgelés | B4: 2.77 | C4: =B4/B$22*B$24 -> 4.3518624 | D4: Kg | E4: =IFERROR(INDEX(Correspondance!$D$2:$D$3000,MATCH(A4,Correspondance!$A$2:$A$3000,0)),0) -> 2.6 | F4: =C4*E4 -> 11.314842 | G4: Mode opératoire : Peser tous les ingrédients d'épicerie Répartir les légumes surgelés et les pommes de terre dans des bacs 1/1 (H15), 2 bacs maximum par recette Mouiller à l'eau, ajouter le fond de volaille, sel, poivre et le beurre, mélanger Ajouter un couvercle sans trou Cuisson : 85°C vapeur 12H00 minimum et 18H00 au maximum (programme Potage cuisson de nuit) Le lendemain : mixer finement au mixeur plongeant, ajouter la crème, rectifier l'assaisonnement Contrôle de la texture : allonger avec un peu de bouillon si nécessaire Refroidir en cellule (63°C à 10°C en moins de deux heures) pour une remise en T° différée ou maintenir en étuve ≥ 63°C pour un service en liaison chaude Sauteuse (compatible cuisson de nuit) : tous les ingrédients, couvrir, 85°C fonction mijotage 12H00 à 18H00, mixer le lendemain
A5: Pommes de terre cubes | B5: 2.77 | C5: =B5/B$22*B$24 -> 4.3518624 | D5: Kg | E5: =IFERROR(INDEX(Correspondance!$D$2:$D$3000,MATCH(A5,Correspondance!$A$2:$A$3000,0)),0) -> 2.2 | F5: =C5*E5 -> 9.5740973
A6: Carottes rondelles surgelées | B6: 1.85 | C6: =B6/B$22*B$24 -> 2.9064785 | D6: Kg | E6: =IFERROR(INDEX(Correspondance!$D$2:$D$3000,MATCH(A6,Correspondance!$A$2:$A$3000,0)),0) -> 1.8 | F6: =C6*E6 -> 5.2316613
A7: Navets cubes surgelés | B7: 0.923 | C7: =B7/B$22*B$24 -> 1.4500971 | D7: Kg | E7: =IFERROR(INDEX(Correspondance!$D$2:$D$3000,MATCH(A7,Correspondance!$A$2:$A$3000,0)),0) -> 2.2 | F7: =C7*E7 -> 3.1902137
A8: Oignons cubes surgelés | B8: 0.462 | C8: =B8/B$22*B$24 -> 0.7258341 | D8: Kg | E8: =IFERROR(INDEX(Correspondance!$D$2:$D$3000,MATCH(A8,Correspondance!$A$2:$A$3000,0)),0) -> 1.8 | F8: =C8*E8 -> 1.3065014
A9: Eau | B9: 7.39 | C9: =B9/B$22*B$24 -> 11.610203 | D9: L | E9: =IFERROR(INDEX(Correspondance!$D$2:$D$3000,MATCH(A9,Correspondance!$A$2:$A$3000,0)),0) -> 0 | F9: =C9*E9 -> 0
A10: Fond de volaille déshydraté | B10: 0.139 | C10: =B10/B$22*B$24 -> 0.21837866 | D10: Kg | E10: =IFERROR(INDEX(Correspondance!$D$2:$D$3000,MATCH(A10,Correspondance!$A$2:$A$3000,0)),0) -> 10 | F10: =C10*E10 -> 2.1837866
A11: Sel | B11: 0.092 | C11: =B11/B$22*B$24 -> 0.14453839 | D11: Kg | E11: =IFERROR(INDEX(Correspondance!$D$2:$D$3000,MATCH(A11,Correspondance!$A$2:$A$3000,0)),0) -> 2 | F11: =C11*E11 -> 0.28907678
A12: Poivre PM | C12: =B12/B$22*B$24 -> 0 | D12: Kg | E12: =IFERROR(INDEX(Correspondance!$D$2:$D$3000,MATCH(A12,Correspondance!$A$2:$A$3000,0)),0) -> 18 | F12: =C12*E12 -> 0
A13: Beurre | B13: 0.185 | C13: =B13/B$22*B$24 -> 0.29064785 | D13: Kg | E13: =IFERROR(INDEX(Correspondance!$D$2:$D$3000,MATCH(A13,Correspondance!$A$2:$A$3000,0)),0) -> 9 | F13: =C13*E13 -> 2.6158307
A14: Crème 35% | B14: 0.923 | C14: =B14/B$22*B$24 -> 1.4500971 | D14: L | E14: =IFERROR(INDEX(Correspondance!$D$2:$D$3000,MATCH(A14,Correspondance!$A$2:$A$3000,0)),0) -> 5.5 | F14: =C14*E14 -> 7.9755342
C15: =B15/B$22*B$24 -> 0 | E15: =IFERROR(INDEX(Correspondance!$D$2:$D$3000,MATCH(A15,Correspondance!$A$2:$A$3000,0)),0) -> 0 | F15: =C15*E15 -> 0
C16: =B16/B$22*B$24 -> 0 | E16: =IFERROR(INDEX(Correspondance!$D$2:$D$3000,MATCH(A16,Correspondance!$A$2:$A$3000,0)),0) -> 0 | F16: =C16*E16 -> 0
C17: =B17/B$22*B$24 -> 0 | E17: =IFERROR(INDEX(Correspondance!$D$2:$D$3000,MATCH(A17,Correspondance!$A$2:$A$3000,0)),0) -> 0 | F17: =C17*E17 -> 0
C18: =B18/B$22*B$24 -> 0 | E18: =IFERROR(INDEX(Correspondance!$D$2:$D$3000,MATCH(A18,Correspondance!$A$2:$A$3000,0)),0) -> 0 | F18: =C18*E18 -> 0
F19: =SUM(F4:F18) -> 43.681544
A20: Prix unitaire portion | B20: =F19/B24 -> 0.39710495
A21: Poids total ou ingrédient principal | B21: =SUM(B3:B18) -> 17.504
A22: Nombre portions recette base | B22: =B21/B23 -> 70.016
A23: Poids net portions | B23: 0.25 | C23: Possibilité de saisir le grammage
A24: Nombre portions à produire | B24: =Paramètres!$B$5 -> 110 | C24: Effectif EHPAD + FAM (feuille Paramètres) – possibilité de saisir un autre nombre

Sheet E-Potage de féculents
A1: Potage de féculents cuisson de nuit | E1: VP Théorique minimum | G1: Cuisson 95°C four vapeur Bac gastro 1/1 avec couvercles sans trou Ou sauteuse fonction mijotage (compatible cuisson de nuit)
E2: > à 10 000
A3: Produits | B3: Qté recette base | C3: Qté production | D3: U | E3: PU | F3: Total €
A4: Pois cassés secs | B4: 1.48 | C4: =B4/B$22*B$24 -> 2.3255814 | D4: Kg | E4: =IFERROR(INDEX(Correspondance!$D$2:$D$3000,MATCH(A4,Correspondance!$A$2:$A$3000,0)),0) -> 2.8 | F4: =C4*E4 -> 6.5116279 | G4: Mode opératoire : Peser tous les ingrédients d'épicerie, rincer les pois cassés Dans des bacs 1/1 (H15) mettre pois cassés, pommes de terre, légumes, lardons, aromates Mouiller à l'eau, ajouter le fond de volaille et le sel, mélanger Ajouter un couvercle sans trou Cuisson : 95°C vapeur 12H00 minimum et 18H00 au maximum Le lendemain : retirer le laurier et le thym, mixer finement, passer au chinois si besoin Ajouter la crème, rectifier sel et poivre, allonger au bouillon selon la texture souhaitée Refroidir en cellule (63°C à 10°C en moins de deux heures) pour une remise en T° différée ou maintenir en étuve ≥ 63°C pour un service en liaison chaude Sauteuse (compatible cuisson de nuit) : tous les ingrédients, couvrir, 95°C fonction mijotage 12H00 à 18H00, mixer le lendemain
A5: Pommes de terre cubes | B5: 1.97 | C5: =B5/B$22*B$24 -> 3.0955374 | D5: Kg | E5: =IFERROR(INDEX(Correspondance!$D$2:$D$3000,MATCH(A5,Correspondance!$A$2:$A$3000,0)),0) -> 2.2 | F5: =C5*E5 -> 6.8101823
A6: Carottes rondelles surgelées | B6: 0.986 | C6: =B6/B$22*B$24 -> 1.54934 | D6: Kg | E6: =IFERROR(INDEX(Correspondance!$D$2:$D$3000,MATCH(A6,Correspondance!$A$2:$A$3000,0)),0) -> 1.8 | F6: =C6*E6 -> 2.7888121
A7: Poireaux rondelles surgelés | B7: 0.986 | C7: =B7/B$22*B$24 -> 1.54934 | D7: Kg | E7: =IFERROR(INDEX(Correspondance!$D$2:$D$3000,MATCH(A7,Correspondance!$A$2:$A$3000,0)),0) -> 2.6 | F7: =C7*E7 -> 4.0282841
A8: Oignons cubes surgelés | B8: 0.493 | C8: =B8/B$22*B$24 -> 0.77467002 | D8: Kg | E8: =IFERROR(INDEX(Correspondance!$D$2:$D$3000,MATCH(A8,Correspondance!$A$2:$A$3000,0)),0) -> 1.8 | F8: =C8*E8 -> 1.394406
A9: Lardons fumés (facultatif) | B9: 0.493 | C9: =B9/B$22*B$24 -> 0.77467002 | D9: Kg | E9: =IFERROR(INDEX(Correspondance!$D$2:$D$3000,MATCH(A9,Correspondance!$A$2:$A$3000,0)),0) -> 8 | F9: =C9*E9 -> 6.1973602
A10: Eau | B10: 9.86 | C10: =B10/B$22*B$24 -> 15.4934 | D10: L | E10: =IFERROR(INDEX(Correspondance!$D$2:$D$3000,MATCH(A10,Correspondance!$A$2:$A$3000,0)),0) -> 0 | F10: =C10*E10 -> 0
A11: Fond de volaille déshydraté | B11: 0.148 | C11: =B11/B$22*B$24 -> 0.23255814 | D11: Kg | E11: =IFERROR(INDEX(Correspondance!$D$2:$D$3000,MATCH(A11,Correspondance!$A$2:$A$3000,0)),0) -> 10 | F11: =C11*E11 -> 2.3255814
A12: Sel | B12: 0.099 | C12: =B12/B$22*B$24 -> 0.15556254 | D12: Kg | E12: =IFERROR(INDEX(Correspondance!$D$2:$D$3000,MATCH(A12,Correspondance!$A$2:$A$3000,0)),0) -> 2 | F12: =C12*E12 -> 0.31112508
A13: Laurier - Thym PM | C13: =B13/B$22*B$24 -> 0 | D13: Kg | E13: =IFERROR(INDEX(Correspondance!$D$2:$D$3000,MATCH(A13,Correspondance!$A$2:$A$3000,0)),0) -> 16 | F13: =C13*E13 -> 0
A14: Crème 35% | B14: 0.986 | C14: =B14/B$22*B$24 -> 1.54934 | D14: L | E14: =IFERROR(INDEX(Correspondance!$D$2:$D$3000,MATCH(A14,Correspondance!$A$2:$A$3000,0)),0) -> 5.5 | F14: =C14*E14 -> 8.5213702
C15: =B15/B$22*B$24 -> 0 | E15: =IFERROR(INDEX(Correspondance!$D$2:$D$3000,MATCH(A15,Correspondance!$A$2:$A$3000,0)),0) -> 0 | F15: =C15*E15 -> 0
C16: =B16/B$22*B$24 -> 0 | E16: =IFERROR(INDEX(Correspondance!$D$2:$D$3000,MATCH(A16,Correspondance!$A$2:$A$3000,0)),0) -> 0 | F16: =C16*E16 -> 0
C17: =B17/B$22*B$24 -> 0 | E17: =IFERROR(INDEX(Correspondance!$D$2:$D$3000,MATCH(A17,Correspondance!$A$2:$A$3000,0)),0) -> 0 | F17: =C17*E17 -> 0
C18: =B18/B$22*B$24 -> 0 | E18: =IFERROR(INDEX(Correspondance!$D$2:$D$3000,MATCH(A18,Correspondance!$A$2:$A$3000,0)),0) -> 0 | F18: =C18*E18 -> 0
F19: =SUM(F4:F18) -> 38.888749
A20: Prix unitaire portion | B20: =F19/B24 -> 0.35353408
A21: Poids total ou ingrédient principal | B21: =SUM(B3:B18) -> 17.501
A22: Nombre portions recette base | B22: =B21/B23 -> 70.004
A23: Poids net portions | B23: 0.25 | C23: Possibilité de saisir le grammage
A24: Nombre portions à produire | B24: =Paramètres!$B$5 -> 110 | C24: Effectif EHPAD + FAM (feuille Paramètres) – possibilité de saisir un autre nombre

Sheet E-Taboulé
A1: Taboulé | E1: VP Théorique minimum | G1: Préparation froide Semoule hydratée à froid Bac gastro + film, 0/+3°C
E2: Liaison froide 0/+3°C
A3: Produits | B3: Qté recette base | C3: Qté production | D3: U | E3: PU | F3: Total €
A4: Semoule de blé moyenne | B4: 2.26 | C4: =B4/B$22*B$24 -> 3.5522093 | D4: Kg | E4: =IFERROR(INDEX(Correspondance!$D$2:$D$3000,MATCH(A4,Correspondance!$A$2:$A$3000,0)),0) -> 1.5 | F4: =C4*E4 -> 5.3283139 | G4: Mode opératoire : Peser tous les ingrédients d'épicerie Décontaminer et rincer tomates, concombre et menthe, tailler en petits dés Décongeler poivrons et oignons en enceinte réfrigérée la veille, bien égoutter Mélanger la semoule avec l'eau froide, le jus de citron, l'huile d'olive et le sel, laisser gonfler 30 min au froid Ajouter légumes, raisins secs, menthe et poivre, mélanger sans écraser Rectifier l'assaisonnement, laisser reposer 2 heures minimum à 0/+3°C Conditionner en bacs gastro filmés, étiqueter (date de fabrication) Service en liaison froide, consommation dans les 48h
A5: Eau froide | B5: 2.26 | C5: =B5/B$22*B$24 -> 3.5522093 | D5: L | E5: =IFERROR(INDEX(Correspondance!$D$2:$D$3000,MATCH(A5,Correspondance!$A$2:$A$3000,0)),0) -> 0 | F5: =C5*E5 -> 0
A6: Tomates en cubes | B6: 1.81 | C6: =B6/B$22*B$24 -> 2.844911 | D6: Kg | E6: =IFERROR(INDEX(Correspondance!$D$2:$D$3000,MATCH(A6,Correspondance!$A$2:$A$3000,0)),0) -> 1.5 | F6: =C6*E6 -> 4.2673665
A7: Concombre en dés | B7: 0.905 | C7: =B7/B$22*B$24 -> 1.4224555 | D7: Kg | E7: =IFERROR(INDEX(Correspondance!$D$2:$D$3000,MATCH(A7,Correspondance!$A$2:$A$3000,0)),0) -> 2.25 | F7: =C7*E7 -> 3.2005248
A8: Poivrons dés surgelés | B8: 0.452 | C8: =B8/B$22*B$24 -> 0.71044186 | D8: Kg | E8: =IFERROR(INDEX(Correspondance!$D$2:$D$3000,MATCH(A8,Correspondance!$A$2:$A$3000,0)),0) -> 3 | F8: =C8*E8 -> 2.1313256
A9: Oignons cubes surgelés | B9: 0.271 | C9: =B9/B$22*B$24 -> 0.42595076 | D9: Kg | E9: =IFERROR(INDEX(Correspondance!$D$2:$D$3000,MATCH(A9,Correspondance!$A$2:$A$3000,0)),0) -> 1.8 | F9: =C9*E9 -> 0.76671137
A10: Raisins secs | B10: 0.181 | C10: =B10/B$22*B$24 -> 0.2844911 | D10: Kg | E10: =IFERROR(INDEX(Correspondance!$D$2:$D$3000,MATCH(A10,Correspondance!$A$2:$A$3000,0)),0) -> 5 | F10: =C10*E10 -> 1.4224555
A11: Huile d'olive | B11: 0.543 | C11: =B11/B$22*B$24 -> 0.85347329 | D11: L | E11: =IFERROR(INDEX(Correspondance!$D$2:$D$3000,MATCH(A11,Correspondance!$A$2:$A$3000,0)),0) -> 7.5 | F11: =C11*E11 -> 6.4010497
A12: Jus de citron | B12: 0.362 | C12: =B12/B$22*B$24 -> 0.56898219 | D12: L | E12: =IFERROR(INDEX(Correspondance!$D$2:$D$3000,MATCH(A12,Correspondance!$A$2:$A$3000,0)),0) -> 2.5 | F12: =C12*E12 -> 1.4224555
A13: Sel | B13: 0.054 | C13: =B13/B$22*B$24 -> 0.084875797 | D13: Kg | E13: =IFERROR(INDEX(Correspondance!$D$2:$D$3000,MATCH(A13,Correspondance!$A$2:$A$3000,0)),0) -> 2 | F13: =C13*E13 -> 0.16975159
A14: Poivre PM | C14: =B14/B$22*B$24 -> 0 | D14: Kg | E14: =IFERROR(INDEX(Correspondance!$D$2:$D$3000,MATCH(A14,Correspondance!$A$2:$A$3000,0)),0) -> 18 | F14: =C14*E14 -> 0
A15: Menthe fraîche ciselée PM | C15: =B15/B$22*B$24 -> 0 | D15: Kg | E15: =IFERROR(INDEX(Correspondance!$D$2:$D$3000,MATCH(A15,Correspondance!$A$2:$A$3000,0)),0) -> 30 | F15: =C15*E15 -> 0
C16: =B16/B$22*B$24 -> 0 | E16: =IFERROR(INDEX(Correspondance!$D$2:$D$3000,MATCH(A16,Correspondance!$A$2:$A$3000,0)),0) -> 0 | F16: =C16*E16 -> 0
C17: =B17/B$22*B$24 -> 0 | E17: =IFERROR(INDEX(Correspondance!$D$2:$D$3000,MATCH(A17,Correspondance!$A$2:$A$3000,0)),0) -> 0 | F17: =C17*E17 -> 0
C18: =B18/B$22*B$24 -> 0 | E18: =IFERROR(INDEX(Correspondance!$D$2:$D$3000,MATCH(A18,Correspondance!$A$2:$A$3000,0)),0) -> 0 | F18: =C18*E18 -> 0
F19: =SUM(F4:F18) -> 25.109954
A20: Prix unitaire portion | B20: =F19/B24 -> 0.22827231
A21: Poids total ou ingrédient principal | B21: =SUM(B3:B18) -> 9.098
A22: Nombre portions recette base | B22: =B21/B23 -> 69.984615
A23: Poids net portions | B23: 0.13 | C23: Possibilité de saisir le grammage
A24: Nombre portions à produire | B24: =Paramètres!$B$5 -> 110 | C24: Effectif EHPAD + FAM (feuille Paramètres) – possibilité de saisir un autre nombre

Sheet E-Feuilleté
A1: Feuilleté | E1: VP Théorique minimum | G1: Four mixte 180°C chaleur sèche Plaques gastro + papier cuisson 15 à 20 min
E2: 63°C à cœur
A3: Produits | B3: Qté recette base | C3: Qté production | D3: U | E3: PU | F3: Total €
A4: Feuilletés jambon fromage surgelés (90 g pièce) | B4: 5.73 | C4: =B4/B$22*B$24 -> 9.0042857 | D4: Kg | E4: =IFERROR(INDEX(Correspondance!$D$2:$D$3000,MATCH(A4,Correspondance!$A$2:$A$3000,0)),0) -> 8.33 | F4: =C4*E4 -> 75.0057 | G4: Mode opératoire : Disposer les feuilletés surgelés sans décongélation sur plaques gastro recouvertes de papier cuisson, espacer Dorer au jaune d'œuf pasteurisé Four mixte 180°C chaleur sèche 15 à 20 min jusqu'à belle coloration Contrôle 63°C à cœur minimum, enregistrer la T° Maintenir en étuve ≥ 63°C jusqu'au service (30 min maximum pour garder le croustillant) Salade : décontaminer, rincer, essorer, préparer la vinaigrette Dressage : 1 feuilleté par personne sur lit de salade assaisonnée au dernier moment En remise en T° différée : refroidir en cellule puis régénérer 180°C 8 min, 63°C à cœur
A5: Salade frisée | B5: 1.37 | C5: =B5/B$22*B$24 -> 2.1528571 | D5: Kg | E5: =IFERROR(INDEX(Correspondance!$D$2:$D$3000,MATCH(A5,Correspondance!$A$2:$A$3000,0)),0) -> 3.6 | F5: =C5*E5 -> 7.7502857
A6: Huile de tournesol | B6: 0.273 | C6: =B6/B$22*B$24 -> 0.429 | D6: L | E6: =IFERROR(INDEX(Correspondance!$D$2:$D$3000,MATCH(A6,Correspondance!$A$2:$A$3000,0)),0) -> 2.2 | F6: =C6*E6 -> 0.9438
A7: Vinaigre de vin | B7: 0.091 | C7: =B7/B$22*B$24 -> 0.143 | D7: L | E7: =IFERROR(INDEX(Correspondance!$D$2:$D$3000,MATCH(A7,Correspondance!$A$2:$A$3000,0)),0) -> 1.5 | F7: =C7*E7 -> 0.2145
A8: Moutarde | B8: 0.036 | C8: =B8/B$22*B$24 -> 0.056571429 | D8: Kg | E8: =IFERROR(INDEX(Correspondance!$D$2:$D$3000,MATCH(A8,Correspondance!$A$2:$A$3000,0)),0) -> 9 | F8: =C8*E8 -> 0.50914286
A9: Sel | B9: 0.018 | C9: =B9/B$22*B$24 -> 0.028285714 | D9: Kg | E9: =IFERROR(INDEX(Correspondance!$D$2:$D$3000,MATCH(A9,Correspondance!$A$2:$A$3000,0)),0) -> 2 | F9: =C9*E9 -> 0.056571429
A10: Poivre PM | C10: =B10/B$22*B$24 -> 0 | D10: Kg | E10: =IFERROR(INDEX(Correspondance!$D$2:$D$3000,MATCH(A10,Correspondance!$A$2:$A$3000,0)),0) -> 18 | F10: =C10*E10 -> 0
A11: Jaune d'œuf pasteurisé (dorure) | B11: 0.182 | C11: =B11/B$22*B$24 -> 0.286 | D11: L | E11: =IFERROR(INDEX(Correspondance!$D$2:$D$3000,MATCH(A11,Correspondance!$A$2:$A$3000,0)),0) -> 6.5 | F11: =C11*E11 -> 1.859
C12: =B12/B$22*B$24 -> 0 | E12: =IFERROR(INDEX(Correspondance!$D$2:$D$3000,MATCH(A12,Correspondance!$A$2:$A$3000,0)),0) -> 0 | F12: =C12*E12 -> 0
C13: =B13/B$22*B$24 -> 0 | E13: =IFERROR(INDEX(Correspondance!$D$2:$D$3000,MATCH(A13,Correspondance!$A$2:$A$3000,0)),0) -> 0 | F13: =C13*E13 -> 0
C14: =B14/B$22*B$24 -> 0 | E14: =IFERROR(INDEX(Correspondance!$D$2:$D$3000,MATCH(A14,Correspondance!$A$2:$A$3000,0)),0) -> 0 | F14: =C14*E14 -> 0
C15: =B15/B$22*B$24 -> 0 | E15: =IFERROR(INDEX(Correspondance!$D$2:$D$3000,MATCH(A15,Correspondance!$A$2:$A$3000,0)),0) -> 0 | F15: =C15*E15 -> 0
C16: =B16/B$22*B$24 -> 0 | E16: =IFERROR(INDEX(Correspondance!$D$2:$D$3000,MATCH(A16,Correspondance!$A$2:$A$3000,0)),0) -> 0 | F16: =C16*E16 -> 0
C17: =B17/B$22*B$24 -> 0 | E17: =IFERROR(INDEX(Correspondance!$D$2:$D$3000,MATCH(A17,Correspondance!$A$2:$A$3000,0)),0) -> 0 | F17: =C17*E17 -> 0
C18: =B18/B$22*B$24 -> 0 | E18: =IFERROR(INDEX(Correspondance!$D$2:$D$3000,MATCH(A18,Correspondance!$A$2:$A$3000,0)),0) -> 0 | F18: =C18*E18 -> 0
F19: =SUM(F4:F18) -> 86.339
A20: Prix unitaire portion | B20: =F19/B24 -> 0.7849
A21: Poids total ou ingrédient principal | B21: =SUM(B3:B18) -> 7.7
A22: Nombre portions recette base | B22: =B21/B23 -> 70
A23: Poids net portions | B23: 0.11 | C23: Possibilité de saisir le grammage
A24: Nombre portions à produire | B24: =Paramètres!$B$5 -> 110 | C24: Effectif EHPAD + FAM (feuille Paramètres) – possibilité de saisir un autre nombre

Sheet E-Salade d'endives
A1: Salade d'endives | E1: VP Théorique minimum | G1: Préparation froide Bac gastro + film, 0/+3°C
E2: Liaison froide 0/+3°C
A3: Produits | B3: Qté recette base | C3: Qté production | D3: U | E3: PU | F3: Total €
A4: Endives | B4: 5.42 | C4: =B4/B$22*B$24 -> 8.522554 | D4: Kg | E4: =IFERROR(INDEX(Correspondance!$D$2:$D$3000,MATCH(A4,Correspondance!$A$2:$A$3000,0)),0) -> 2.6 | F4: =C4*E4 -> 22.15864 | G4: Mode opératoire : Parer les endives, retirer les premières feuilles et le cône amer à la base Décontaminer, rincer à l'eau claire, égoutter Émincer les endives en tronçons de 1 cm, citronner légèrement pour éviter l'oxydation Vinaigrette : moutarde, sel, poivre, vinaigre, monter à l'huile, ajouter les échalotes Conditionner les endives en bacs gastro filmés, vinaigrette à part Stocker à 0/+3°C, assaisonner et parsemer de persil au moment du service Service en liaison froide, consommation dans les 24h
A5: Huile de tournesol | B5: 0.452 | C5: =B5/B$22*B$24 -> 0.71073698 | D5: L | E5: =IFERROR(INDEX(Correspondance!$D$2:$D$3000,MATCH(A5,Correspondance!$A$2:$A$3000,0)),0) -> 2.2 | F5: =C5*E5 -> 1.5636213
A6: Vinaigre de cidre | B6: 0.136 | C6: =B6/B$22*B$24 -> 0.21385006 | D6: L | E6: =IFERROR(INDEX(Correspondance!$D$2:$D$3000,MATCH(A6,Correspondance!$A$2:$A$3000,0)),0) -> 1.8 | F6: =C6*E6 -> 0.38493011
A7: Moutarde | B7: 0.072 | C7: =B7/B$22*B$24 -> 0.11321474 | D7: Kg | E7: =IFERROR(INDEX(Correspondance!$D$2:$D$3000,MATCH(A7,Correspondance!$A$2:$A$3000,0)),0) -> 9 | F7: =C7*E7 -> 1.0189327
A8: Jus de citron | B8: 0.09 | C8: =B8/B$22*B$24 -> 0.14151842 | D8: L | E8: =IFERROR(INDEX(Correspondance!$D$2:$D$3000,MATCH(A8,Correspondance!$A$2:$A$3000,0)),0) -> 2.5 | F8: =C8*E8 -> 0.35379606
A9: Échalotes ciselées surgelées | B9: 0.09 | C9: =B9/B$22*B$24 -> 0.14151842 | D9: Kg | E9: =IFERROR(INDEX(Correspondance!$D$2:$D$3000,MATCH(A9,Correspondance!$A$2:$A$3000,0)),0) -> 4.5 | F9: =C9*E9 -> 0.63683291
A10: Sel | B10: 0.036 | C10: =B10/B$22*B$24 -> 0.05660737 | D10: Kg | E10: =IFERROR(INDEX(Correspondance!$D$2:$D$3000,MATCH(A10,Correspondance!$A$2:$A$3000,0)),0) -> 2 | F10: =C10*E10 -> 0.11321474
A11: Poivre PM | C11: =B11/B$22*B$24 -> 0 | D11: Kg | E11: =IFERROR(INDEX(Correspondance!$D$2:$D$3000,MATCH(A11,Correspondance!$A$2:$A$3000,0)),0) -> 18 | F11: =C11*E11 -> 0
A12: Persil haché PM | C12: =B12/B$22*B$24 -> 0 | D12: Kg | E12: =IFERROR(INDEX(Correspondance!$D$2:$D$3000,MATCH(A12,Correspondance!$A$2:$A$3000,0)),0) -> 8 | F12: =C12*E12 -> 0
C13: =B13/B$22*B$24 -> 0 | E13: =IFERROR(INDEX(Correspondance!$D$2:$D$3000,MATCH(A13,Correspondance!$A$2:$A$3000,0)),0) -> 0 | F13: =C13*E13 -> 0
C14: =B14/B$22*B$24 -> 0 | E14: =IFERROR(INDEX(Correspondance!$D$2:$D$3000,MATCH(A14,Correspondance!$A$2:$A$3000,0)),0) -> 0 | F14: =C14*E14 -> 0
C15: =B15/B$22*B$24 -> 0 | E15: =IFERROR(INDEX(Correspondance!$D$2:$D$3000,MATCH(A15,Correspondance!$A$2:$A$3000,0)),0) -> 0 | F15: =C15*E15 -> 0
C16: =B16/B$22*B$24 -> 0 | E16: =IFERROR(INDEX(Correspondance!$D$2:$D$3000,MATCH(A16,Correspondance!$A$2:$A$3000,0)),0) -> 0 | F16: =C16*E16 -> 0
C17: =B17/B$22*B$24 -> 0 | E17: =IFERROR(INDEX(Correspondance!$D$2:$D$3000,MATCH(A17,Correspondance!$A$2:$A$3000,0)),0) -> 0 | F17: =C17*E17 -> 0
C18: =B18/B$22*B$24 -> 0 | E18: =IFERROR(INDEX(Correspondance!$D$2:$D$3000,MATCH(A18,Correspondance!$A$2:$A$3000,0)),0) -> 0 | F18: =C18*E18 -> 0
F19: =SUM(F4:F18) -> 26.229968
A20: Prix unitaire portion | B20: =F19/B24 -> 0.23845426
A21: Poids total ou ingrédient principal | B21: =SUM(B3:B18) -> 6.296
A22: Nombre portions recette base | B22: =B21/B23 -> 69.955556
A23: Poids net portions | B23: 0.09 | C23: Possibilité de saisir le grammage
A24: Nombre portions à produire | B24: =Paramètres!$B$5 -> 110 | C24: Effectif EHPAD + FAM (feuille Paramètres) – possibilité de saisir un autre nombre

Sheet E-Salade d'endives aux noix
A1: Salade d'endives aux noix | E1: VP Théorique minimum | G1: Préparation froide Bac gastro + film, 0/+3°C
E2: Liaison froide 0/+3°C
A3: Produits | B3: Qté recette base | C3: Qté production | D3: U | E3: PU | F3: Total €
A4: Endives | B4: 4.95 | C4: =B4/B$22*B$24 -> 7.7852445 | D4: Kg | E4: =IFERROR(INDEX(Correspondance!$D$2:$D$3000,MATCH(A4,Correspondance!$A$2:$A$3000,0)),0) -> 2.6 | F4: =C4*E4 -> 20.241636 | G4: Mode opératoire : Parer les endives, retirer le cône amer, décontaminer, rincer, égoutter Émincer en tronçons de 1 cm, citronner Laver les pommes, tailler en petits dés avec la peau, citronner Concasser grossièrement les cerneaux de noix Vinaigrette : moutarde, sel, poivre, vinaigre, monter aux huiles de noix et de tournesol Mélanger endives et pommes, conditionner en bacs gastro filmés, noix et vinaigrette à part Stocker à 0/+3°C, assaisonner et parsemer de noix au moment du service Service en liaison froide, consommation dans les 24h
A5: Cerneaux de noix | B5: 0.36 | C5: =B5/B$22*B$24 -> 0.5661996 | D5: Kg | E5: =IFERROR(INDEX(Correspondance!$D$2:$D$3000,MATCH(A5,Correspondance!$A$2:$A$3000,0)),0) -> 14 | F5: =C5*E5 -> 7.9267944
A6: Pommes | B6: 0.901 | C6: =B6/B$22*B$24 -> 1.4170718 | D6: Kg | E6: =IFERROR(INDEX(Correspondance!$D$2:$D$3000,MATCH(A6,Correspondance!$A$2:$A$3000,0)),0) -> 1.7 | F6: =C6*E6 -> 2.409022
A7: Huile de noix | B7: 0.18 | C7: =B7/B$22*B$24 -> 0.2830998 | D7: L | E7: =IFERROR(INDEX(Correspondance!$D$2:$D$3000,MATCH(A7,Correspondance!$A$2:$A$3000,0)),0) -> 12 | F7: =C7*E7 -> 3.3971976
A8: Huile de tournesol | B8: 0.27 | C8: =B8/B$22*B$24 -> 0.4246497 | D8: L | E8: =IFERROR(INDEX(Correspondance!$D$2:$D$3000,MATCH(A8,Correspondance!$A$2:$A$3000,0)),0) -> 2.2 | F8: =C8*E8 -> 0.93422934
A9: Vinaigre de cidre | B9: 0.135 | C9: =B9/B$22*B$24 -> 0.21232485 | D9: L | E9: =IFERROR(INDEX(Correspondance!$D$2:$D$3000,MATCH(A9,Correspondance!$A$2:$A$3000,0)),0) -> 1.8 | F9: =C9*E9 -> 0.38218473
A10: Moutarde | B10: 0.072 | C10: =B10/B$22*B$24 -> 0.11323992 | D10: Kg | E10: =IFERROR(INDEX(Correspondance!$D$2:$D$3000,MATCH(A10,Correspondance!$A$2:$A$3000,0)),0) -> 9 | F10: =C10*E10 -> 1.0191593
A11: Jus de citron | B11: 0.09 | C11: =B11/B$22*B$24 -> 0.1415499 | D11: L | E11: =IFERROR(INDEX(Correspondance!$D$2:$D$3000,MATCH(A11,Correspondance!$A$2:$A$3000,0)),0) -> 2.5 | F11: =C11*E11 -> 0.35387475
A12: Sel | B12: 0.036 | C12: =B12/B$22*B$24 -> 0.05661996 | D12: Kg | E12: =IFERROR(INDEX(Correspondance!$D$2:$D$3000,MATCH(A12,Correspondance!$A$2:$A$3000,0)),0) -> 2 | F12: =C12*E12 -> 0.11323992
A13: Poivre PM | C13: =B13/B$22*B$24 -> 0 | D13: Kg | E13: =IFERROR(INDEX(Correspondance!$D$2:$D$3000,MATCH(A13,Correspondance!$A$2:$A$3000,0)),0) -> 18 | F13: =C13*E13 -> 0
C14: =B14/B$22*B$24 -> 0 | E14: =IFERROR(INDEX(Correspondance!$D$2:$D$3000,MATCH(A14,Correspondance!$A$2:$A$3000,0)),0) -> 0 | F14: =C14*E14 -> 0
C15: =B15/B$22*B$24 -> 0 | E15: =IFERROR(INDEX(Correspondance!$D$2:$D$3000,MATCH(A15,Correspondance!$A$2:$A$3000,0)),0) -> 0 | F15: =C15*E15 -> 0
C16: =B16/B$22*B$24 -> 0 | E16: =IFERROR(INDEX(Correspondance!$D$2:$D$3000,MATCH(A16,Correspondance!$A$2:$A$3000,0)),0) -> 0 | F16: =C16*E16 -> 0
C17: =B17/B$22*B$24 -> 0 | E17: =IFERROR(INDEX(Correspondance!$D$2:$D$3000,MATCH(A17,Correspondance!$A$2:$A$3000,0)),0) -> 0 | F17: =C17*E17 -> 0
C18: =B18/B$22*B$24 -> 0 | E18: =IFERROR(INDEX(Correspondance!$D$2:$D$3000,MATCH(A18,Correspondance!$A$2:$A$3000,0)),0) -> 0 | F18: =C18*E18 -> 0
F19: =SUM(F4:F18) -> 36.777338
A20: Prix unitaire portion | B20: =F19/B24 -> 0.33433943
A21: Poids total ou ingrédient principal | B21: =SUM(B3:B18) -> 6.994
A22: Nombre portions recette base | B22: =B21/B23 -> 69.94
A23: Poids net portions | B23: 0.1 | C23: Possibilité de saisir le grammage
A24: Nombre portions à produire | B24: =Paramètres!$B$5 -> 110 | C24: Effectif EHPAD + FAM (feuille Paramètres) – possibilité de saisir un autre nombre

Sheet E-Endives au bleu et aux noix
A1: Endives au bleu et aux noix | E1: VP Théorique minimum | G1: Préparation froide Bac gastro + film, 0/+3°C
E2: Liaison froide 0/+3°C
A3: Produits | B3: Qté recette base | C3: Qté production | D3: U | E3: PU | F3: Total €
A4: Endives | B4: 4.76 | C4: =B4/B$22*B$24 -> 7.4780576 | D4: Kg | E4: =IFERROR(INDEX(Correspondance!$D$2:$D$3000,MATCH(A4,Correspondance!$A$2:$A$3000,0)),0) -> 2.6 | F4: =C4*E4 -> 19.44295 | G4: Mode opératoire : Parer les endives, retirer le cône amer, décontaminer, rincer, égoutter, émincer et citronner Tailler les pommes en dés, citronner Sauce au bleu : écraser le bleu à la fourchette, détendre à la crème, ajouter moutarde, vinaigre, huile, poivre, peu de sel (le bleu est salé) Concasser les noix Mélanger endives et pommes, conditionner en bacs gastro filmés Sauce au bleu et noix à part en pots fermés, stocker le tout à 0/+3°C Au service : napper de sauce au bleu, parsemer de noix Service en liaison froide, consommation dans les 24h
A5: Bleu d'Auvergne | B5: 0.952 | C5: =B5/B$22*B$24 -> 1.4956115 | D5: Kg | E5: =IFERROR(INDEX(Correspondance!$D$2:$D$3000,MATCH(A5,Correspondance!$A$2:$A$3000,0)),0) -> 10.5 | F5: =C5*E5 -> 15.703921
A6: Cerneaux de noix | B6: 0.381 | C6: =B6/B$22*B$24 -> 0.59855882 | D6: Kg | E6: =IFERROR(INDEX(Correspondance!$D$2:$D$3000,MATCH(A6,Correspondance!$A$2:$A$3000,0)),0) -> 14 | F6: =C6*E6 -> 8.3798234
A7: Pommes | B7: 0.761 | C7: =B7/B$22*B$24 -> 1.1955466 | D7: Kg | E7: =IFERROR(INDEX(Correspondance!$D$2:$D$3000,MATCH(A7,Correspondance!$A$2:$A$3000,0)),0) -> 1.7 | F7: =C7*E7 -> 2.0324292
A8: Crème 35% | B8: 0.286 | C8: =B8/B$22*B$24 -> 0.44931187 | D8: L | E8: =IFERROR(INDEX(Correspondance!$D$2:$D$3000,MATCH(A8,Correspondance!$A$2:$A$3000,0)),0) -> 5.5 | F8: =C8*E8 -> 2.4712153
A9: Huile de tournesol | B9: 0.286 | C9: =B9/B$22*B$24 -> 0.44931187 | D9: L | E9: =IFERROR(INDEX(Correspondance!$D$2:$D$3000,MATCH(A9,Correspondance!$A$2:$A$3000,0)),0) -> 2.2 | F9: =C9*E9 -> 0.98848611
A10: Vinaigre de cidre | B10: 0.114 | C10: =B10/B$22*B$24 -> 0.17909634 | D10: L | E10: =IFERROR(INDEX(Correspondance!$D$2:$D$3000,MATCH(A10,Correspondance!$A$2:$A$3000,0)),0) -> 1.8 | F10: =C10*E10 -> 0.32237341
A11: Moutarde | B11: 0.048 | C11: =B11/B$22*B$24 -> 0.075408985 | D11: Kg | E11: =IFERROR(INDEX(Correspondance!$D$2:$D$3000,MATCH(A11,Correspondance!$A$2:$A$3000,0)),0) -> 9 | F11: =C11*E11 -> 0.67868086
A12: Jus de citron | B12: 0.095 | C12: =B12/B$22*B$24 -> 0.14924695 | D12: L | E12: =IFERROR(INDEX(Correspondance!$D$2:$D$3000,MATCH(A12,Correspondance!$A$2:$A$3000,0)),0) -> 2.5 | F12: =C12*E12 -> 0.37311737
A13: Sel | B13: 0.019 | C13: =B13/B$22*B$24 -> 0.02984939 | D13: Kg | E13: =IFERROR(INDEX(Correspondance!$D$2:$D$3000,MATCH(A13,Correspondance!$A$2:$A$3000,0)),0) -> 2 | F13: =C13*E13 -> 0.05969878
A14: Poivre PM | C14: =B14/B$22*B$24 -> 0 | D14: Kg | E14: =IFERROR(INDEX(Correspondance!$D$2:$D$3000,MATCH(A14,Correspondance!$A$2:$A$3000,0)),0) -> 18 | F14: =C14*E14 -> 0
C15: =B15/B$22*B$24 -> 0 | E15: =IFERROR(INDEX(Correspondance!$D$2:$D$3000,MATCH(A15,Correspondance!$A$2:$A$3000,0)),0) -> 0 | F15: =C15*E15 -> 0
C16: =B16/B$22*B$24 -> 0 | E16: =IFERROR(INDEX(Correspondance!$D$2:$D$3000,MATCH(A16,Correspondance!$A$2:$A$3000,0)),0) -> 0 | F16: =C16*E16 -> 0
C17: =B17/B$22*B$24 -> 0 | E17: =IFERROR(INDEX(Correspondance!$D$2:$D$3000,MATCH(A17,Correspondance!$A$2:$A$3000,0)),0) -> 0 | F17: =C17*E17 -> 0
C18: =B18/B$22*B$24 -> 0 | E18: =IFERROR(INDEX(Correspondance!$D$2:$D$3000,MATCH(A18,Correspondance!$A$2:$A$3000,0)),0) -> 0 | F18: =C18*E18 -> 0
F19: =SUM(F4:F18) -> 50.452695
A20: Prix unitaire portion | B20: =F19/B24 -> 0.45866087
A21: Poids total ou ingrédient principal | B21: =SUM(B3:B18) -> 7.702
A22: Nombre portions recette base | B22: =B21/B23 -> 70.018182
A23: Poids net portions | B23: 0.11 | C23: Possibilité de saisir le grammage
A24: Nombre portions à produire | B24: =Paramètres!$B$5 -> 110 | C24: Effectif EHPAD + FAM (feuille Paramètres) – possibilité de saisir un autre nombre

Sheet E-Salade de riz
A1: Salade de riz | E1: VP Théorique minimum | G1: Riz cuit à l'eau puis refroidi en cellule Assemblage en liaison froide Bac gastro + film, 0/+3°C
E2: Liaison froide 0/+3°C
A3: Produits | B3: Qté recette base | C3: Qté production | D3: U | E3: PU | F3: Total €
A4: Riz long étuvé | B4: 2.17 | C4: =B4/B$22*B$24 -> 3.4055404 | D4: Kg | E4: =IFERROR(INDEX(Correspondance!$D$2:$D$3000,MATCH(A4,Correspondance!$A$2:$A$3000,0)),0) -> 1.9 | F4: =C4*E4 -> 6.4705267 | G4: Mode opératoire : Cuire le riz à grande eau salée bouillante 12 à 14 min, égoutter Refroidir immédiatement en cellule (63°C à 10°C en moins de deux heures), réserver à 0/+3°C Décontaminer et tailler les tomates, décongeler les poivrons au froid et égoutter Émietter le thon, couper les œufs durs en quartiers, égoutter le maïs et les olives Vinaigrette : moutarde, sel, poivre, vinaigre, monter à l'huile Mélanger riz froid, légumes, thon, olives et vinaigrette, rectifier l'assaisonnement Conditionner en bacs gastro, décorer avec les œufs et la ciboulette, filmer, étiqueter Stocker à 0/+3°C, service en liaison froide, consommation dans les 48h
A5: Tomates en cubes | B5: 1.63 | C5: =B5/B$22*B$24 -> 2.5580787 | D5: Kg | E5: =IFERROR(INDEX(Correspondance!$D$2:$D$3000,MATCH(A5,Correspondance!$A$2:$A$3000,0)),0) -> 1.5 | F5: =C5*E5 -> 3.8371181
A6: Maïs doux appertisé égoutté | B6: 1.09 | C6: =B6/B$22*B$24 -> 1.710617 | D6: Kg | E6: =IFERROR(INDEX(Correspondance!$D$2:$D$3000,MATCH(A6,Correspondance!$A$2:$A$3000,0)),0) -> 2.2 | F6: =C6*E6 -> 3.7633575
A7: Thon au naturel égoutté | B7: 1.09 | C7: =B7/B$22*B$24 -> 1.710617 | D7: Kg | E7: =IFERROR(INDEX(Correspondance!$D$2:$D$3000,MATCH(A7,Correspondance!$A$2:$A$3000,0)),0) -> 9.5 | F7: =C7*E7 -> 16.250862
A8: Œufs durs écalés pasteurisés | B8: 0.868 | C8: =B8/B$22*B$24 -> 1.3622161 | D8: Kg | E8: =IFERROR(INDEX(Correspondance!$D$2:$D$3000,MATCH(A8,Correspondance!$A$2:$A$3000,0)),0) -> 5.6 | F8: =C8*E8 -> 7.6284104
A9: Poivrons dés surgelés | B9: 0.543 | C9: =B9/B$22*B$24 -> 0.85216978 | D9: Kg | E9: =IFERROR(INDEX(Correspondance!$D$2:$D$3000,MATCH(A9,Correspondance!$A$2:$A$3000,0)),0) -> 3 | F9: =C9*E9 -> 2.5565093
A10: Olives noires dénoyautées | B10: 0.217 | C10: =B10/B$22*B$24 -> 0.34055404 | D10: Kg | E10: =IFERROR(INDEX(Correspondance!$D$2:$D$3000,MATCH(A10,Correspondance!$A$2:$A$3000,0)),0) -> 5.5 | F10: =C10*E10 -> 1.8730472
A11: Huile de tournesol | B11: 0.543 | C11: =B11/B$22*B$24 -> 0.85216978 | D11: L | E11: =IFERROR(INDEX(Correspondance!$D$2:$D$3000,MATCH(A11,Correspondance!$A$2:$A$3000,0)),0) -> 2.2 | F11: =C11*E11 -> 1.8747735
A12: Vinaigre de vin | B12: 0.163 | C12: =B12/B$22*B$24 -> 0.25580787 | D12: L | E12: =IFERROR(INDEX(Correspondance!$D$2:$D$3000,MATCH(A12,Correspondance!$A$2:$A$3000,0)),0) -> 1.5 | F12: =C12*E12 -> 0.38371181
A13: Moutarde | B13: 0.054 | C13: =B13/B$22*B$24 -> 0.084746166 | D13: Kg | E13: =IFERROR(INDEX(Correspondance!$D$2:$D$3000,MATCH(A13,Correspondance!$A$2:$A$3000,0)),0) -> 9 | F13: =C13*E13 -> 0.76271549
A14: Sel | B14: 0.043 | C14: =B14/B$22*B$24 -> 0.067483058 | D14: Kg | E14: =IFERROR(INDEX(Correspondance!$D$2:$D$3000,MATCH(A14,Correspondance!$A$2:$A$3000,0)),0) -> 2 | F14: =C14*E14 -> 0.13496612
A15: Poivre PM | C15: =B15/B$22*B$24 -> 0 | D15: Kg | E15: =IFERROR(INDEX(Correspondance!$D$2:$D$3000,MATCH(A15,Correspondance!$A$2:$A$3000,0)),0) -> 18 | F15: =C15*E15 -> 0
A16: Ciboulette ciselée PM | C16: =B16/B$22*B$24 -> 0 | D16: Kg | E16: =IFERROR(INDEX(Correspondance!$D$2:$D$3000,MATCH(A16,Correspondance!$A$2:$A$3000,0)),0) -> 13 | F16: =C16*E16 -> 0
C17: =B17/B$22*B$24 -> 0 | E17: =IFERROR(INDEX(Correspondance!$D$2:$D$3000,MATCH(A17,Correspondance!$A$2:$A$3000,0)),0) -> 0 | F17: =C17*E17 -> 0
C18: =B18/B$22*B$24 -> 0 | E18: =IFERROR(INDEX(Correspondance!$D$2:$D$3000,MATCH(A18,Correspondance!$A$2:$A$3000,0)),0) -> 0 | F18: =C18*E18 -> 0
F19: =SUM(F4:F18) -> 45.535998
A20: Prix unitaire portion | B20: =F19/B24 -> 0.41396362
A21: Poids total ou ingrédient principal | B21: =SUM(B3:B18) -> 8.411
A22: Nombre portions recette base | B22: =B21/B23 -> 70.091667
A23: Poids net portions | B23: 0.12 | C23: Possibilité de saisir le grammage
A24: Nombre portions à produire | B24: =Paramètres!$B$5 -> 110 | C24: Effectif EHPAD + FAM (feuille Paramètres) – possibilité de saisir un autre nombre

Sheet E-Betteraves vinaigrette
A1: Betteraves vinaigrette sous vide basse température | E1: VP Théorique minimum | G1: Sous vide 90°C four vapeur ou thermoplongeur Poches sous vide, 1H30 à 2H00 Refroidissement cellule, DLC J+5
E2: > à 10 000
A3: Produits | B3: Qté recette base | C3: Qté production | D3: U | E3: PU | F3: Total €
A4: Betteraves rouges crues | B4: 6.02 | C4: =B4/B$22*B$24 -> 9.4572979 | D4: Kg | E4: =IFERROR(INDEX(Correspondance!$D$2:$D$3000,MATCH(A4,Correspondance!$A$2:$A$3000,0)),0) -> 1.4 | F4: =C4*E4 -> 13.240217 | G4: Mode opératoire : Laver et brosser les betteraves, éplucher, tailler en cubes de 1 cm Conditionner en poches sous vide à plat (2 kg maximum par poche), ajouter une pincée de sel, mettre sous vide Cuisson : 90°C vapeur ou thermoplongeur 1H30 à 2H00 selon la taille, contrôle de tendreté à la pointe du couteau Refroidir en cellule (63°C à 10°C en moins de deux heures), étiqueter, DLC 5 jours maximum (J+5) en poche fermée Le jour du service : ouvrir les poches, égoutter les betteraves Vinaigrette : moutarde, sel, poivre, vinaigre, monter à l'huile, ajouter les échalotes Mélanger betteraves et vinaigrette, laisser mariner 1 heure à 0/+3°C Conditionner en bacs gastro filmés, parsemer de persil au service, consommation dans les 48h après ouverture
A5: Huile de tournesol | B5: 0.501 | C5: =B5/B$22*B$24 -> 0.78706084 | D5: L | E5: =IFERROR(INDEX(Correspondance!$D$2:$D$3000,MATCH(A5,Correspondance!$A$2:$A$3000,0)),0) -> 2.2 | F5: =C5*E5 -> 1.7315338
A6: Vinaigre de vin | B6: 0.201 | C6: =B6/B$22*B$24 -> 0.31576692 | D6: L | E6: =IFERROR(INDEX(Correspondance!$D$2:$D$3000,MATCH(A6,Correspondance!$A$2:$A$3000,0)),0) -> 1.5 | F6: =C6*E6 -> 0.47365039
A7: Moutarde | B7: 0.08 | C7: =B7/B$22*B$24 -> 0.12567838 | D7: Kg | E7: =IFERROR(INDEX(Correspondance!$D$2:$D$3000,MATCH(A7,Correspondance!$A$2:$A$3000,0)),0) -> 9 | F7: =C7*E7 -> 1.1311054
A8: Échalotes ciselées surgelées | B8: 0.15 | C8: =B8/B$22*B$24 -> 0.23564696 | D8: Kg | E8: =IFERROR(INDEX(Correspondance!$D$2:$D$3000,MATCH(A8,Correspondance!$A$2:$A$3000,0)),0) -> 4.5 | F8: =C8*E8 -> 1.0604113
A9: Sel | B9: 0.05 | C9: =B9/B$22*B$24 -> 0.078548986 | D9: Kg | E9: =IFERROR(INDEX(Correspondance!$D$2:$D$3000,MATCH(A9,Correspondance!$A$2:$A$3000,0)),0) -> 2 | F9: =C9*E9 -> 0.15709797
A10: Poivre PM | C10: =B10/B$22*B$24 -> 0 | D10: Kg | E10: =IFERROR(INDEX(Correspondance!$D$2:$D$3000,MATCH(A10,Correspondance!$A$2:$A$3000,0)),0) -> 18 | F10: =C10*E10 -> 0
A11: Persil haché PM | C11: =B11/B$22*B$24 -> 0 | D11: Kg | E11: =IFERROR(INDEX(Correspondance!$D$2:$D$3000,MATCH(A11,Correspondance!$A$2:$A$3000,0)),0) -> 8 | F11: =C11*E11 -> 0
C12: =B12/B$22*B$24 -> 0 | E12: =IFERROR(INDEX(Correspondance!$D$2:$D$3000,MATCH(A12,Correspondance!$A$2:$A$3000,0)),0) -> 0 | F12: =C12*E12 -> 0
C13: =B13/B$22*B$24 -> 0 | E13: =IFERROR(INDEX(Correspondance!$D$2:$D$3000,MATCH(A13,Correspondance!$A$2:$A$3000,0)),0) -> 0 | F13: =C13*E13 -> 0
C14: =B14/B$22*B$24 -> 0 | E14: =IFERROR(INDEX(Correspondance!$D$2:$D$3000,MATCH(A14,Correspondance!$A$2:$A$3000,0)),0) -> 0 | F14: =C14*E14 -> 0
C15: =B15/B$22*B$24 -> 0 | E15: =IFERROR(INDEX(Correspondance!$D$2:$D$3000,MATCH(A15,Correspondance!$A$2:$A$3000,0)),0) -> 0 | F15: =C15*E15 -> 0
C16: =B16/B$22*B$24 -> 0 | E16: =IFERROR(INDEX(Correspondance!$D$2:$D$3000,MATCH(A16,Correspondance!$A$2:$A$3000,0)),0) -> 0 | F16: =C16*E16 -> 0
C17: =B17/B$22*B$24 -> 0 | E17: =IFERROR(INDEX(Correspondance!$D$2:$D$3000,MATCH(A17,Correspondance!$A$2:$A$3000,0)),0) -> 0 | F17: =C17*E17 -> 0
C18: =B18/B$22*B$24 -> 0 | E18: =IFERROR(INDEX(Correspondance!$D$2:$D$3000,MATCH(A18,Correspondance!$A$2:$A$3000,0)),0) -> 0 | F18: =C18*E18 -> 0
F19: =SUM(F4:F18) -> 17.794016
A20: Prix unitaire portion | B20: =F19/B24 -> 0.16176378
A21: Poids total ou ingrédient principal | B21: =SUM(B3:B18) -> 7.002
A22: Nombre portions recette base | B22: =B21/B23 -> 70.02
A23: Poids net portions | B23: 0.1 | C23: Possibilité de saisir le grammage
A24: Nombre portions à produire | B24: =Paramètres!$B$5 -> 110 | C24: Effectif EHPAD + FAM (feuille Paramètres) – possibilité de saisir un autre nombre

Sheet E-Salade de betteraves et maïs
A1: Salade de betteraves et maïs sous vide basse température | E1: VP Théorique minimum | G1: Sous vide 90°C four vapeur ou thermoplongeur Poches sous vide, 1H30 à 2H00 Assemblage froid après refroidissement
E2: > à 10 000
A3: Produits | B3: Qté recette base | C3: Qté production | D3: U | E3: PU | F3: Total €
A4: Betteraves rouges crues | B4: 4.13 | C4: =B4/B$22*B$24 -> 6.4937107 | D4: Kg | E4: =IFERROR(INDEX(Correspondance!$D$2:$D$3000,MATCH(A4,Correspondance!$A$2:$A$3000,0)),0) -> 1.4 | F4: =C4*E4 -> 9.091195 | G4: Mode opératoire : Laver, brosser et éplucher les betteraves, tailler en cubes de 1 cm Conditionner en poches sous vide à plat (2 kg maximum), mettre sous vide Cuisson : 90°C vapeur ou thermoplongeur 1H30 à 2H00, contrôle de tendreté Refroidir en cellule (63°C à 10°C en moins de deux heures), étiqueter, DLC J+5 en poche fermée Le jour du service : égoutter les betteraves, égoutter et rincer le maïs Vinaigrette : moutarde, sel, poivre, vinaigre, monter à l'huile Mélanger betteraves, maïs, oignons rouges et vinaigrette, laisser mariner 1 heure à 0/+3°C Conditionner en bacs gastro filmés, ciboulette au service, consommation dans les 48h
A5: Maïs doux appertisé égoutté | B5: 1.83 | C5: =B5/B$22*B$24 -> 2.8773585 | D5: Kg | E5: =IFERROR(INDEX(Correspondance!$D$2:$D$3000,MATCH(A5,Correspondance!$A$2:$A$3000,0)),0) -> 2.2 | F5: =C5*E5 -> 6.3301887
A6: Oignons rouges émincés | B6: 0.275 | C6: =B6/B$22*B$24 -> 0.43238994 | D6: Kg | E6: =IFERROR(INDEX(Correspondance!$D$2:$D$3000,MATCH(A6,Correspondance!$A$2:$A$3000,0)),0) -> 1.8 | F6: =C6*E6 -> 0.77830189
A7: Huile de tournesol | B7: 0.459 | C7: =B7/B$22*B$24 -> 0.72169811 | D7: L | E7: =IFERROR(INDEX(Correspondance!$D$2:$D$3000,MATCH(A7,Correspondance!$A$2:$A$3000,0)),0) -> 2.2 | F7: =C7*E7 -> 1.5877358
A8: Vinaigre de cidre | B8: 0.183 | C8: =B8/B$22*B$24 -> 0.28773585 | D8: L | E8: =IFERROR(INDEX(Correspondance!$D$2:$D$3000,MATCH(A8,Correspondance!$A$2:$A$3000,0)),0) -> 1.8 | F8: =C8*E8 -> 0.51792453
A9: Moutarde | B9: 0.073 | C9: =B9/B$22*B$24 -> 0.11477987 | D9: Kg | E9: =IFERROR(INDEX(Correspondance!$D$2:$D$3000,MATCH(A9,Correspondance!$A$2:$A$3000,0)),0) -> 9 | F9: =C9*E9 -> 1.0330189
A10: Sel | B10: 0.046 | C10: =B10/B$22*B$24 -> 0.072327044 | D10: Kg | E10: =IFERROR(INDEX(Correspondance!$D$2:$D$3000,MATCH(A10,Correspondance!$A$2:$A$3000,0)),0) -> 2 | F10: =C10*E10 -> 0.14465409
A11: Poivre PM | C11: =B11/B$22*B$24 -> 0 | D11: Kg | E11: =IFERROR(INDEX(Correspondance!$D$2:$D$3000,MATCH(A11,Correspondance!$A$2:$A$3000,0)),0) -> 18 | F11: =C11*E11 -> 0
A12: Ciboulette ciselée PM | C12: =B12/B$22*B$24 -> 0 | D12: Kg | E12: =IFERROR(INDEX(Correspondance!$D$2:$D$3000,MATCH(A12,Correspondance!$A$2:$A$3000,0)),0) -> 13 | F12: =C12*E12 -> 0
C13: =B13/B$22*B$24 -> 0 | E13: =IFERROR(INDEX(Correspondance!$D$2:$D$3000,MATCH(A13,Correspondance!$A$2:$A$3000,0)),0) -> 0 | F13: =C13*E13 -> 0
C14: =B14/B$22*B$24 -> 0 | E14: =IFERROR(INDEX(Correspondance!$D$2:$D$3000,MATCH(A14,Correspondance!$A$2:$A$3000,0)),0) -> 0 | F14: =C14*E14 -> 0
C15: =B15/B$22*B$24 -> 0 | E15: =IFERROR(INDEX(Correspondance!$D$2:$D$3000,MATCH(A15,Correspondance!$A$2:$A$3000,0)),0) -> 0 | F15: =C15*E15 -> 0
C16: =B16/B$22*B$24 -> 0 | E16: =IFERROR(INDEX(Correspondance!$D$2:$D$3000,MATCH(A16,Correspondance!$A$2:$A$3000,0)),0) -> 0 | F16: =C16*E16 -> 0
C17: =B17/B$22*B$24 -> 0 | E17: =IFERROR(INDEX(Correspondance!$D$2:$D$3000,MATCH(A17,Correspondance!$A$2:$A$3000,0)),0) -> 0 | F17: =C17*E17 -> 0
C18: =B18/B$22*B$24 -> 0 | E18: =IFERROR(INDEX(Correspondance!$D$2:$D$3000,MATCH(A18,Correspondance!$A$2:$A$3000,0)),0) -> 0 | F18: =C18*E18 -> 0
F19: =SUM(F4:F18) -> 19.483019
A20: Prix unitaire portion | B20: =F19/B24 -> 0.17711835
A21: Poids total ou ingrédient principal | B21: =SUM(B3:B18) -> 6.996
A22: Nombre portions recette base | B22: =B21/B23 -> 69.96
A23: Poids net portions | B23: 0.1 | C23: Possibilité de saisir le grammage
A24: Nombre portions à produire | B24: =Paramètres!$B$5 -> 110 | C24: Effectif EHPAD + FAM (feuille Paramètres) – possibilité de saisir un autre nombre

Sheet E-Salade mexicaine
A1: Salade mexicaine | E1: VP Théorique minimum | G1: Préparation froide Bac gastro + film, 0/+3°C
E2: Liaison froide 0/+3°C
A3: Produits | B3: Qté recette base | C3: Qté production | D3: U | E3: PU | F3: Total €
A4: Haricots rouges appertisés égouttés | B4: 2.31 | C4: =B4/B$22*B$24 -> 3.628445 | D4: Kg | E4: =IFERROR(INDEX(Correspondance!$D$2:$D$3000,MATCH(A4,Correspondance!$A$2:$A$3000,0)),0) -> 2 | F4: =C4*E4 -> 7.2568899 | G4: Mode opératoire : Peser tous les ingrédients d'épicerie Égoutter et rincer soigneusement haricots rouges et maïs Décongeler les poivrons au froid la veille, égoutter Décontaminer et rincer tomates et coriandre, tailler les tomates en cubes Sauce : jus de citron vert, sel, cumin, paprika, piment, monter à l'huile Mélanger tous les légumes avec la sauce, laisser mariner 1 heure à 0/+3°C Conditionner en bacs gastro filmés, étiqueter, coriandre ciselée au service Service en liaison froide, consommation dans les 48h
A5: Maïs doux appertisé égoutté | B5: 1.85 | C5: =B5/B$22*B$24 -> 2.9058975 | D5: Kg | E5: =IFERROR(INDEX(Correspondance!$D$2:$D$3000,MATCH(A5,Correspondance!$A$2:$A$3000,0)),0) -> 2.2 | F5: =C5*E5 -> 6.3929744
A6: Poivrons dés surgelés | B6: 0.923 | C6: =B6/B$22*B$24 -> 1.4498072 | D6: Kg | E6: =IFERROR(INDEX(Correspondance!$D$2:$D$3000,MATCH(A6,Correspondance!$A$2:$A$3000,0)),0) -> 3 | F6: =C6*E6 -> 4.3494217
A7: Tomates en cubes | B7: 0.923 | C7: =B7/B$22*B$24 -> 1.4498072 | D7: Kg | E7: =IFERROR(INDEX(Correspondance!$D$2:$D$3000,MATCH(A7,Correspondance!$A$2:$A$3000,0)),0) -> 1.5 | F7: =C7*E7 -> 2.1747108
A8: Oignons rouges émincés | B8: 0.277 | C8: =B8/B$22*B$24 -> 0.43509924 | D8: Kg | E8: =IFERROR(INDEX(Correspondance!$D$2:$D$3000,MATCH(A8,Correspondance!$A$2:$A$3000,0)),0) -> 1.8 | F8: =C8*E8 -> 0.78317864
A9: Huile de tournesol | B9: 0.462 | C9: =B9/B$22*B$24 -> 0.72568899 | D9: L | E9: =IFERROR(INDEX(Correspondance!$D$2:$D$3000,MATCH(A9,Correspondance!$A$2:$A$3000,0)),0) -> 2.2 | F9: =C9*E9 -> 1.5965158
A10: Jus de citron vert | B10: 0.185 | C10: =B10/B$22*B$24 -> 0.29058975 | D10: L | E10: =IFERROR(INDEX(Correspondance!$D$2:$D$3000,MATCH(A10,Correspondance!$A$2:$A$3000,0)),0) -> 4.5 | F10: =C10*E10 -> 1.3076539
A11: Cumin moulu | B11: 0.018 | C11: =B11/B$22*B$24 -> 0.028273597 | D11: Kg | E11: =IFERROR(INDEX(Correspondance!$D$2:$D$3000,MATCH(A11,Correspondance!$A$2:$A$3000,0)),0) -> 12 | F11: =C11*E11 -> 0.33928316
A12: Paprika | B12: 0.018 | C12: =B12/B$22*B$24 -> 0.028273597 | D12: Kg | E12: =IFERROR(INDEX(Correspondance!$D$2:$D$3000,MATCH(A12,Correspondance!$A$2:$A$3000,0)),0) -> 11 | F12: =C12*E12 -> 0.31100957
A13: Sel | B13: 0.037 | C13: =B13/B$22*B$24 -> 0.058117949 | D13: Kg | E13: =IFERROR(INDEX(Correspondance!$D$2:$D$3000,MATCH(A13,Correspondance!$A$2:$A$3000,0)),0) -> 2 | F13: =C13*E13 -> 0.1162359
A14: Piment doux PM | C14: =B14/B$22*B$24 -> 0 | D14: Kg | E14: =IFERROR(INDEX(Correspondance!$D$2:$D$3000,MATCH(A14,Correspondance!$A$2:$A$3000,0)),0) -> 12 | F14: =C14*E14 -> 0
A15: Coriandre fraîche PM | C15: =B15/B$22*B$24 -> 0 | D15: Kg | E15: =IFERROR(INDEX(Correspondance!$D$2:$D$3000,MATCH(A15,Correspondance!$A$2:$A$3000,0)),0) -> 30 | F15: =C15*E15 -> 0
C16: =B16/B$22*B$24 -> 0 | E16: =IFERROR(INDEX(Correspondance!$D$2:$D$3000,MATCH(A16,Correspondance!$A$2:$A$3000,0)),0) -> 0 | F16: =C16*E16 -> 0
C17: =B17/B$22*B$24 -> 0 | E17: =IFERROR(INDEX(Correspondance!$D$2:$D$3000,MATCH(A17,Correspondance!$A$2:$A$3000,0)),0) -> 0 | F17: =C17*E17 -> 0
C18: =B18/B$22*B$24 -> 0 | E18: =IFERROR(INDEX(Correspondance!$D$2:$D$3000,MATCH(A18,Correspondance!$A$2:$A$3000,0)),0) -> 0 | F18: =C18*E18 -> 0
F19: =SUM(F4:F18) -> 24.627874
A20: Prix unitaire portion | B20: =F19/B24 -> 0.22388976
A21: Poids total ou ingrédient principal | B21: =SUM(B3:B18) -> 7.003
A22: Nombre portions recette base | B22: =B21/B23 -> 70.03
A23: Poids net portions | B23: 0.1 | C23: Possibilité de saisir le grammage
A24: Nombre portions à produire | B24: =Paramètres!$B$5 -> 110 | C24: Effectif EHPAD + FAM (feuille Paramètres) – possibilité de saisir un autre nombre

Sheet E-Melon
A1: Melon | E1: VP Théorique minimum | G1: Préparation froide Tranchage le jour même Bac gastro + film, 0/+3°C
E2: Liaison froide 0/+3°C
A3: Produits | B3: Qté recette base | C3: Qté production | D3: U | E3: PU | F3: Total €
A4: Melon charentais (≈ 1 kg pièce) | B4: 9.29 | C4: =B4/B$22*B$24 -> 14.601353 | D4: Kg | E4: =IFERROR(INDEX(Correspondance!$D$2:$D$3000,MATCH(A4,Correspondance!$A$2:$A$3000,0)),0) -> 1.8 | F4: =C4*E4 -> 26.282435 | G4: Mode opératoire : Réceptionner les melons à maturité (odeur, pédoncule), stocker à 0/+3°C Laver et décontaminer la peau des melons avant découpe (rinçage abondant) Couper en 4 quartiers, épépiner, laisser la peau ou détailler en billes/cubes pour les textures adaptées Portion : 1/4 de melon (≈ 150 g net) ou 150 g de cubes Dresser en assiettes ou bacs gastro, citronner légèrement, filmer Option : accompagner d'une tranche de jambon cru ou d'un trait de porto, décorer de menthe Stocker à 0/+3°C, service en liaison froide dans les 24h Ne jamais laisser le melon tranché à température ambiante
A5: Jambon cru tranché (facultatif) | B5: 0.65 | C5: =B5/B$22*B$24 -> 1.0216232 | D5: Kg | E5: =IFERROR(INDEX(Correspondance!$D$2:$D$3000,MATCH(A5,Correspondance!$A$2:$A$3000,0)),0) -> 22 | F5: =C5*E5 -> 22.47571
A6: Porto (facultatif) | B6: 0.279 | C6: =B6/B$22*B$24 -> 0.4385121 | D6: L | E6: =IFERROR(INDEX(Correspondance!$D$2:$D$3000,MATCH(A6,Correspondance!$A$2:$A$3000,0)),0) -> 9 | F6: =C6*E6 -> 3.9466089
A7: Citron jaune | B7: 0.279 | C7: =B7/B$22*B$24 -> 0.4385121 | D7: Kg | E7: =IFERROR(INDEX(Correspondance!$D$2:$D$3000,MATCH(A7,Correspondance!$A$2:$A$3000,0)),0) -> 2.2 | F7: =C7*E7 -> 0.96472661
A8: Menthe fraîche PM | C8: =B8/B$22*B$24 -> 0 | D8: Kg | E8: =IFERROR(INDEX(Correspondance!$D$2:$D$3000,MATCH(A8,Correspondance!$A$2:$A$3000,0)),0) -> 30 | F8: =C8*E8 -> 0
A9: Sel fin PM | C9: =B9/B$22*B$24 -> 0 | D9: Kg | E9: =IFERROR(INDEX(Correspondance!$D$2:$D$3000,MATCH(A9,Correspondance!$A$2:$A$3000,0)),0) -> 2 | F9: =C9*E9 -> 0
C10: =B10/B$22*B$24 -> 0 | E10: =IFERROR(INDEX(Correspondance!$D$2:$D$3000,MATCH(A10,Correspondance!$A$2:$A$3000,0)),0) -> 0 | F10: =C10*E10 -> 0
C11: =B11/B$22*B$24 -> 0 | E11: =IFERROR(INDEX(Correspondance!$D$2:$D$3000,MATCH(A11,Correspondance!$A$2:$A$3000,0)),0) -> 0 | F11: =C11*E11 -> 0
C12: =B12/B$22*B$24 -> 0 | E12: =IFERROR(INDEX(Correspondance!$D$2:$D$3000,MATCH(A12,Correspondance!$A$2:$A$3000,0)),0) -> 0 | F12: =C12*E12 -> 0
C13: =B13/B$22*B$24 -> 0 | E13: =IFERROR(INDEX(Correspondance!$D$2:$D$3000,MATCH(A13,Correspondance!$A$2:$A$3000,0)),0) -> 0 | F13: =C13*E13 -> 0
C14: =B14/B$22*B$24 -> 0 | E14: =IFERROR(INDEX(Correspondance!$D$2:$D$3000,MATCH(A14,Correspondance!$A$2:$A$3000,0)),0) -> 0 | F14: =C14*E14 -> 0
C15: =B15/B$22*B$24 -> 0 | E15: =IFERROR(INDEX(Correspondance!$D$2:$D$3000,MATCH(A15,Correspondance!$A$2:$A$3000,0)),0) -> 0 | F15: =C15*E15 -> 0
C16: =B16/B$22*B$24 -> 0 | E16: =IFERROR(INDEX(Correspondance!$D$2:$D$3000,MATCH(A16,Correspondance!$A$2:$A$3000,0)),0) -> 0 | F16: =C16*E16 -> 0
C17: =B17/B$22*B$24 -> 0 | E17: =IFERROR(INDEX(Correspondance!$D$2:$D$3000,MATCH(A17,Correspondance!$A$2:$A$3000,0)),0) -> 0 | F17: =C17*E17 -> 0
C18: =B18/B$22*B$24 -> 0 | E18: =IFERROR(INDEX(Correspondance!$D$2:$D$3000,MATCH(A18,Correspondance!$A$2:$A$3000,0)),0) -> 0 | F18: =C18*E18 -> 0
F19: =SUM(F4:F18) -> 53.66948
A20: Prix unitaire portion | B20: =F19/B24 -> 0.48790436
A21: Poids total ou ingrédient principal | B21: =SUM(B3:B18) -> 10.498
A22: Nombre portions recette base | B22: =B21/B23 -> 69.986667
A23: Poids net portions | B23: 0.15 | C23: Possibilité de saisir le grammage
A24: Nombre portions à produire | B24: =Paramètres!$B$5 -> 110 | C24: Effectif EHPAD + FAM (feuille Paramètres) – possibilité de saisir un autre nombre

Sheet E-Pastèque
A1: Pastèque | E1: VP Théorique minimum | G1: Préparation froide Tranchage le jour même Bac gastro + film, 0/+3°C
E2: Liaison froide 0/+3°C
A3: Produits | B3: Qté recette base | C3: Qté production | D3: U | E3: PU | F3: Total €
A4: Pastèque | B4: 11.37 | C4: =B4/B$22*B$24 -> 17.864307 | D4: Kg | E4: =IFERROR(INDEX(Correspondance!$D$2:$D$3000,MATCH(A4,Correspondance!$A$2:$A$3000,0)),0) -> 1.1 | F4: =C4*E4 -> 19.650738 | G4: Mode opératoire : Laver et décontaminer la peau de la pastèque avant découpe Couper en tranches puis en cubes de 2 cm, retirer le maximum de pépins Portion : 180 g de cubes (ou une tranche épaisse sans peau) Option salée : ajouter feta en dés, huile d'olive, poivre et menthe ciselée Option sucrée : jus de citron vert, pointe de sucre, menthe Conditionner en bacs gastro ou ramequins, filmer, étiqueter Stocker à 0/+3°C, service en liaison froide dans les 24h
A5: Feta en dés (facultatif) | B5: 0.758 | C5: =B5/B$22*B$24 -> 1.1909538 | D5: Kg | E5: =IFERROR(INDEX(Correspondance!$D$2:$D$3000,MATCH(A5,Correspondance!$A$2:$A$3000,0)),0) -> 9 | F5: =C5*E5 -> 10.718584
A6: Citron vert | B6: 0.284 | C6: =B6/B$22*B$24 -> 0.44621489 | D6: Kg | E6: =IFERROR(INDEX(Correspondance!$D$2:$D$3000,MATCH(A6,Correspondance!$A$2:$A$3000,0)),0) -> 3.5 | F6: =C6*E6 -> 1.5617521
A7: Huile d'olive | B7: 0.095 | C7: =B7/B$22*B$24 -> 0.14926202 | D7: L | E7: =IFERROR(INDEX(Correspondance!$D$2:$D$3000,MATCH(A7,Correspondance!$A$2:$A$3000,0)),0) -> 7.5 | F7: =C7*E7 -> 1.1194652
A8: Sucre semoule | B8: 0.095 | C8: =B8/B$22*B$24 -> 0.14926202 | D8: Kg | E8: =IFERROR(INDEX(Correspondance!$D$2:$D$3000,MATCH(A8,Correspondance!$A$2:$A$3000,0)),0) -> 1.3 | F8: =C8*E8 -> 0.19404063
A9: Menthe fraîche PM | C9: =B9/B$22*B$24 -> 0 | D9: Kg | E9: =IFERROR(INDEX(Correspondance!$D$2:$D$3000,MATCH(A9,Correspondance!$A$2:$A$3000,0)),0) -> 30 | F9: =C9*E9 -> 0
A10: Poivre PM | C10: =B10/B$22*B$24 -> 0 | D10: Kg | E10: =IFERROR(INDEX(Correspondance!$D$2:$D$3000,MATCH(A10,Correspondance!$A$2:$A$3000,0)),0) -> 18 | F10: =C10*E10 -> 0
C11: =B11/B$22*B$24 -> 0 | E11: =IFERROR(INDEX(Correspondance!$D$2:$D$3000,MATCH(A11,Correspondance!$A$2:$A$3000,0)),0) -> 0 | F11: =C11*E11 -> 0
C12: =B12/B$22*B$24 -> 0 | E12: =IFERROR(INDEX(Correspondance!$D$2:$D$3000,MATCH(A12,Correspondance!$A$2:$A$3000,0)),0) -> 0 | F12: =C12*E12 -> 0
C13: =B13/B$22*B$24 -> 0 | E13: =IFERROR(INDEX(Correspondance!$D$2:$D$3000,MATCH(A13,Correspondance!$A$2:$A$3000,0)),0) -> 0 | F13: =C13*E13 -> 0
C14: =B14/B$22*B$24 -> 0 | E14: =IFERROR(INDEX(Correspondance!$D$2:$D$3000,MATCH(A14,Correspondance!$A$2:$A$3000,0)),0) -> 0 | F14: =C14*E14 -> 0
C15: =B15/B$22*B$24 -> 0 | E15: =IFERROR(INDEX(Correspondance!$D$2:$D$3000,MATCH(A15,Correspondance!$A$2:$A$3000,0)),0) -> 0 | F15: =C15*E15 -> 0
C16: =B16/B$22*B$24 -> 0 | E16: =IFERROR(INDEX(Correspondance!$D$2:$D$3000,MATCH(A16,Correspondance!$A$2:$A$3000,0)),0) -> 0 | F16: =C16*E16 -> 0
C17: =B17/B$22*B$24 -> 0 | E17: =IFERROR(INDEX(Correspondance!$D$2:$D$3000,MATCH(A17,Correspondance!$A$2:$A$3000,0)),0) -> 0 | F17: =C17*E17 -> 0
C18: =B18/B$22*B$24 -> 0 | E18: =IFERROR(INDEX(Correspondance!$D$2:$D$3000,MATCH(A18,Correspondance!$A$2:$A$3000,0)),0) -> 0 | F18: =C18*E18 -> 0
F19: =SUM(F4:F18) -> 33.24458
A20: Prix unitaire portion | B20: =F19/B24 -> 0.30222346
A21: Poids total ou ingrédient principal | B21: =SUM(B3:B18) -> 12.602
A22: Nombre portions recette base | B22: =B21/B23 -> 70.011111
A23: Poids net portions | B23: 0.18 | C23: Possibilité de saisir le grammage
A24: Nombre portions à produire | B24: =Paramètres!$B$5 -> 110 | C24: Effectif EHPAD + FAM (feuille Paramètres) – possibilité de saisir un autre nombre

Sheet E-Pamplemousse
A1: Pamplemousse | E1: VP Théorique minimum | G1: Préparation froide Bac gastro + film, 0/+3°C
E2: Liaison froide 0/+3°C
A3: Produits | B3: Qté recette base | C3: Qté production | D3: U | E3: PU | F3: Total €
A4: Pamplemousse rose (≈ 400 g pièce, 1/2 par portion) | B4: 13.42 | C4: =B4/B$22*B$24 -> 21.094598 | D4: Kg | E4: =IFERROR(INDEX(Correspondance!$D$2:$D$3000,MATCH(A4,Correspondance!$A$2:$A$3000,0)),0) -> 2.25 | F4: =C4*E4 -> 47.462847 | G4: Mode opératoire : Laver et décontaminer les pamplemousses Couper en deux, détacher les quartiers de la membrane au couteau à pamplemousse Saupoudrer d'une pointe de sucre, 1 trait de grenadine, décorer d'une cerise confite et d'une feuille de menthe Texture modifiée : peler à vif et prélever les suprêmes, mixer ou détailler selon la texture prescrite Dresser en coupelles ou bacs gastro, filmer, étiqueter Stocker à 0/+3°C, service en liaison froide dans les 24h
A5: Sucre semoule | B5: 0.288 | C5: =B5/B$22*B$24 -> 0.45270077 | D5: Kg | E5: =IFERROR(INDEX(Correspondance!$D$2:$D$3000,MATCH(A5,Correspondance!$A$2:$A$3000,0)),0) -> 1.3 | F5: =C5*E5 -> 0.588511
A6: Sirop de grenadine | B6: 0.192 | C6: =B6/B$22*B$24 -> 0.30180051 | D6: L | E6: =IFERROR(INDEX(Correspondance!$D$2:$D$3000,MATCH(A6,Correspondance!$A$2:$A$3000,0)),0) -> 3.5 | F6: =C6*E6 -> 1.0563018
A7: Cerises confites | B7: 0.096 | C7: =B7/B$22*B$24 -> 0.15090026 | D7: Kg | E7: =IFERROR(INDEX(Correspondance!$D$2:$D$3000,MATCH(A7,Correspondance!$A$2:$A$3000,0)),0) -> 9 | F7: =C7*E7 -> 1.3581023
A8: Menthe fraîche PM | C8: =B8/B$22*B$24 -> 0 | D8: Kg | E8: =IFERROR(INDEX(Correspondance!$D$2:$D$3000,MATCH(A8,Correspondance!$A$2:$A$3000,0)),0) -> 30 | F8: =C8*E8 -> 0
A9: Citron jaune PM | C9: =B9/B$22*B$24 -> 0 | D9: Kg | E9: =IFERROR(INDEX(Correspondance!$D$2:$D$3000,MATCH(A9,Correspondance!$A$2:$A$3000,0)),0) -> 2.2 | F9: =C9*E9 -> 0
C10: =B10/B$22*B$24 -> 0 | E10: =IFERROR(INDEX(Correspondance!$D$2:$D$3000,MATCH(A10,Correspondance!$A$2:$A$3000,0)),0) -> 0 | F10: =C10*E10 -> 0
C11: =B11/B$22*B$24 -> 0 | E11: =IFERROR(INDEX(Correspondance!$D$2:$D$3000,MATCH(A11,Correspondance!$A$2:$A$3000,0)),0) -> 0 | F11: =C11*E11 -> 0
C12: =B12/B$22*B$24 -> 0 | E12: =IFERROR(INDEX(Correspondance!$D$2:$D$3000,MATCH(A12,Correspondance!$A$2:$A$3000,0)),0) -> 0 | F12: =C12*E12 -> 0
C13: =B13/B$22*B$24 -> 0 | E13: =IFERROR(INDEX(Correspondance!$D$2:$D$3000,MATCH(A13,Correspondance!$A$2:$A$3000,0)),0) -> 0 | F13: =C13*E13 -> 0
C14: =B14/B$22*B$24 -> 0 | E14: =IFERROR(INDEX(Correspondance!$D$2:$D$3000,MATCH(A14,Correspondance!$A$2:$A$3000,0)),0) -> 0 | F14: =C14*E14 -> 0
C15: =B15/B$22*B$24 -> 0 | E15: =IFERROR(INDEX(Correspondance!$D$2:$D$3000,MATCH(A15,Correspondance!$A$2:$A$3000,0)),0) -> 0 | F15: =C15*E15 -> 0
C16: =B16/B$22*B$24 -> 0 | E16: =IFERROR(INDEX(Correspondance!$D$2:$D$3000,MATCH(A16,Correspondance!$A$2:$A$3000,0)),0) -> 0 | F16: =C16*E16 -> 0
C17: =B17/B$22*B$24 -> 0 | E17: =IFERROR(INDEX(Correspondance!$D$2:$D$3000,MATCH(A17,Correspondance!$A$2:$A$3000,0)),0) -> 0 | F17: =C17*E17 -> 0
C18: =B18/B$22*B$24 -> 0 | E18: =IFERROR(INDEX(Correspondance!$D$2:$D$3000,MATCH(A18,Correspondance!$A$2:$A$3000,0)),0) -> 0 | F18: =C18*E18 -> 0
F19: =SUM(F4:F18) -> 50.465762
A20: Prix unitaire portion | B20: =F19/B24 -> 0.45877965
A21: Poids total ou ingrédient principal | B21: =SUM(B3:B18) -> 13.996
A22: Nombre portions recette base | B22: =B21/B23 -> 69.98
A23: Poids net portions | B23: 0.2 | C23: Possibilité de saisir le grammage
A24: Nombre portions à produire | B24: =Paramètres!$B$5 -> 110 | C24: Effectif EHPAD + FAM (feuille Paramètres) – possibilité de saisir un autre nombre

Sheet E-Poireaux vinaigrette
A1: Poireaux vinaigrette sous vide basse température | E1: VP Théorique minimum | G1: Sous vide 90°C four vapeur ou thermoplongeur Poches sous vide, 45 min à 1H00 Refroidissement cellule, DLC J+5
E2: > à 10 000
A3: Produits | B3: Qté recette base | C3: Qté production | D3: U | E3: PU | F3: Total €
A4: Blancs de poireaux | B4: 6.34 | C4: =B4/B$22*B$24 -> 9.9641512 | D4: Kg | E4: =IFERROR(INDEX(Correspondance!$D$2:$D$3000,MATCH(A4,Correspondance!$A$2:$A$3000,0)),0) -> 2 | F4: =C4*E4 -> 19.928302 | G4: Mode opératoire : Parer les poireaux, fendre en deux, laver abondamment pour éliminer le sable, tailler en tronçons de 8 cm Ranger à plat en poches sous vide (2 kg maximum), saler, mettre sous vide Cuisson : 90°C vapeur ou thermoplongeur 45 min à 1H00, contrôle de tendreté à la pointe du couteau Refroidir en cellule (63°C à 10°C en moins de deux heures), étiqueter, DLC 5 jours maximum (J+5) Le jour du service : ouvrir les poches, égoutter les poireaux sur grille Vinaigrette : moutarde, sel, poivre, vinaigre, monter à l'huile, ajouter les échalotes Dresser les poireaux en bacs gastro, napper de vinaigrette, parsemer d'œuf dur haché et de persil Filmer, stocker à 0/+3°C, service en liaison froide dans les 24h
A5: Huile de tournesol | B5: 0.453 | C5: =B5/B$22*B$24 -> 0.7119496 | D5: L | E5: =IFERROR(INDEX(Correspondance!$D$2:$D$3000,MATCH(A5,Correspondance!$A$2:$A$3000,0)),0) -> 2.2 | F5: =C5*E5 -> 1.5662891
A6: Vinaigre de vin | B6: 0.181 | C6: =B6/B$22*B$24 -> 0.28446552 | D6: L | E6: =IFERROR(INDEX(Correspondance!$D$2:$D$3000,MATCH(A6,Correspondance!$A$2:$A$3000,0)),0) -> 1.5 | F6: =C6*E6 -> 0.42669827
A7: Moutarde | B7: 0.091 | C7: =B7/B$22*B$24 -> 0.14301857 | D7: Kg | E7: =IFERROR(INDEX(Correspondance!$D$2:$D$3000,MATCH(A7,Correspondance!$A$2:$A$3000,0)),0) -> 9 | F7: =C7*E7 -> 1.2871672
A8: Échalotes ciselées surgelées | B8: 0.136 | C8: =B8/B$22*B$24 -> 0.21374204 | D8: Kg | E8: =IFERROR(INDEX(Correspondance!$D$2:$D$3000,MATCH(A8,Correspondance!$A$2:$A$3000,0)),0) -> 4.5 | F8: =C8*E8 -> 0.9618392
A9: Œufs durs écalés pasteurisés | B9: 0.453 | C9: =B9/B$22*B$24 -> 0.7119496 | D9: Kg | E9: =IFERROR(INDEX(Correspondance!$D$2:$D$3000,MATCH(A9,Correspondance!$A$2:$A$3000,0)),0) -> 5.6 | F9: =C9*E9 -> 3.9869178
A10: Sel | B10: 0.045 | C10: =B10/B$22*B$24 -> 0.070723471 | D10: Kg | E10: =IFERROR(INDEX(Correspondance!$D$2:$D$3000,MATCH(A10,Correspondance!$A$2:$A$3000,0)),0) -> 2 | F10: =C10*E10 -> 0.14144694
A11: Poivre PM | C11: =B11/B$22*B$24 -> 0 | D11: Kg | E11: =IFERROR(INDEX(Correspondance!$D$2:$D$3000,MATCH(A11,Correspondance!$A$2:$A$3000,0)),0) -> 18 | F11: =C11*E11 -> 0
A12: Persil haché PM | C12: =B12/B$22*B$24 -> 0 | D12: Kg | E12: =IFERROR(INDEX(Correspondance!$D$2:$D$3000,MATCH(A12,Correspondance!$A$2:$A$3000,0)),0) -> 8 | F12: =C12*E12 -> 0
C13: =B13/B$22*B$24 -> 0 | E13: =IFERROR(INDEX(Correspondance!$D$2:$D$3000,MATCH(A13,Correspondance!$A$2:$A$3000,0)),0) -> 0 | F13: =C13*E13 -> 0
C14: =B14/B$22*B$24 -> 0 | E14: =IFERROR(INDEX(Correspondance!$D$2:$D$3000,MATCH(A14,Correspondance!$A$2:$A$3000,0)),0) -> 0 | F14: =C14*E14 -> 0
C15: =B15/B$22*B$24 -> 0 | E15: =IFERROR(INDEX(Correspondance!$D$2:$D$3000,MATCH(A15,Correspondance!$A$2:$A$3000,0)),0) -> 0 | F15: =C15*E15 -> 0
C16: =B16/B$22*B$24 -> 0 | E16: =IFERROR(INDEX(Correspondance!$D$2:$D$3000,MATCH(A16,Correspondance!$A$2:$A$3000,0)),0) -> 0 | F16: =C16*E16 -> 0
C17: =B17/B$22*B$24 -> 0 | E17: =IFERROR(INDEX(Correspondance!$D$2:$D$3000,MATCH(A17,Correspondance!$A$2:$A$3000,0)),0) -> 0 | F17: =C17*E17 -> 0
C18: =B18/B$22*B$24 -> 0 | E18: =IFERROR(INDEX(Correspondance!$D$2:$D$3000,MATCH(A18,Correspondance!$A$2:$A$3000,0)),0) -> 0 | F18: =C18*E18 -> 0
F19: =SUM(F4:F18) -> 28.298661
A20: Prix unitaire portion | B20: =F19/B24 -> 0.25726055
A21: Poids total ou ingrédient principal | B21: =SUM(B3:B18) -> 7.699
A22: Nombre portions recette base | B22: =B21/B23 -> 69.990909
A23: Poids net portions | B23: 0.11 | C23: Possibilité de saisir le grammage
A24: Nombre portions à produire | B24: =Paramètres!$B$5 -> 110 | C24: Effectif EHPAD + FAM (feuille Paramètres) – possibilité de saisir un autre nombre

Sheet E-Avocat vinaigrette ou mayonna
A1: Avocat vinaigrette ou mayonnaise | E1: VP Théorique minimum | G1: Préparation froide Découpe au plus près du service Bac gastro + film, 0/+3°C
E2: Liaison froide 0/+3°C
A3: Produits | B3: Qté recette base | C3: Qté production | D3: U | E3: PU | F3: Total €
A4: Avocats mûrs (1/2 par portion) | B4: 6.7 | C4: =B4/B$22*B$24 -> 10.52356 | D4: Kg | E4: =IFERROR(INDEX(Correspondance!$D$2:$D$3000,MATCH(A4,Correspondance!$A$2:$A$3000,0)),0) -> 5.5 | F4: =C4*E4 -> 57.879581 | G4: Mode opératoire : Réceptionner des avocats à maturité, laver et décontaminer la peau Préparer la vinaigrette (moutarde, sel, poivre, vinaigre, huile) et la mayonnaise citronnée Couper les avocats en deux au plus près du service, dénoyauter, citronner immédiatement la chair Dresser 1/2 avocat par personne, garnir le creux de vinaigrette ou de mayonnaise selon le menu Texture modifiée : écraser la chair avec citron et mayonnaise, dresser à la poche Parsemer de ciboulette, filmer, étiqueter Stocker à 0/+3°C, service en liaison froide dans les 4 heures (oxydation rapide) Mayonnaise : exclusivement à base d'ovoproduits pasteurisés, conservation 0/+3°C
A5: Mayonnaise (ovoproduit pasteurisé) | B5: 0.957 | C5: =B5/B$22*B$24 -> 1.5031414 | D5: Kg | E5: =IFERROR(INDEX(Correspondance!$D$2:$D$3000,MATCH(A5,Correspondance!$A$2:$A$3000,0)),0) -> 4.5 | F5: =C5*E5 -> 6.7641361
A6: Huile de tournesol | B6: 0.287 | C6: =B6/B$22*B$24 -> 0.45078534 | D6: L | E6: =IFERROR(INDEX(Correspondance!$D$2:$D$3000,MATCH(A6,Correspondance!$A$2:$A$3000,0)),0) -> 2.2 | F6: =C6*E6 -> 0.99172775
A7: Vinaigre de vin | B7: 0.096 | C7: =B7/B$22*B$24 -> 0.15078534 | D7: L | E7: =IFERROR(INDEX(Correspondance!$D$2:$D$3000,MATCH(A7,Correspondance!$A$2:$A$3000,0)),0) -> 1.5 | F7: =C7*E7 -> 0.22617801
A8: Moutarde | B8: 0.048 | C8: =B8/B$22*B$24 -> 0.07539267 | D8: Kg | E8: =IFERROR(INDEX(Correspondance!$D$2:$D$3000,MATCH(A8,Correspondance!$A$2:$A$3000,0)),0) -> 9 | F8: =C8*E8 -> 0.67853403
A9: Jus de citron | B9: 0.287 | C9: =B9/B$22*B$24 -> 0.45078534 | D9: L | E9: =IFERROR(INDEX(Correspondance!$D$2:$D$3000,MATCH(A9,Correspondance!$A$2:$A$3000,0)),0) -> 2.5 | F9: =C9*E9 -> 1.1269634
A10: Sel | B10: 0.029 | C10: =B10/B$22*B$24 -> 0.045549738 | D10: Kg | E10: =IFERROR(INDEX(Correspondance!$D$2:$D$3000,MATCH(A10,Correspondance!$A$2:$A$3000,0)),0) -> 2 | F10: =C10*E10 -> 0.091099476
A11: Poivre PM | C11: =B11/B$22*B$24 -> 0 | D11: Kg | E11: =IFERROR(INDEX(Correspondance!$D$2:$D$3000,MATCH(A11,Correspondance!$A$2:$A$3000,0)),0) -> 18 | F11: =C11*E11 -> 0
A12: Ciboulette ciselée PM | C12: =B12/B$22*B$24 -> 0 | D12: Kg | E12: =IFERROR(INDEX(Correspondance!$D$2:$D$3000,MATCH(A12,Correspondance!$A$2:$A$3000,0)),0) -> 13 | F12: =C12*E12 -> 0
C13: =B13/B$22*B$24 -> 0 | E13: =IFERROR(INDEX(Correspondance!$D$2:$D$3000,MATCH(A13,Correspondance!$A$2:$A$3000,0)),0) -> 0 | F13: =C13*E13 -> 0
C14: =B14/B$22*B$24 -> 0 | E14: =IFERROR(INDEX(Correspondance!$D$2:$D$3000,MATCH(A14,Correspondance!$A$2:$A$3000,0)),0) -> 0 | F14: =C14*E14 -> 0
C15: =B15/B$22*B$24 -> 0 | E15: =IFERROR(INDEX(Correspondance!$D$2:$D$3000,MATCH(A15,Correspondance!$A$2:$A$3000,0)),0) -> 0 | F15: =C15*E15 -> 0
C16: =B16/B$22*B$24 -> 0 | E16: =IFERROR(INDEX(Correspondance!$D$2:$D$3000,MATCH(A16,Correspondance!$A$2:$A$3000,0)),0) -> 0 | F16: =C16*E16 -> 0
C17: =B17/B$22*B$24 -> 0 | E17: =IFERROR(INDEX(Correspondance!$D$2:$D$3000,MATCH(A17,Correspondance!$A$2:$A$3000,0)),0) -> 0 | F17: =C17*E17 -> 0
C18: =B18/B$22*B$24 -> 0 | E18: =IFERROR(INDEX(Correspondance!$D$2:$D$3000,MATCH(A18,Correspondance!$A$2:$A$3000,0)),0) -> 0 | F18: =C18*E18 -> 0
F19: =SUM(F4:F18) -> 67.75822
A20: Prix unitaire portion | B20: =F19/B24 -> 0.61598382
A21: Poids total ou ingrédient principal | B21: =SUM(B3:B18) -> 8.404
A22: Nombre portions recette base | B22: =B21/B23 -> 70.033333
A23: Poids net portions | B23: 0.12 | C23: Possibilité de saisir le grammage
A24: Nombre portions à produire | B24: =Paramètres!$B$5 -> 110 | C24: Effectif EHPAD + FAM (feuille Paramètres) – possibilité de saisir un autre nombre

Sheet E-Salade de lentilles
A1: Lentilles vinaigrette nuit cuisson de nuit | E1: VP Théorique minimum | G1: Cuisson nuit 93°C vapeur Bac gastro avec couvercles
E2: > à 10 000
A3: Produits | B3: Qté recette base | C3: Qté production | D3: U | E3: PU | F3: Total €
A4: Lentilles | B4: 1.76 | C4: =B4/B$23*B$25 -> 2.7657143 | D4: Kg | E4: =IFERROR(INDEX(Correspondance!$D$2:$D$3000,MATCH(A4,Correspondance!$A$2:$A$3000,0)),0) -> 3.2 | F4: =C4*E4 -> 8.8502857 | G4: Mode opératoire : Dans des bacs mettre tous les ingrédients (sauf ciboulette) Mélanger et ajouter un couvercle Cuisson : 93°C vapeur 12H00 minimum et 18h00 au maximum Refroidir en cellule (63°C à 10°C en moins de deux heures Finaliser l'assaisonnement avec la ciboulette avant le conditionnement
A5: Eau | B5: 3.52 | C5: =B5/B$23*B$25 -> 5.5314286 | D5: Kg | E5: =IFERROR(INDEX(Correspondance!$D$2:$D$3000,MATCH(A5,Correspondance!$A$2:$A$3000,0)),0) -> 0 | F5: =C5*E5 -> 0
A6: Brunoise | B6: 0.616 | C6: =B6/B$23*B$25 -> 0.968 | D6: Kg | E6: =IFERROR(INDEX(Correspondance!$D$2:$D$3000,MATCH(A6,Correspondance!$A$2:$A$3000,0)),0) -> 4 | F6: =C6*E6 -> 3.872
A7: Vinaigrette | B7: 0.792 | C7: =B7/B$23*B$25 -> 1.2445714 | D7: Kg | E7: =IFERROR(INDEX(Correspondance!$D$2:$D$3000,MATCH(A7,Correspondance!$A$2:$A$3000,0)),0) -> 3 | F7: =C7*E7 -> 3.7337143
A8: Sel | B8: 0.044 | C8: =B8/B$23*B$25 -> 0.069142857 | D8: Kg | E8: =IFERROR(INDEX(Correspondance!$D$2:$D$3000,MATCH(A8,Correspondance!$A$2:$A$3000,0)),0) -> 2 | F8: =C8*E8 -> 0.13828571
A9: Poivre | B9: 0.004 | C9: =B9/B$23*B$25 -> 0.0062857143 | D9: Kg | E9: =IFERROR(INDEX(Correspondance!$D$2:$D$3000,MATCH(A9,Correspondance!$A$2:$A$3000,0)),0) -> 18 | F9: =C9*E9 -> 0.11314286
C10: =B10/B$23*B$25 -> 0 | D10: Kg | F10: =C10*E10 -> 0
A11: Finition J+1 | C11: =B11/B$23*B$25 -> 0 | D11: Kg | E11: =IFERROR(INDEX(Correspondance!$D$2:$D$3000,MATCH(A11,Correspondance!$A$2:$A$3000,0)),0) -> 0 | F11: =C11*E11 -> 0
A12: Ciboulette surgelée | B12: 0.264 | C12: =B12/B$23*B$25 -> 0.41485714 | D12: Kg | E12: =IFERROR(INDEX(Correspondance!$D$2:$D$3000,MATCH(A12,Correspondance!$A$2:$A$3000,0)),0) -> 13 | F12: =C12*E12 -> 5.3931429
C13: =B13/B$23*B$25 -> 0 | F13: =C13*E13 -> 0
C14: =B14/B$23*B$25 -> 0 | F14: =C14*E14 -> 0
C15: =B15/B$23*B$25 -> 0 | F15: =C15*E15 -> 0
C16: =B16/B$23*B$25 -> 0 | F16: =C16*E16 -> 0
C17: =B17/B$23*B$25 -> 0 | F17: =C17*E17 -> 0
C18: =B18/B$23*B$25 -> 0 | F18: =C18*E18 -> 0
C19: =B19/B$23*B$25 -> 0 | F19: =C19*E19 -> 0
F20: =SUM(F4:F19) -> 22.100571
A21: Prix unitaire portion | B21: =F20/B25 -> 0.20091429
A22: Poids total ou ingrédient principal | B22: =SUM(B4:B19) -> 7
A23: Nombre portions recette base | B23: =B22/B24 -> 70
A24: Poids net portions | B24: 0.1 | C24: Possibilité de saisir le grammage
A25: Nombre portions à produire | B25: =Paramètres!$B$5 -> 110 | C25: Effectif EHPAD + FAM (feuille Paramètres) – possibilité de saisir un autre nombre

Sheet E-Terrine de légumes
A1: Terrine de légumes sous vide basse température | E1: VP Théorique minimum | G1: Cuisson 85°C four vapeur Moules à terrine ou bacs 1/3 filmés sous vide 1H30, 75°C à cœur
E2: > à 10 000
A3: Produits | B3: Qté recette base | C3: Qté production | D3: U | E3: PU | F3: Total €
A4: Carottes rondelles surgelées | B4: 2.35 | C4: =B4/B$22*B$24 -> 3.6969197 | D4: Kg | E4: =IFERROR(INDEX(Correspondance!$D$2:$D$3000,MATCH(A4,Correspondance!$A$2:$A$3000,0)),0) -> 1.8 | F4: =C4*E4 -> 6.6544554 | G4: Mode opératoire : Peser tous les ingrédients d'épicerie Cuire les légumes vapeur 100°C 8 à 10 min, égoutter, refroidir en cellule Appareil : mélanger œufs pasteurisés, crème, fécule délayée, sel, poivre, muscade Mixer la moitié des carottes et des brocolis avec l'appareil, garder le reste des légumes entiers pour le visuel Chemiser les moules à terrine ou bacs 1/3 de film cuisson, monter en couches (carottes, brocolis, haricots verts) en alternant avec l'appareil Filmer hermétiquement puis conditionner en poche sous vide Cuisson : 85°C vapeur 1H30, contrôle 75°C à cœur Refroidir en cellule (63°C à 10°C en moins de deux heures), réserver 12 heures à 0/+3°C avant démoulage, DLC J+5 en poche fermée Démouler, trancher 1 tranche de 130 g, servir avec un coulis de tomates ou une sauce fromage blanc ciboulette Service en liaison froide, consommation dans les 24h après ouverture
A5: Brocolis fleurettes surgelés | B5: 1.88 | C5: =B5/B$22*B$24 -> 2.9575358 | D5: Kg | E5: =IFERROR(INDEX(Correspondance!$D$2:$D$3000,MATCH(A5,Correspondance!$A$2:$A$3000,0)),0) -> 2.3 | F5: =C5*E5 -> 6.8023322
A6: Haricots verts surgelés | B6: 1.41 | C6: =B6/B$22*B$24 -> 2.2181518 | D6: Kg | E6: =IFERROR(INDEX(Correspondance!$D$2:$D$3000,MATCH(A6,Correspondance!$A$2:$A$3000,0)),0) -> 2.2 | F6: =C6*E6 -> 4.879934
A7: Œufs entiers liquides pasteurisés | B7: 1.88 | C7: =B7/B$22*B$24 -> 2.9575358 | D7: L | E7: =IFERROR(INDEX(Correspondance!$D$2:$D$3000,MATCH(A7,Correspondance!$A$2:$A$3000,0)),0) -> 3.8 | F7: =C7*E7 -> 11.238636
A8: Crème 35% | B8: 1.41 | C8: =B8/B$22*B$24 -> 2.2181518 | D8: L | E8: =IFERROR(INDEX(Correspondance!$D$2:$D$3000,MATCH(A8,Correspondance!$A$2:$A$3000,0)),0) -> 5.5 | F8: =C8*E8 -> 12.199835
A9: Fécule de pomme de terre | B9: 0.094 | C9: =B9/B$22*B$24 -> 0.14787679 | D9: Kg | E9: =IFERROR(INDEX(Correspondance!$D$2:$D$3000,MATCH(A9,Correspondance!$A$2:$A$3000,0)),0) -> 2.2 | F9: =C9*E9 -> 0.32532893
A10: Sel | B10: 0.066 | C10: =B10/B$22*B$24 -> 0.10382838 | D10: Kg | E10: =IFERROR(INDEX(Correspondance!$D$2:$D$3000,MATCH(A10,Correspondance!$A$2:$A$3000,0)),0) -> 2 | F10: =C10*E10 -> 0.20765677
A11: Poivre PM | C11: =B11/B$22*B$24 -> 0 | D11: Kg | E11: =IFERROR(INDEX(Correspondance!$D$2:$D$3000,MATCH(A11,Correspondance!$A$2:$A$3000,0)),0) -> 18 | F11: =C11*E11 -> 0
A12: Muscade PM | C12: =B12/B$22*B$24 -> 0 | D12: Kg | E12: =IFERROR(INDEX(Correspondance!$D$2:$D$3000,MATCH(A12,Correspondance!$A$2:$A$3000,0)),0) -> 30 | F12: =C12*E12 -> 0
A13: Ciboulette ciselée PM | C13: =B13/B$22*B$24 -> 0 | D13: Kg | E13: =IFERROR(INDEX(Correspondance!$D$2:$D$3000,MATCH(A13,Correspondance!$A$2:$A$3000,0)),0) -> 13 | F13: =C13*E13 -> 0
C14: =B14/B$22*B$24 -> 0 | E14: =IFERROR(INDEX(Correspondance!$D$2:$D$3000,MATCH(A14,Correspondance!$A$2:$A$3000,0)),0) -> 0 | F14: =C14*E14 -> 0
C15: =B15/B$22*B$24 -> 0 | E15: =IFERROR(INDEX(Correspondance!$D$2:$D$3000,MATCH(A15,Correspondance!$A$2:$A$3000,0)),0) -> 0 | F15: =C15*E15 -> 0
C16: =B16/B$22*B$24 -> 0 | E16: =IFERROR(INDEX(Correspondance!$D$2:$D$3000,MATCH(A16,Correspondance!$A$2:$A$3000,0)),0) -> 0 | F16: =C16*E16 -> 0
C17: =B17/B$22*B$24 -> 0 | E17: =IFERROR(INDEX(Correspondance!$D$2:$D$3000,MATCH(A17,Correspondance!$A$2:$A$3000,0)),0) -> 0 | F17: =C17*E17 -> 0
C18: =B18/B$22*B$24 -> 0 | E18: =IFERROR(INDEX(Correspondance!$D$2:$D$3000,MATCH(A18,Correspondance!$A$2:$A$3000,0)),0) -> 0 | F18: =C18*E18 -> 0
F19: =SUM(F4:F18) -> 42.308178
A20: Prix unitaire portion | B20: =F19/B24 -> 0.3846198
A21: Poids total ou ingrédient principal | B21: =SUM(B3:B18) -> 9.09
A22: Nombre portions recette base | B22: =B21/B23 -> 69.923077
A23: Poids net portions | B23: 0.13 | C23: Possibilité de saisir le grammage
A24: Nombre portions à produire | B24: =Paramètres!$B$5 -> 110 | C24: Effectif EHPAD + FAM (feuille Paramètres) – possibilité de saisir un autre nombre

Sheet E-Salade de pois chiches
A1: Salade de pois chiches cuisson de nuit | E1: VP Théorique minimum | G1: Cuisson 95°C four vapeur Bac gastro avec couvercles Ou cuisson sauteuse (compatible cuisson de nuit)
E2: > à 10 000
A3: Produits | B3: Qté recette base | C3: Qté production | D3: U | E3: PU | F3: Total €
A4: Pois chiches secs | B4: 1.47 | C4: =B4/B$22*B$24 -> 2.310275 | D4: Kg | E4: =IFERROR(INDEX(Correspondance!$D$2:$D$3000,MATCH(A4,Correspondance!$A$2:$A$3000,0)),0) -> 3.2 | F4: =C4*E4 -> 7.3928801 | G4: Mode opératoire : Rincer les pois chiches (trempage 12 heures facultatif, non nécessaire en cuisson de nuit) Four : dans des bacs 1/1 (H15) mettre pois chiches, eau, sel et une pincée de bicarbonate (quantités pour un bac) Mélanger et ajouter un couvercle sans trou Cuisson : 95°C vapeur 12H00 minimum et 18H00 au maximum Le lendemain : égoutter, refroidir en cellule (63°C à 10°C en moins de deux heures), réserver à 0/+3°C Décontaminer et tailler les tomates, décongeler et égoutter les poivrons Sauce : jus de citron, sel, cumin, poivre, monter à l'huile d'olive Mélanger pois chiches froids, légumes, oignons rouges et sauce, laisser mariner 1 heure Conditionner en bacs gastro filmés, herbes au service, consommation dans les 48h Sauteuse (compatible cuisson de nuit) : tous les ingrédients, couvrir, 95°C fonction mijotage 12H00 à 18H00
A5: Eau | B5: 4.41 | C5: =B5/B$22*B$24 -> 6.9308251 | D5: L | E5: =IFERROR(INDEX(Correspondance!$D$2:$D$3000,MATCH(A5,Correspondance!$A$2:$A$3000,0)),0) -> 0 | F5: =C5*E5 -> 0
A6: Sel | B6: 0.049 | C6: =B6/B$22*B$24 -> 0.077009168 | D6: Kg | E6: =IFERROR(INDEX(Correspondance!$D$2:$D$3000,MATCH(A6,Correspondance!$A$2:$A$3000,0)),0) -> 2 | F6: =C6*E6 -> 0.15401834
A7: Bicarbonate de soude PM | C7: =B7/B$22*B$24 -> 0 | D7: Kg | E7: =IFERROR(INDEX(Correspondance!$D$2:$D$3000,MATCH(A7,Correspondance!$A$2:$A$3000,0)),0) -> 3 | F7: =C7*E7 -> 0
A8: Tomates en cubes | B8: 0.98 | C8: =B8/B$22*B$24 -> 1.5401834 | D8: Kg | E8: =IFERROR(INDEX(Correspondance!$D$2:$D$3000,MATCH(A8,Correspondance!$A$2:$A$3000,0)),0) -> 1.5 | F8: =C8*E8 -> 2.310275
A9: Poivrons dés surgelés | B9: 0.49 | C9: =B9/B$22*B$24 -> 0.77009168 | D9: Kg | E9: =IFERROR(INDEX(Correspondance!$D$2:$D$3000,MATCH(A9,Correspondance!$A$2:$A$3000,0)),0) -> 3 | F9: =C9*E9 -> 2.310275
A10: Oignons rouges émincés | B10: 0.294 | C10: =B10/B$22*B$24 -> 0.46205501 | D10: Kg | E10: =IFERROR(INDEX(Correspondance!$D$2:$D$3000,MATCH(A10,Correspondance!$A$2:$A$3000,0)),0) -> 1.8 | F10: =C10*E10 -> 0.83169901
A11: Huile d'olive | B11: 0.392 | C11: =B11/B$22*B$24 -> 0.61607334 | D11: L | E11: =IFERROR(INDEX(Correspondance!$D$2:$D$3000,MATCH(A11,Correspondance!$A$2:$A$3000,0)),0) -> 7.5 | F11: =C11*E11 -> 4.6205501
A12: Jus de citron | B12: 0.294 | C12: =B12/B$22*B$24 -> 0.46205501 | D12: L | E12: =IFERROR(INDEX(Correspondance!$D$2:$D$3000,MATCH(A12,Correspondance!$A$2:$A$3000,0)),0) -> 2.5 | F12: =C12*E12 -> 1.1551375
A13: Cumin moulu | B13: 0.02 | C13: =B13/B$22*B$24 -> 0.031432313 | D13: Kg | E13: =IFERROR(INDEX(Correspondance!$D$2:$D$3000,MATCH(A13,Correspondance!$A$2:$A$3000,0)),0) -> 12 | F13: =C13*E13 -> 0.37718776
A14: Poivre PM | C14: =B14/B$22*B$24 -> 0 | D14: Kg | E14: =IFERROR(INDEX(Correspondance!$D$2:$D$3000,MATCH(A14,Correspondance!$A$2:$A$3000,0)),0) -> 18 | F14: =C14*E14 -> 0
A15: Coriandre ou persil haché PM | C15: =B15/B$22*B$24 -> 0 | D15: Kg | E15: =IFERROR(INDEX(Correspondance!$D$2:$D$3000,MATCH(A15,Correspondance!$A$2:$A$3000,0)),0) -> 13 | F15: =C15*E15 -> 0
C16: =B16/B$22*B$24 -> 0 | E16: =IFERROR(INDEX(Correspondance!$D$2:$D$3000,MATCH(A16,Correspondance!$A$2:$A$3000,0)),0) -> 0 | F16: =C16*E16 -> 0
C17: =B17/B$22*B$24 -> 0 | E17: =IFERROR(INDEX(Correspondance!$D$2:$D$3000,MATCH(A17,Correspondance!$A$2:$A$3000,0)),0) -> 0 | F17: =C17*E17 -> 0
C18: =B18/B$22*B$24 -> 0 | E18: =IFERROR(INDEX(Correspondance!$D$2:$D$3000,MATCH(A18,Correspondance!$A$2:$A$3000,0)),0) -> 0 | F18: =C18*E18 -> 0
F19: =SUM(F4:F18) -> 19.152023
A20: Prix unitaire portion | B20: =F19/B24 -> 0.1741093
A21: Poids total ou ingrédient principal | B21: =SUM(B3:B18) -> 8.399
A22: Nombre portions recette base | B22: =B21/B23 -> 69.991667
A23: Poids net portions | B23: 0.12 | C23: Possibilité de saisir le grammage
A24: Nombre portions à produire | B24: =Paramètres!$B$5 -> 110 | C24: Effectif EHPAD + FAM (feuille Paramètres) – possibilité de saisir un autre nombre

Sheet E-Macédoine mayonnaise
A1: Macédoine mayonnaise | E1: VP Théorique minimum | G1: Préparation froide Macédoine appertisée égouttée Bac gastro + film, 0/+3°C
E2: Liaison froide 0/+3°C
A3: Produits | B3: Qté recette base | C3: Qté production | D3: U | E3: PU | F3: Total €
A4: Macédoine de légumes appertisée égouttée | B4: 5.34 | C4: =B4/B$22*B$24 -> 8.3842421 | D4: Kg | E4: =IFERROR(INDEX(Correspondance!$D$2:$D$3000,MATCH(A4,Correspondance!$A$2:$A$3000,0)),0) -> 2 | F4: =C4*E4 -> 16.768484 | G4: Mode opératoire : Ouvrir les boîtes, égoutter et rincer la macédoine, laisser égoutter 30 min sur grille au froid Détendre la mayonnaise avec la moutarde, le jus de citron, sel et poivre Mélanger délicatement la macédoine et la mayonnaise sans écraser les légumes Rectifier l'assaisonnement Conditionner en bacs gastro, décorer de quartiers d'œuf dur et de persil, filmer, étiqueter Stocker à 0/+3°C, service en liaison froide dans les 24h Mayonnaise exclusivement à base d'ovoproduits pasteurisés, ne jamais rompre la chaîne du froid
A5: Mayonnaise (ovoproduit pasteurisé) | B5: 1.07 | C5: =B5/B$22*B$24 -> 1.6799886 | D5: Kg | E5: =IFERROR(INDEX(Correspondance!$D$2:$D$3000,MATCH(A5,Correspondance!$A$2:$A$3000,0)),0) -> 4.5 | F5: =C5*E5 -> 7.5599486
A6: Œufs durs écalés pasteurisés | B6: 0.445 | C6: =B6/B$22*B$24 -> 0.69868684 | D6: Kg | E6: =IFERROR(INDEX(Correspondance!$D$2:$D$3000,MATCH(A6,Correspondance!$A$2:$A$3000,0)),0) -> 5.6 | F6: =C6*E6 -> 3.9126463
A7: Moutarde | B7: 0.044 | C7: =B7/B$22*B$24 -> 0.069083643 | D7: Kg | E7: =IFERROR(INDEX(Correspondance!$D$2:$D$3000,MATCH(A7,Correspondance!$A$2:$A$3000,0)),0) -> 9 | F7: =C7*E7 -> 0.62175278
A8: Jus de citron | B8: 0.089 | C8: =B8/B$22*B$24 -> 0.13973737 | D8: L | E8: =IFERROR(INDEX(Correspondance!$D$2:$D$3000,MATCH(A8,Correspondance!$A$2:$A$3000,0)),0) -> 2.5 | F8: =C8*E8 -> 0.34934342
A9: Sel | B9: 0.018 | C9: =B9/B$22*B$24 -> 0.02826149 | D9: Kg | E9: =IFERROR(INDEX(Correspondance!$D$2:$D$3000,MATCH(A9,Correspondance!$A$2:$A$3000,0)),0) -> 2 | F9: =C9*E9 -> 0.05652298
A10: Poivre PM | C10: =B10/B$22*B$24 -> 0 | D10: Kg | E10: =IFERROR(INDEX(Correspondance!$D$2:$D$3000,MATCH(A10,Correspondance!$A$2:$A$3000,0)),0) -> 18 | F10: =C10*E10 -> 0
A11: Persil haché PM | C11: =B11/B$22*B$24 -> 0 | D11: Kg | E11: =IFERROR(INDEX(Correspondance!$D$2:$D$3000,MATCH(A11,Correspondance!$A$2:$A$3000,0)),0) -> 8 | F11: =C11*E11 -> 0
C12: =B12/B$22*B$24 -> 0 | E12: =IFERROR(INDEX(Correspondance!$D$2:$D$3000,MATCH(A12,Correspondance!$A$2:$A$3000,0)),0) -> 0 | F12: =C12*E12 -> 0
C13: =B13/B$22*B$24 -> 0 | E13: =IFERROR(INDEX(Correspondance!$D$2:$D$3000,MATCH(A13,Correspondance!$A$2:$A$3000,0)),0) -> 0 | F13: =C13*E13 -> 0
C14: =B14/B$22*B$24 -> 0 | E14: =IFERROR(INDEX(Correspondance!$D$2:$D$3000,MATCH(A14,Correspondance!$A$2:$A$3000,0)),0) -> 0 | F14: =C14*E14 -> 0
C15: =B15/B$22*B$24 -> 0 | E15: =IFERROR(INDEX(Correspondance!$D$2:$D$3000,MATCH(A15,Correspondance!$A$2:$A$3000,0)),0) -> 0 | F15: =C15*E15 -> 0
C16: =B16/B$22*B$24 -> 0 | E16: =IFERROR(INDEX(Correspondance!$D$2:$D$3000,MATCH(A16,Correspondance!$A$2:$A$3000,0)),0) -> 0 | F16: =C16*E16 -> 0
C17: =B17/B$22*B$24 -> 0 | E17: =IFERROR(INDEX(Correspondance!$D$2:$D$3000,MATCH(A17,Correspondance!$A$2:$A$3000,0)),0) -> 0 | F17: =C17*E17 -> 0
C18: =B18/B$22*B$24 -> 0 | E18: =IFERROR(INDEX(Correspondance!$D$2:$D$3000,MATCH(A18,Correspondance!$A$2:$A$3000,0)),0) -> 0 | F18: =C18*E18 -> 0
F19: =SUM(F4:F18) -> 29.268698
A20: Prix unitaire portion | B20: =F19/B24 -> 0.26607908
A21: Poids total ou ingrédient principal | B21: =SUM(B3:B18) -> 7.006
A22: Nombre portions recette base | B22: =B21/B23 -> 70.06
A23: Poids net portions | B23: 0.1 | C23: Possibilité de saisir le grammage
A24: Nombre portions à produire | B24: =Paramètres!$B$5 -> 110 | C24: Effectif EHPAD + FAM (feuille Paramètres) – possibilité de saisir un autre nombre

Sheet E-Salade de mâche
A1: Salade de mâche | E1: VP Théorique minimum | G1: Préparation froide Bac gastro + film, 0/+3°C Vinaigrette à part
E2: Liaison froide 0/+3°C
A3: Produits | B3: Qté recette base | C3: Qté production | D3: U | E3: PU | F3: Total €
A4: Mâche | B4: 3.13 | C4: =B4/B$22*B$24 -> 4.9244338 | D4: Kg | E4: =IFERROR(INDEX(Correspondance!$D$2:$D$3000,MATCH(A4,Correspondance!$A$2:$A$3000,0)),0) -> 9.5 | F4: =C4*E4 -> 46.782122 | G4: Mode opératoire : Trier la mâche, retirer les racines et les feuilles jaunes Décontamination : trempage 5 min en eau + désinfectant agréé, rinçage abondant, essorage délicat Vinaigrette : moutarde, sel, poivre, vinaigre de xérès, monter à l'huile de colza, ajouter les échalotes Conditionner la mâche en bacs gastro filmés, vinaigrette et croûtons à part Stocker à 0/+3°C, assaisonner et parsemer de croûtons au dernier moment Service en liaison froide, consommation dans les 24h
A5: Croûtons | B5: 0.313 | C5: =B5/B$22*B$24 -> 0.49244338 | D5: Kg | E5: =IFERROR(INDEX(Correspondance!$D$2:$D$3000,MATCH(A5,Correspondance!$A$2:$A$3000,0)),0) -> 6 | F5: =C5*E5 -> 2.9546603
A6: Huile de colza | B6: 0.418 | C6: =B6/B$22*B$24 -> 0.65764005 | D6: L | E6: =IFERROR(INDEX(Correspondance!$D$2:$D$3000,MATCH(A6,Correspondance!$A$2:$A$3000,0)),0) -> 2.3 | F6: =C6*E6 -> 1.5125721
A7: Vinaigre de xérès | B7: 0.157 | C7: =B7/B$22*B$24 -> 0.24700834 | D7: L | E7: =IFERROR(INDEX(Correspondance!$D$2:$D$3000,MATCH(A7,Correspondance!$A$2:$A$3000,0)),0) -> 6 | F7: =C7*E7 -> 1.4820501
A8: Moutarde | B8: 0.052 | C8: =B8/B$22*B$24 -> 0.081811681 | D8: Kg | E8: =IFERROR(INDEX(Correspondance!$D$2:$D$3000,MATCH(A8,Correspondance!$A$2:$A$3000,0)),0) -> 9 | F8: =C8*E8 -> 0.73630513
A9: Échalotes ciselées surgelées | B9: 0.104 | C9: =B9/B$22*B$24 -> 0.16362336 | D9: Kg | E9: =IFERROR(INDEX(Correspondance!$D$2:$D$3000,MATCH(A9,Correspondance!$A$2:$A$3000,0)),0) -> 4.5 | F9: =C9*E9 -> 0.73630513
A10: Sel | B10: 0.021 | C10: =B10/B$22*B$24 -> 0.033039333 | D10: Kg | E10: =IFERROR(INDEX(Correspondance!$D$2:$D$3000,MATCH(A10,Correspondance!$A$2:$A$3000,0)),0) -> 2 | F10: =C10*E10 -> 0.066078665
A11: Poivre PM | C11: =B11/B$22*B$24 -> 0 | D11: Kg | E11: =IFERROR(INDEX(Correspondance!$D$2:$D$3000,MATCH(A11,Correspondance!$A$2:$A$3000,0)),0) -> 18 | F11: =C11*E11 -> 0
C12: =B12/B$22*B$24 -> 0 | E12: =IFERROR(INDEX(Correspondance!$D$2:$D$3000,MATCH(A12,Correspondance!$A$2:$A$3000,0)),0) -> 0 | F12: =C12*E12 -> 0
C13: =B13/B$22*B$24 -> 0 | E13: =IFERROR(INDEX(Correspondance!$D$2:$D$3000,MATCH(A13,Correspondance!$A$2:$A$3000,0)),0) -> 0 | F13: =C13*E13 -> 0
C14: =B14/B$22*B$24 -> 0 | E14: =IFERROR(INDEX(Correspondance!$D$2:$D$3000,MATCH(A14,Correspondance!$A$2:$A$3000,0)),0) -> 0 | F14: =C14*E14 -> 0
C15: =B15/B$22*B$24 -> 0 | E15: =IFERROR(INDEX(Correspondance!$D$2:$D$3000,MATCH(A15,Correspondance!$A$2:$A$3000,0)),0) -> 0 | F15: =C15*E15 -> 0
C16: =B16/B$22*B$24 -> 0 | E16: =IFERROR(INDEX(Correspondance!$D$2:$D$3000,MATCH(A16,Correspondance!$A$2:$A$3000,0)),0) -> 0 | F16: =C16*E16 -> 0
C17: =B17/B$22*B$24 -> 0 | E17: =IFERROR(INDEX(Correspondance!$D$2:$D$3000,MATCH(A17,Correspondance!$A$2:$A$3000,0)),0) -> 0 | F17: =C17*E17 -> 0
C18: =B18/B$22*B$24 -> 0 | E18: =IFERROR(INDEX(Correspondance!$D$2:$D$3000,MATCH(A18,Correspondance!$A$2:$A$3000,0)),0) -> 0 | F18: =C18*E18 -> 0
F19: =SUM(F4:F18) -> 54.270093
A20: Prix unitaire portion | B20: =F19/B24 -> 0.49336448
A21: Poids total ou ingrédient principal | B21: =SUM(B3:B18) -> 4.195
A22: Nombre portions recette base | B22: =B21/B23 -> 69.916667
A23: Poids net portions | B23: 0.06 | C23: Possibilité de saisir le grammage
A24: Nombre portions à produire | B24: =Paramètres!$B$5 -> 110 | C24: Effectif EHPAD + FAM (feuille Paramètres) – possibilité de saisir un autre nombre

Sheet E-Mâche et tartine de chèvre ch
A1: Mâche et tartine de chèvre chaud | E1: VP Théorique minimum | G1: Four mixte 200°C chaleur sèche Plaques gastro + papier cuisson 6 à 8 min
E2: 63°C à cœur
A3: Produits | B3: Qté recette base | C3: Qté production | D3: U | E3: PU | F3: Total €
A4: Mâche | B4: 2.32 | C4: =B4/B$22*B$24 -> 3.6445986 | D4: Kg | E4: =IFERROR(INDEX(Correspondance!$D$2:$D$3000,MATCH(A4,Correspondance!$A$2:$A$3000,0)),0) -> 9.5 | F4: =C4*E4 -> 34.623687 | G4: Mode opératoire : Trier, décontaminer, rincer et essorer la mâche, réserver à 0/+3°C Vinaigrette : moutarde, sel, poivre, vinaigre, monter à l'huile de noix Disposer les tranches de pain sur plaques gastro + papier cuisson, poser 1 rondelle de chèvre de 50 g par tranche, thym, poivre Four mixte 200°C chaleur sèche 6 à 8 min jusqu'à coloration du chèvre, contrôle 63°C à cœur Napper d'un filet de miel à la sortie du four Dressage immédiat : mâche assaisonnée, 1 tartine chaude, noix concassées Servir sans attente (pas de maintien prolongé, pas de refroidissement : préparation à consommer dès cuisson) Texture modifiée : chèvre fondu sur mie de pain sans croûte, mâche hachée
A5: Pain de campagne tranché (50 g la tranche) | B5: 3.25 | C5: =B5/B$22*B$24 -> 5.1055799 | D5: Kg | E5: =IFERROR(INDEX(Correspondance!$D$2:$D$3000,MATCH(A5,Correspondance!$A$2:$A$3000,0)),0) -> 3 | F5: =C5*E5 -> 15.31674
A6: Bûche de chèvre (50 g par tartine) | B6: 3.25 | C6: =B6/B$22*B$24 -> 5.1055799 | D6: Kg | E6: =IFERROR(INDEX(Correspondance!$D$2:$D$3000,MATCH(A6,Correspondance!$A$2:$A$3000,0)),0) -> 11 | F6: =C6*E6 -> 56.161379
A7: Miel | B7: 0.278 | C7: =B7/B$22*B$24 -> 0.43672345 | D7: Kg | E7: =IFERROR(INDEX(Correspondance!$D$2:$D$3000,MATCH(A7,Correspondance!$A$2:$A$3000,0)),0) -> 7.5 | F7: =C7*E7 -> 3.2754259
A8: Cerneaux de noix | B8: 0.278 | C8: =B8/B$22*B$24 -> 0.43672345 | D8: Kg | E8: =IFERROR(INDEX(Correspondance!$D$2:$D$3000,MATCH(A8,Correspondance!$A$2:$A$3000,0)),0) -> 14 | F8: =C8*E8 -> 6.1141283
A9: Huile de noix | B9: 0.278 | C9: =B9/B$22*B$24 -> 0.43672345 | D9: L | E9: =IFERROR(INDEX(Correspondance!$D$2:$D$3000,MATCH(A9,Correspondance!$A$2:$A$3000,0)),0) -> 12 | F9: =C9*E9 -> 5.2406814
A10: Vinaigre de cidre | B10: 0.093 | C10: =B10/B$22*B$24 -> 0.14609813 | D10: L | E10: =IFERROR(INDEX(Correspondance!$D$2:$D$3000,MATCH(A10,Correspondance!$A$2:$A$3000,0)),0) -> 1.8 | F10: =C10*E10 -> 0.26297664
A11: Moutarde | B11: 0.037 | C11: =B11/B$22*B$24 -> 0.058125064 | D11: Kg | E11: =IFERROR(INDEX(Correspondance!$D$2:$D$3000,MATCH(A11,Correspondance!$A$2:$A$3000,0)),0) -> 9 | F11: =C11*E11 -> 0.52312557
A12: Sel | B12: 0.019 | C12: =B12/B$22*B$24 -> 0.029848006 | D12: Kg | E12: =IFERROR(INDEX(Correspondance!$D$2:$D$3000,MATCH(A12,Correspondance!$A$2:$A$3000,0)),0) -> 2 | F12: =C12*E12 -> 0.059696011
A13: Poivre PM | C13: =B13/B$22*B$24 -> 0 | D13: Kg | E13: =IFERROR(INDEX(Correspondance!$D$2:$D$3000,MATCH(A13,Correspondance!$A$2:$A$3000,0)),0) -> 18 | F13: =C13*E13 -> 0
A14: Thym PM | C14: =B14/B$22*B$24 -> 0 | D14: Kg | E14: =IFERROR(INDEX(Correspondance!$D$2:$D$3000,MATCH(A14,Correspondance!$A$2:$A$3000,0)),0) -> 16 | F14: =C14*E14 -> 0
C15: =B15/B$22*B$24 -> 0 | E15: =IFERROR(INDEX(Correspondance!$D$2:$D$3000,MATCH(A15,Correspondance!$A$2:$A$3000,0)),0) -> 0 | F15: =C15*E15 -> 0
C16: =B16/B$22*B$24 -> 0 | E16: =IFERROR(INDEX(Correspondance!$D$2:$D$3000,MATCH(A16,Correspondance!$A$2:$A$3000,0)),0) -> 0 | F16: =C16*E16 -> 0
C17: =B17/B$22*B$24 -> 0 | E17: =IFERROR(INDEX(Correspondance!$D$2:$D$3000,MATCH(A17,Correspondance!$A$2:$A$3000,0)),0) -> 0 | F17: =C17*E17 -> 0
C18: =B18/B$22*B$24 -> 0 | E18: =IFERROR(INDEX(Correspondance!$D$2:$D$3000,MATCH(A18,Correspondance!$A$2:$A$3000,0)),0) -> 0 | F18: =C18*E18 -> 0
F19: =SUM(F4:F18) -> 121.57784
A20: Prix unitaire portion | B20: =F19/B24 -> 1.1052531
A21: Poids total ou ingrédient principal | B21: =SUM(B3:B18) -> 9.803
A22: Nombre portions recette base | B22: =B21/B23 -> 70.021429
A23: Poids net portions | B23: 0.14 | C23: Possibilité de saisir le grammage
A24: Nombre portions à produire | B24: =Paramètres!$B$5 -> 110 | C24: Effectif EHPAD + FAM (feuille Paramètres) – possibilité de saisir un autre nombre

Sheet E-Carottes râpées
A1: Carottes râpées | E1: VP Théorique minimum | G1: Préparation froide Bac gastro + film, 0/+3°C
E2: Liaison froide 0/+3°C
A3: Produits | B3: Qté recette base | C3: Qté production | D3: U | E3: PU | F3: Total €
A4: Carottes | B4: 5.31 | C4: =B4/B$22*B$24 -> 8.3442857 | D4: Kg | E4: =IFERROR(INDEX(Correspondance!$D$2:$D$3000,MATCH(A4,Correspondance!$A$2:$A$3000,0)),0) -> 1 | F4: =C4*E4 -> 8.3442857 | G4: Mode opératoire : Éplucher les carottes, décontaminer, rincer à l'eau claire Râper au robot coupe (grille fine) Sauce : jus de citron, moutarde, sel, sucre, poivre, monter à l'huile Mélanger carottes, sauce et raisins secs, laisser mariner 1 heure à 0/+3°C Rectifier l'assaisonnement Conditionner en bacs gastro filmés, étiqueter, herbes au service Stocker à 0/+3°C, service en liaison froide dans les 48h
A5: Huile de tournesol | B5: 0.442 | C5: =B5/B$22*B$24 -> 0.69457143 | D5: L | E5: =IFERROR(INDEX(Correspondance!$D$2:$D$3000,MATCH(A5,Correspondance!$A$2:$A$3000,0)),0) -> 2.2 | F5: =C5*E5 -> 1.5280571
A6: Jus de citron | B6: 0.265 | C6: =B6/B$22*B$24 -> 0.41642857 | D6: L | E6: =IFERROR(INDEX(Correspondance!$D$2:$D$3000,MATCH(A6,Correspondance!$A$2:$A$3000,0)),0) -> 2.5 | F6: =C6*E6 -> 1.0410714
A7: Moutarde | B7: 0.044 | C7: =B7/B$22*B$24 -> 0.069142857 | D7: Kg | E7: =IFERROR(INDEX(Correspondance!$D$2:$D$3000,MATCH(A7,Correspondance!$A$2:$A$3000,0)),0) -> 9 | F7: =C7*E7 -> 0.62228571
A8: Raisins secs (facultatif) | B8: 0.177 | C8: =B8/B$22*B$24 -> 0.27814286 | D8: Kg | E8: =IFERROR(INDEX(Correspondance!$D$2:$D$3000,MATCH(A8,Correspondance!$A$2:$A$3000,0)),0) -> 5 | F8: =C8*E8 -> 1.3907143
A9: Sucre | B9: 0.027 | C9: =B9/B$22*B$24 -> 0.042428571 | D9: Kg | E9: =IFERROR(INDEX(Correspondance!$D$2:$D$3000,MATCH(A9,Correspondance!$A$2:$A$3000,0)),0) -> 1.3 | F9: =C9*E9 -> 0.055157143
A10: Sel | B10: 0.035 | C10: =B10/B$22*B$24 -> 0.055 | D10: Kg | E10: =IFERROR(INDEX(Correspondance!$D$2:$D$3000,MATCH(A10,Correspondance!$A$2:$A$3000,0)),0) -> 2 | F10: =C10*E10 -> 0.11
A11: Poivre PM | C11: =B11/B$22*B$24 -> 0 | D11: Kg | E11: =IFERROR(INDEX(Correspondance!$D$2:$D$3000,MATCH(A11,Correspondance!$A$2:$A$3000,0)),0) -> 18 | F11: =C11*E11 -> 0
A12: Persil ou ciboulette PM | C12: =B12/B$22*B$24 -> 0 | D12: Kg | E12: =IFERROR(INDEX(Correspondance!$D$2:$D$3000,MATCH(A12,Correspondance!$A$2:$A$3000,0)),0) -> 8 | F12: =C12*E12 -> 0
C13: =B13/B$22*B$24 -> 0 | E13: =IFERROR(INDEX(Correspondance!$D$2:$D$3000,MATCH(A13,Correspondance!$A$2:$A$3000,0)),0) -> 0 | F13: =C13*E13 -> 0
C14: =B14/B$22*B$24 -> 0 | E14: =IFERROR(INDEX(Correspondance!$D$2:$D$3000,MATCH(A14,Correspondance!$A$2:$A$3000,0)),0) -> 0 | F14: =C14*E14 -> 0
C15: =B15/B$22*B$24 -> 0 | E15: =IFERROR(INDEX(Correspondance!$D$2:$D$3000,MATCH(A15,Correspondance!$A$2:$A$3000,0)),0) -> 0 | F15: =C15*E15 -> 0
C16: =B16/B$22*B$24 -> 0 | E16: =IFERROR(INDEX(Correspondance!$D$2:$D$3000,MATCH(A16,Correspondance!$A$2:$A$3000,0)),0) -> 0 | F16: =C16*E16 -> 0
C17: =B17/B$22*B$24 -> 0 | E17: =IFERROR(INDEX(Correspondance!$D$2:$D$3000,MATCH(A17,Correspondance!$A$2:$A$3000,0)),0) -> 0 | F17: =C17*E17 -> 0
C18: =B18/B$22*B$24 -> 0 | E18: =IFERROR(INDEX(Correspondance!$D$2:$D$3000,MATCH(A18,Correspondance!$A$2:$A$3000,0)),0) -> 0 | F18: =C18*E18 -> 0
F19: =SUM(F4:F18) -> 13.091571
A20: Prix unitaire portion | B20: =F19/B24 -> 0.11901429
A21: Poids total ou ingrédient principal | B21: =SUM(B3:B18) -> 6.3
A22: Nombre portions recette base | B22: =B21/B23 -> 70
A23: Poids net portions | B23: 0.09 | C23: Possibilité de saisir le grammage
A24: Nombre portions à produire | B24: =Paramètres!$B$5 -> 110 | C24: Effectif EHPAD + FAM (feuille Paramètres) – possibilité de saisir un autre nombre

Sheet E-Pizza
A1: Pizza | E1: VP Théorique minimum | G1: Four mixte 220°C chaleur sèche Plaques gastro ou grilles 10 à 12 min
E2: 63°C à cœur
A3: Produits | B3: Qté recette base | C3: Qté production | D3: U | E3: PU | F3: Total €
A4: Pizzas surgelées prêtes à cuire (400 g pièce, 1/4 par portion) | B4: 6.45 | C4: =B4/B$22*B$24 -> 10.144168 | D4: Kg | E4: =IFERROR(INDEX(Correspondance!$D$2:$D$3000,MATCH(A4,Correspondance!$A$2:$A$3000,0)),0) -> 6.5 | F4: =C4*E4 -> 65.93709 | G4: Mode opératoire : Déconditionner les pizzas surgelées, disposer sans décongélation sur plaques gastro ou grilles Ajouter un peu de gruyère râpé et d'origan Four mixte 220°C chaleur sèche 10 à 12 min jusqu'à coloration de la pâte et du fromage Contrôle 63°C à cœur, enregistrer la T° Découper en 4, maintenir en étuve ≥ 63°C jusqu'au service (30 min maximum) Salade : décontaminer, rincer, essorer, vinaigrette à part Dressage : 1/4 de pizza avec salade verte assaisonnée Remise en T° différée : refroidir en cellule, régénérer 200°C 6 à 8 min, 63°C à cœur
A5: Gruyère râpé (complément) | B5: 0.277 | C5: =B5/B$22*B$24 -> 0.43564875 | D5: Kg | E5: =IFERROR(INDEX(Correspondance!$D$2:$D$3000,MATCH(A5,Correspondance!$A$2:$A$3000,0)),0) -> 7.5 | F5: =C5*E5 -> 3.2673657
A6: Salade verte | B6: 1.38 | C6: =B6/B$22*B$24 -> 2.1703801 | D6: Kg | E6: =IFERROR(INDEX(Correspondance!$D$2:$D$3000,MATCH(A6,Correspondance!$A$2:$A$3000,0)),0) -> 5.5 | F6: =C6*E6 -> 11.93709
A7: Huile de tournesol | B7: 0.184 | C7: =B7/B$22*B$24 -> 0.28938401 | D7: L | E7: =IFERROR(INDEX(Correspondance!$D$2:$D$3000,MATCH(A7,Correspondance!$A$2:$A$3000,0)),0) -> 2.2 | F7: =C7*E7 -> 0.63664482
A8: Vinaigre de vin | B8: 0.074 | C8: =B8/B$22*B$24 -> 0.1163827 | D8: L | E8: =IFERROR(INDEX(Correspondance!$D$2:$D$3000,MATCH(A8,Correspondance!$A$2:$A$3000,0)),0) -> 1.5 | F8: =C8*E8 -> 0.17457405
A9: Moutarde | B9: 0.028 | C9: =B9/B$22*B$24 -> 0.044036697 | D9: Kg | E9: =IFERROR(INDEX(Correspondance!$D$2:$D$3000,MATCH(A9,Correspondance!$A$2:$A$3000,0)),0) -> 9 | F9: =C9*E9 -> 0.39633028
A10: Origan PM | C10: =B10/B$22*B$24 -> 0 | D10: Kg | E10: =IFERROR(INDEX(Correspondance!$D$2:$D$3000,MATCH(A10,Correspondance!$A$2:$A$3000,0)),0) -> 14 | F10: =C10*E10 -> 0
A11: Sel - Poivre PM | C11: =B11/B$22*B$24 -> 0 | D11: Kg | E11: =IFERROR(INDEX(Correspondance!$D$2:$D$3000,MATCH(A11,Correspondance!$A$2:$A$3000,0)),0) -> 2 | F11: =C11*E11 -> 0
C12: =B12/B$22*B$24 -> 0 | E12: =IFERROR(INDEX(Correspondance!$D$2:$D$3000,MATCH(A12,Correspondance!$A$2:$A$3000,0)),0) -> 0 | F12: =C12*E12 -> 0
C13: =B13/B$22*B$24 -> 0 | E13: =IFERROR(INDEX(Correspondance!$D$2:$D$3000,MATCH(A13,Correspondance!$A$2:$A$3000,0)),0) -> 0 | F13: =C13*E13 -> 0
C14: =B14/B$22*B$24 -> 0 | E14: =IFERROR(INDEX(Correspondance!$D$2:$D$3000,MATCH(A14,Correspondance!$A$2:$A$3000,0)),0) -> 0 | F14: =C14*E14 -> 0
C15: =B15/B$22*B$24 -> 0 | E15: =IFERROR(INDEX(Correspondance!$D$2:$D$3000,MATCH(A15,Correspondance!$A$2:$A$3000,0)),0) -> 0 | F15: =C15*E15 -> 0
C16: =B16/B$22*B$24 -> 0 | E16: =IFERROR(INDEX(Correspondance!$D$2:$D$3000,MATCH(A16,Correspondance!$A$2:$A$3000,0)),0) -> 0 | F16: =C16*E16 -> 0
C17: =B17/B$22*B$24 -> 0 | E17: =IFERROR(INDEX(Correspondance!$D$2:$D$3000,MATCH(A17,Correspondance!$A$2:$A$3000,0)),0) -> 0 | F17: =C17*E17 -> 0
C18: =B18/B$22*B$24 -> 0 | E18: =IFERROR(INDEX(Correspondance!$D$2:$D$3000,MATCH(A18,Correspondance!$A$2:$A$3000,0)),0) -> 0 | F18: =C18*E18 -> 0
F19: =SUM(F4:F18) -> 82.349096
A20: Prix unitaire portion | B20: =F19/B24 -> 0.74862814
A21: Poids total ou ingrédient principal | B21: =SUM(B3:B18) -> 8.393
A22: Nombre portions recette base | B22: =B21/B23 -> 69.941667
A23: Poids net portions | B23: 0.12 | C23: Possibilité de saisir le grammage
A24: Nombre portions à produire | B24: =Paramètres!$B$5 -> 110 | C24: Effectif EHPAD + FAM (feuille Paramètres) – possibilité de saisir un autre nombre

Sheet E-Rosette
A1: Rosette | E1: VP Théorique minimum | G1: Préparation froide Tranchage le jour même Bac gastro + film, 0/+3°C
E2: Liaison froide 0/+3°C
A3: Produits | B3: Qté recette base | C3: Qté production | D3: U | E3: PU | F3: Total €
A4: Rosette tranchée (2 tranches de 20 g) | B4: 2.75 | C4: =B4/B$22*B$24 -> 4.3229725 | D4: Kg | E4: =IFERROR(INDEX(Correspondance!$D$2:$D$3000,MATCH(A4,Correspondance!$A$2:$A$3000,0)),0) -> 15 | F4: =C4*E4 -> 64.844587 | G4: Mode opératoire : Contrôler la DLC et la T° à réception, stocker à 0/+3°C Déconditionner la rosette, trancher le jour même (ou utiliser du prétranché) Décontaminer, rincer et essorer la salade, laver les tomates cerises Dresser 2 tranches de rosette par assiette, 1 à 2 cornichons, 1 beurre portion, salade et tomates cerises Filmer, étiqueter, stocker à 0/+3°C Service en liaison froide, consommation dans les 24h après ouverture du conditionnement
A5: Cornichons | B5: 0.491 | C5: =B5/B$22*B$24 -> 0.77184709 | D5: Kg | E5: =IFERROR(INDEX(Correspondance!$D$2:$D$3000,MATCH(A5,Correspondance!$A$2:$A$3000,0)),0) -> 6.5 | F5: =C5*E5 -> 5.0170061
A6: Beurre portions 10 g | B6: 0.688 | C6: =B6/B$22*B$24 -> 1.0815291 | D6: Kg | E6: =IFERROR(INDEX(Correspondance!$D$2:$D$3000,MATCH(A6,Correspondance!$A$2:$A$3000,0)),0) -> 10.5 | F6: =C6*E6 -> 11.356056
A7: Salade frisée | B7: 0.982 | C7: =B7/B$22*B$24 -> 1.5436942 | D7: Kg | E7: =IFERROR(INDEX(Correspondance!$D$2:$D$3000,MATCH(A7,Correspondance!$A$2:$A$3000,0)),0) -> 3.6 | F7: =C7*E7 -> 5.557299
A8: Tomates cerises | B8: 0.491 | C8: =B8/B$22*B$24 -> 0.77184709 | D8: Kg | E8: =IFERROR(INDEX(Correspondance!$D$2:$D$3000,MATCH(A8,Correspondance!$A$2:$A$3000,0)),0) -> 4.5 | F8: =C8*E8 -> 3.4733119
A9: Moutarde | B9: 0.196 | C9: =B9/B$22*B$24 -> 0.30811004 | D9: Kg | E9: =IFERROR(INDEX(Correspondance!$D$2:$D$3000,MATCH(A9,Correspondance!$A$2:$A$3000,0)),0) -> 9 | F9: =C9*E9 -> 2.7729904
C10: =B10/B$22*B$24 -> 0 | E10: =IFERROR(INDEX(Correspondance!$D$2:$D$3000,MATCH(A10,Correspondance!$A$2:$A$3000,0)),0) -> 0 | F10: =C10*E10 -> 0
C11: =B11/B$22*B$24 -> 0 | E11: =IFERROR(INDEX(Correspondance!$D$2:$D$3000,MATCH(A11,Correspondance!$A$2:$A$3000,0)),0) -> 0 | F11: =C11*E11 -> 0
C12: =B12/B$22*B$24 -> 0 | E12: =IFERROR(INDEX(Correspondance!$D$2:$D$3000,MATCH(A12,Correspondance!$A$2:$A$3000,0)),0) -> 0 | F12: =C12*E12 -> 0
C13: =B13/B$22*B$24 -> 0 | E13: =IFERROR(INDEX(Correspondance!$D$2:$D$3000,MATCH(A13,Correspondance!$A$2:$A$3000,0)),0) -> 0 | F13: =C13*E13 -> 0
C14: =B14/B$22*B$24 -> 0 | E14: =IFERROR(INDEX(Correspondance!$D$2:$D$3000,MATCH(A14,Correspondance!$A$2:$A$3000,0)),0) -> 0 | F14: =C14*E14 -> 0
C15: =B15/B$22*B$24 -> 0 | E15: =IFERROR(INDEX(Correspondance!$D$2:$D$3000,MATCH(A15,Correspondance!$A$2:$A$3000,0)),0) -> 0 | F15: =C15*E15 -> 0
C16: =B16/B$22*B$24 -> 0 | E16: =IFERROR(INDEX(Correspondance!$D$2:$D$3000,MATCH(A16,Correspondance!$A$2:$A$3000,0)),0) -> 0 | F16: =C16*E16 -> 0
C17: =B17/B$22*B$24 -> 0 | E17: =IFERROR(INDEX(Correspondance!$D$2:$D$3000,MATCH(A17,Correspondance!$A$2:$A$3000,0)),0) -> 0 | F17: =C17*E17 -> 0
C18: =B18/B$22*B$24 -> 0 | E18: =IFERROR(INDEX(Correspondance!$D$2:$D$3000,MATCH(A18,Correspondance!$A$2:$A$3000,0)),0) -> 0 | F18: =C18*E18 -> 0
F19: =SUM(F4:F18) -> 93.02125
A20: Prix unitaire portion | B20: =F19/B24 -> 0.84564773
A21: Poids total ou ingrédient principal | B21: =SUM(B3:B18) -> 5.598
A22: Nombre portions recette base | B22: =B21/B23 -> 69.975
A23: Poids net portions | B23: 0.08 | C23: Possibilité de saisir le grammage
A24: Nombre portions à produire | B24: =Paramètres!$B$5 -> 110 | C24: Effectif EHPAD + FAM (feuille Paramètres) – possibilité de saisir un autre nombre

Sheet E-Saucisse sèche
A1: Saucisse sèche | E1: VP Théorique minimum | G1: Préparation froide Tranchage le jour même Bac gastro + film, 0/+3°C
E2: Liaison froide 0/+3°C
A3: Produits | B3: Qté recette base | C3: Qté production | D3: U | E3: PU | F3: Total €
A4: Saucisse sèche (≈ 8 rondelles de 5 g) | B4: 2.27 | C4: =B4/B$22*B$24 -> 3.566415 | D4: Kg | E4: =IFERROR(INDEX(Correspondance!$D$2:$D$3000,MATCH(A4,Correspondance!$A$2:$A$3000,0)),0) -> 14 | F4: =C4*E4 -> 49.92981 | G4: Mode opératoire : Contrôler la DLC et la T° à réception, stocker à 0/+3°C Retirer la peau de la saucisse sèche, trancher à la trancheuse (épaisseur 3 mm) le jour même Décontaminer, rincer et essorer la salade, laver et équeuter les radis Dresser 40 g de saucisse sèche par assiette, cornichons, beurre portion, salade et radis Filmer, étiqueter, stocker à 0/+3°C Service en liaison froide, consommation dans les 24h
A5: Cornichons | B5: 0.454 | C5: =B5/B$22*B$24 -> 0.713283 | D5: Kg | E5: =IFERROR(INDEX(Correspondance!$D$2:$D$3000,MATCH(A5,Correspondance!$A$2:$A$3000,0)),0) -> 6.5 | F5: =C5*E5 -> 4.6363395
A6: Beurre portions 10 g | B6: 0.635 | C6: =B6/B$22*B$24 -> 0.99765354 | D6: Kg | E6: =IFERROR(INDEX(Correspondance!$D$2:$D$3000,MATCH(A6,Correspondance!$A$2:$A$3000,0)),0) -> 10.5 | F6: =C6*E6 -> 10.475362
A7: Salade frisée | B7: 0.907 | C7: =B7/B$22*B$24 -> 1.4249949 | D7: Kg | E7: =IFERROR(INDEX(Correspondance!$D$2:$D$3000,MATCH(A7,Correspondance!$A$2:$A$3000,0)),0) -> 3.6 | F7: =C7*E7 -> 5.1299816
A8: Radis | B8: 0.454 | C8: =B8/B$22*B$24 -> 0.713283 | D8: Kg | E8: =IFERROR(INDEX(Correspondance!$D$2:$D$3000,MATCH(A8,Correspondance!$A$2:$A$3000,0)),0) -> 3.33 | F8: =C8*E8 -> 2.3752324
A9: Moutarde | B9: 0.181 | C9: =B9/B$22*B$24 -> 0.28437054 | D9: Kg | E9: =IFERROR(INDEX(Correspondance!$D$2:$D$3000,MATCH(A9,Correspondance!$A$2:$A$3000,0)),0) -> 9 | F9: =C9*E9 -> 2.5593348
C10: =B10/B$22*B$24 -> 0 | E10: =IFERROR(INDEX(Correspondance!$D$2:$D$3000,MATCH(A10,Correspondance!$A$2:$A$3000,0)),0) -> 0 | F10: =C10*E10 -> 0
C11: =B11/B$22*B$24 -> 0 | E11: =IFERROR(INDEX(Correspondance!$D$2:$D$3000,MATCH(A11,Correspondance!$A$2:$A$3000,0)),0) -> 0 | F11: =C11*E11 -> 0
C12: =B12/B$22*B$24 -> 0 | E12: =IFERROR(INDEX(Correspondance!$D$2:$D$3000,MATCH(A12,Correspondance!$A$2:$A$3000,0)),0) -> 0 | F12: =C12*E12 -> 0
C13: =B13/B$22*B$24 -> 0 | E13: =IFERROR(INDEX(Correspondance!$D$2:$D$3000,MATCH(A13,Correspondance!$A$2:$A$3000,0)),0) -> 0 | F13: =C13*E13 -> 0
C14: =B14/B$22*B$24 -> 0 | E14: =IFERROR(INDEX(Correspondance!$D$2:$D$3000,MATCH(A14,Correspondance!$A$2:$A$3000,0)),0) -> 0 | F14: =C14*E14 -> 0
C15: =B15/B$22*B$24 -> 0 | E15: =IFERROR(INDEX(Correspondance!$D$2:$D$3000,MATCH(A15,Correspondance!$A$2:$A$3000,0)),0) -> 0 | F15: =C15*E15 -> 0
C16: =B16/B$22*B$24 -> 0 | E16: =IFERROR(INDEX(Correspondance!$D$2:$D$3000,MATCH(A16,Correspondance!$A$2:$A$3000,0)),0) -> 0 | F16: =C16*E16 -> 0
C17: =B17/B$22*B$24 -> 0 | E17: =IFERROR(INDEX(Correspondance!$D$2:$D$3000,MATCH(A17,Correspondance!$A$2:$A$3000,0)),0) -> 0 | F17: =C17*E17 -> 0
C18: =B18/B$22*B$24 -> 0 | E18: =IFERROR(INDEX(Correspondance!$D$2:$D$3000,MATCH(A18,Correspondance!$A$2:$A$3000,0)),0) -> 0 | F18: =C18*E18 -> 0
F19: =SUM(F4:F18) -> 75.106061
A20: Prix unitaire portion | B20: =F19/B24 -> 0.68278237
A21: Poids total ou ingrédient principal | B21: =SUM(B3:B18) -> 4.901
A22: Nombre portions recette base | B22: =B21/B23 -> 70.014286
A23: Poids net portions | B23: 0.07 | C23: Possibilité de saisir le grammage
A24: Nombre portions à produire | B24: =Paramètres!$B$5 -> 110 | C24: Effectif EHPAD + FAM (feuille Paramètres) – possibilité de saisir un autre nombre

Sheet E-Coleslaw
A1: Coleslaw | E1: VP Théorique minimum | G1: Préparation froide Bac gastro + film, 0/+3°C
E2: Liaison froide 0/+3°C
A3: Produits | B3: Qté recette base | C3: Qté production | D3: U | E3: PU | F3: Total €
A4: Chou blanc | B4: 3.54 | C4: =B4/B$22*B$24 -> 5.5572998 | D4: Kg | E4: =IFERROR(INDEX(Correspondance!$D$2:$D$3000,MATCH(A4,Correspondance!$A$2:$A$3000,0)),0) -> 1 | F4: =C4*E4 -> 5.5572998 | G4: Mode opératoire : Retirer les premières feuilles du chou, couper en quartiers, retirer le trognon, décontaminer, rincer Éplucher et laver les carottes Émincer finement le chou au robot coupe, râper les carottes (grille fine) Sauce : mayonnaise, fromage blanc, moutarde, vinaigre, sucre, sel, poivre, oignons décongelés Mélanger chou, carottes et sauce, laisser mariner 2 heures minimum à 0/+3°C pour attendrir le chou Rectifier l'assaisonnement Conditionner en bacs gastro filmés, étiqueter, ciboulette au service Stocker à 0/+3°C, service en liaison froide dans les 48h
A5: Carottes | B5: 1.77 | C5: =B5/B$22*B$24 -> 2.7786499 | D5: Kg | E5: =IFERROR(INDEX(Correspondance!$D$2:$D$3000,MATCH(A5,Correspondance!$A$2:$A$3000,0)),0) -> 1 | F5: =C5*E5 -> 2.7786499
A6: Mayonnaise (ovoproduit pasteurisé) | B6: 0.884 | C6: =B6/B$22*B$24 -> 1.3877551 | D6: Kg | E6: =IFERROR(INDEX(Correspondance!$D$2:$D$3000,MATCH(A6,Correspondance!$A$2:$A$3000,0)),0) -> 4.5 | F6: =C6*E6 -> 6.244898
A7: Fromage blanc | B7: 0.442 | C7: =B7/B$22*B$24 -> 0.69387755 | D7: Kg | E7: =IFERROR(INDEX(Correspondance!$D$2:$D$3000,MATCH(A7,Correspondance!$A$2:$A$3000,0)),0) -> 2.8 | F7: =C7*E7 -> 1.9428571
A8: Oignons cubes surgelés | B8: 0.177 | C8: =B8/B$22*B$24 -> 0.27786499 | D8: Kg | E8: =IFERROR(INDEX(Correspondance!$D$2:$D$3000,MATCH(A8,Correspondance!$A$2:$A$3000,0)),0) -> 1.8 | F8: =C8*E8 -> 0.50015699
A9: Vinaigre de cidre | B9: 0.088 | C9: =B9/B$22*B$24 -> 0.13814757 | D9: L | E9: =IFERROR(INDEX(Correspondance!$D$2:$D$3000,MATCH(A9,Correspondance!$A$2:$A$3000,0)),0) -> 1.8 | F9: =C9*E9 -> 0.24866562
A10: Moutarde | B10: 0.044 | C10: =B10/B$22*B$24 -> 0.069073783 | D10: Kg | E10: =IFERROR(INDEX(Correspondance!$D$2:$D$3000,MATCH(A10,Correspondance!$A$2:$A$3000,0)),0) -> 9 | F10: =C10*E10 -> 0.62166405
A11: Sucre | B11: 0.027 | C11: =B11/B$22*B$24 -> 0.042386185 | D11: Kg | E11: =IFERROR(INDEX(Correspondance!$D$2:$D$3000,MATCH(A11,Correspondance!$A$2:$A$3000,0)),0) -> 1.3 | F11: =C11*E11 -> 0.055102041
A12: Sel | B12: 0.035 | C12: =B12/B$22*B$24 -> 0.054945055 | D12: Kg | E12: =IFERROR(INDEX(Correspondance!$D$2:$D$3000,MATCH(A12,Correspondance!$A$2:$A$3000,0)),0) -> 2 | F12: =C12*E12 -> 0.10989011
A13: Poivre PM | C13: =B13/B$22*B$24 -> 0 | D13: Kg | E13: =IFERROR(INDEX(Correspondance!$D$2:$D$3000,MATCH(A13,Correspondance!$A$2:$A$3000,0)),0) -> 18 | F13: =C13*E13 -> 0
A14: Ciboulette ciselée PM | C14: =B14/B$22*B$24 -> 0 | D14: Kg | E14: =IFERROR(INDEX(Correspondance!$D$2:$D$3000,MATCH(A14,Correspondance!$A$2:$A$3000,0)),0) -> 13 | F14: =C14*E14 -> 0
C15: =B15/B$22*B$24 -> 0 | E15: =IFERROR(INDEX(Correspondance!$D$2:$D$3000,MATCH(A15,Correspondance!$A$2:$A$3000,0)),0) -> 0 | F15: =C15*E15 -> 0
C16: =B16/B$22*B$24 -> 0 | E16: =IFERROR(INDEX(Correspondance!$D$2:$D$3000,MATCH(A16,Correspondance!$A$2:$A$3000,0)),0) -> 0 | F16: =C16*E16 -> 0
C17: =B17/B$22*B$24 -> 0 | E17: =IFERROR(INDEX(Correspondance!$D$2:$D$3000,MATCH(A17,Correspondance!$A$2:$A$3000,0)),0) -> 0 | F17: =C17*E17 -> 0
C18: =B18/B$22*B$24 -> 0 | E18: =IFERROR(INDEX(Correspondance!$D$2:$D$3000,MATCH(A18,Correspondance!$A$2:$A$3000,0)),0) -> 0 | F18: =C18*E18 -> 0
F19: =SUM(F4:F18) -> 18.059184
A20: Prix unitaire portion | B20: =F19/B24 -> 0.1641744
A21: Poids total ou ingrédient principal | B21: =SUM(B3:B18) -> 7.007
A22: Nombre portions recette base | B22: =B21/B23 -> 70.07
A23: Poids net portions | B23: 0.1 | C23: Possibilité de saisir le grammage
A24: Nombre portions à produire | B24: =Paramètres!$B$5 -> 110 | C24: Effectif EHPAD + FAM (feuille Paramètres) – possibilité de saisir un autre nombre

Sheet E-Salade de chou chinois
A1: Salade de chou chinois | E1: VP Théorique minimum | G1: Préparation froide Bac gastro + film, 0/+3°C
E2: Liaison froide 0/+3°C
A3: Produits | B3: Qté recette base | C3: Qté production | D3: U | E3: PU | F3: Total €
A4: Chou chinois | B4: 4.44 | C4: =B4/B$22*B$24 -> 6.9793585 | D4: Kg | E4: =IFERROR(INDEX(Correspondance!$D$2:$D$3000,MATCH(A4,Correspondance!$A$2:$A$3000,0)),0) -> 1.9 | F4: =C4*E4 -> 13.260781 | G4: Mode opératoire : Retirer les feuilles extérieures du chou chinois, couper en deux, décontaminer, rincer, égoutter Émincer finement le chou, râper les carottes Sauce : sauce soja, vinaigre, sucre, gingembre, sel, monter aux huiles de tournesol et de sésame Mélanger chou, carottes et sauce, laisser mariner 1 heure à 0/+3°C Torréfier légèrement les graines de sésame à sec Conditionner en bacs gastro filmés, étiqueter, sésame et coriandre au service Stocker à 0/+3°C, service en liaison froide dans les 24h
A5: Carottes | B5: 0.889 | C5: =B5/B$22*B$24 -> 1.3974436 | D5: Kg | E5: =IFERROR(INDEX(Correspondance!$D$2:$D$3000,MATCH(A5,Correspondance!$A$2:$A$3000,0)),0) -> 1 | F5: =C5*E5 -> 1.3974436
A6: Huile de tournesol | B6: 0.355 | C6: =B6/B$22*B$24 -> 0.5580343 | D6: L | E6: =IFERROR(INDEX(Correspondance!$D$2:$D$3000,MATCH(A6,Correspondance!$A$2:$A$3000,0)),0) -> 2.2 | F6: =C6*E6 -> 1.2276755
A7: Sauce soja | B7: 0.178 | C7: =B7/B$22*B$24 -> 0.27980311 | D7: L | E7: =IFERROR(INDEX(Correspondance!$D$2:$D$3000,MATCH(A7,Correspondance!$A$2:$A$3000,0)),0) -> 4 | F7: =C7*E7 -> 1.1192124
A8: Vinaigre de riz ou de cidre | B8: 0.178 | C8: =B8/B$22*B$24 -> 0.27980311 | D8: L | E8: =IFERROR(INDEX(Correspondance!$D$2:$D$3000,MATCH(A8,Correspondance!$A$2:$A$3000,0)),0) -> 4 | F8: =C8*E8 -> 1.1192124
A9: Huile de sésame | B9: 0.089 | C9: =B9/B$22*B$24 -> 0.13990156 | D9: L | E9: =IFERROR(INDEX(Correspondance!$D$2:$D$3000,MATCH(A9,Correspondance!$A$2:$A$3000,0)),0) -> 11 | F9: =C9*E9 -> 1.5389171
A10: Graines de sésame | B10: 0.089 | C10: =B10/B$22*B$24 -> 0.13990156 | D10: Kg | E10: =IFERROR(INDEX(Correspondance!$D$2:$D$3000,MATCH(A10,Correspondance!$A$2:$A$3000,0)),0) -> 6 | F10: =C10*E10 -> 0.83940934
A11: Sucre | B11: 0.044 | C11: =B11/B$22*B$24 -> 0.069164814 | D11: Kg | E11: =IFERROR(INDEX(Correspondance!$D$2:$D$3000,MATCH(A11,Correspondance!$A$2:$A$3000,0)),0) -> 1.3 | F11: =C11*E11 -> 0.089914258
A12: Gingembre moulu | B12: 0.018 | C12: =B12/B$22*B$24 -> 0.028294697 | D12: Kg | E12: =IFERROR(INDEX(Correspondance!$D$2:$D$3000,MATCH(A12,Correspondance!$A$2:$A$3000,0)),0) -> 14 | F12: =C12*E12 -> 0.39612575
A13: Sel | B13: 0.018 | C13: =B13/B$22*B$24 -> 0.028294697 | D13: Kg | E13: =IFERROR(INDEX(Correspondance!$D$2:$D$3000,MATCH(A13,Correspondance!$A$2:$A$3000,0)),0) -> 2 | F13: =C13*E13 -> 0.056589393
A14: Coriandre fraîche PM | C14: =B14/B$22*B$24 -> 0 | D14: Kg | E14: =IFERROR(INDEX(Correspondance!$D$2:$D$3000,MATCH(A14,Correspondance!$A$2:$A$3000,0)),0) -> 30 | F14: =C14*E14 -> 0
C15: =B15/B$22*B$24 -> 0 | E15: =IFERROR(INDEX(Correspondance!$D$2:$D$3000,MATCH(A15,Correspondance!$A$2:$A$3000,0)),0) -> 0 | F15: =C15*E15 -> 0
C16: =B16/B$22*B$24 -> 0 | E16: =IFERROR(INDEX(Correspondance!$D$2:$D$3000,MATCH(A16,Correspondance!$A$2:$A$3000,0)),0) -> 0 | F16: =C16*E16 -> 0
C17: =B17/B$22*B$24 -> 0 | E17: =IFERROR(INDEX(Correspondance!$D$2:$D$3000,MATCH(A17,Correspondance!$A$2:$A$3000,0)),0) -> 0 | F17: =C17*E17 -> 0
C18: =B18/B$22*B$24 -> 0 | E18: =IFERROR(INDEX(Correspondance!$D$2:$D$3000,MATCH(A18,Correspondance!$A$2:$A$3000,0)),0) -> 0 | F18: =C18*E18 -> 0
F19: =SUM(F4:F18) -> 21.045281
A20: Prix unitaire portion | B20: =F19/B24 -> 0.19132074
A21: Poids total ou ingrédient principal | B21: =SUM(B3:B18) -> 6.298
A22: Nombre portions recette base | B22: =B21/B23 -> 69.977778
A23: Poids net portions | B23: 0.09 | C23: Possibilité de saisir le grammage
A24: Nombre portions à produire | B24: =Paramètres!$B$5 -> 110 | C24: Effectif EHPAD + FAM (feuille Paramètres) – possibilité de saisir un autre nombre

Sheet E-Salade de tomates
A1: Salade de tomates | E1: VP Théorique minimum | G1: Préparation froide Bac gastro + film, 0/+3°C
E2: Liaison froide 0/+3°C
A3: Produits | B3: Qté recette base | C3: Qté production | D3: U | E3: PU | F3: Total €
A4: Tomates rondes | B4: 6.54 | C4: =B4/B$22*B$24 -> 10.279813 | D4: Kg | E4: =IFERROR(INDEX(Correspondance!$D$2:$D$3000,MATCH(A4,Correspondance!$A$2:$A$3000,0)),0) -> 2.4 | F4: =C4*E4 -> 24.671551 | G4: Mode opératoire : Décontaminer et rincer les tomates, retirer le pédoncule Couper en quartiers ou en rondelles au plus près du service (ne pas laisser dégorger trop longtemps) Vinaigrette : moutarde, sel, poivre, vinaigre balsamique, monter à l'huile d'olive, ajouter échalotes Dresser les tomates en bacs gastro, parsemer d'oignons rouges Vinaigrette à part, assaisonner au moment du service, herbes ciselées Filmer, étiqueter, stocker à 0/+3°C Service en liaison froide, consommation dans les 24h
A5: Oignons rouges émincés | B5: 0.374 | C5: =B5/B$22*B$24 -> 0.58786698 | D5: Kg | E5: =IFERROR(INDEX(Correspondance!$D$2:$D$3000,MATCH(A5,Correspondance!$A$2:$A$3000,0)),0) -> 1.8 | F5: =C5*E5 -> 1.0581606
A6: Échalotes ciselées surgelées | B6: 0.093 | C6: =B6/B$22*B$24 -> 0.14618083 | D6: Kg | E6: =IFERROR(INDEX(Correspondance!$D$2:$D$3000,MATCH(A6,Correspondance!$A$2:$A$3000,0)),0) -> 4.5 | F6: =C6*E6 -> 0.65781372
A7: Huile d'olive | B7: 0.467 | C7: =B7/B$22*B$24 -> 0.7340478 | D7: L | E7: =IFERROR(INDEX(Correspondance!$D$2:$D$3000,MATCH(A7,Correspondance!$A$2:$A$3000,0)),0) -> 7.5 | F7: =C7*E7 -> 5.5053585
A8: Vinaigre balsamique | B8: 0.14 | C8: =B8/B$22*B$24 -> 0.22005716 | D8: L | E8: =IFERROR(INDEX(Correspondance!$D$2:$D$3000,MATCH(A8,Correspondance!$A$2:$A$3000,0)),0) -> 3.5 | F8: =C8*E8 -> 0.77020005
A9: Moutarde | B9: 0.037 | C9: =B9/B$22*B$24 -> 0.058157963 | D9: Kg | E9: =IFERROR(INDEX(Correspondance!$D$2:$D$3000,MATCH(A9,Correspondance!$A$2:$A$3000,0)),0) -> 9 | F9: =C9*E9 -> 0.52342167
A10: Sel | B10: 0.047 | C10: =B10/B$22*B$24 -> 0.073876332 | D10: Kg | E10: =IFERROR(INDEX(Correspondance!$D$2:$D$3000,MATCH(A10,Correspondance!$A$2:$A$3000,0)),0) -> 2 | F10: =C10*E10 -> 0.14775266
A11: Poivre PM | C11: =B11/B$22*B$24 -> 0 | D11: Kg | E11: =IFERROR(INDEX(Correspondance!$D$2:$D$3000,MATCH(A11,Correspondance!$A$2:$A$3000,0)),0) -> 18 | F11: =C11*E11 -> 0
A12: Basilic ou persil PM | C12: =B12/B$22*B$24 -> 0 | D12: Kg | E12: =IFERROR(INDEX(Correspondance!$D$2:$D$3000,MATCH(A12,Correspondance!$A$2:$A$3000,0)),0) -> 12 | F12: =C12*E12 -> 0
C13: =B13/B$22*B$24 -> 0 | E13: =IFERROR(INDEX(Correspondance!$D$2:$D$3000,MATCH(A13,Correspondance!$A$2:$A$3000,0)),0) -> 0 | F13: =C13*E13 -> 0
C14: =B14/B$22*B$24 -> 0 | E14: =IFERROR(INDEX(Correspondance!$D$2:$D$3000,MATCH(A14,Correspondance!$A$2:$A$3000,0)),0) -> 0 | F14: =C14*E14 -> 0
C15: =B15/B$22*B$24 -> 0 | E15: =IFERROR(INDEX(Correspondance!$D$2:$D$3000,MATCH(A15,Correspondance!$A$2:$A$3000,0)),0) -> 0 | F15: =C15*E15 -> 0
C16: =B16/B$22*B$24 -> 0 | E16: =IFERROR(INDEX(Correspondance!$D$2:$D$3000,MATCH(A16,Correspondance!$A$2:$A$3000,0)),0) -> 0 | F16: =C16*E16 -> 0
C17: =B17/B$22*B$24 -> 0 | E17: =IFERROR(INDEX(Correspondance!$D$2:$D$3000,MATCH(A17,Correspondance!$A$2:$A$3000,0)),0) -> 0 | F17: =C17*E17 -> 0
C18: =B18/B$22*B$24 -> 0 | E18: =IFERROR(INDEX(Correspondance!$D$2:$D$3000,MATCH(A18,Correspondance!$A$2:$A$3000,0)),0) -> 0 | F18: =C18*E18 -> 0
F19: =SUM(F4:F18) -> 33.334258
A20: Prix unitaire portion | B20: =F19/B24 -> 0.30303871
A21: Poids total ou ingrédient principal | B21: =SUM(B3:B18) -> 7.698
A22: Nombre portions recette base | B22: =B21/B23 -> 69.981818
A23: Poids net portions | B23: 0.11 | C23: Possibilité de saisir le grammage
A24: Nombre portions à produire | B24: =Paramètres!$B$5 -> 110 | C24: Effectif EHPAD + FAM (feuille Paramètres) – possibilité de saisir un autre nombre

Sheet E-Tomates mozzarella
A1: Tomates mozzarella | E1: VP Théorique minimum | G1: Préparation froide Bac gastro + film, 0/+3°C
E2: Liaison froide 0/+3°C
A3: Produits | B3: Qté recette base | C3: Qté production | D3: U | E3: PU | F3: Total €
A4: Tomates rondes | B4: 4.78 | C4: =B4/B$22*B$24 -> 7.5078534 | D4: Kg | E4: =IFERROR(INDEX(Correspondance!$D$2:$D$3000,MATCH(A4,Correspondance!$A$2:$A$3000,0)),0) -> 2.4 | F4: =C4*E4 -> 18.018848 | G4: Mode opératoire : Décontaminer et rincer les tomates, retirer le pédoncule, trancher en rondelles de 1 cm Égoutter la mozzarella, trancher en rondelles de 5 mm Dresser en alternant tomate et mozzarella, 70 g de tomate et 40 g de mozzarella par portion Assaisonner : sel, poivre, origan, filet d'huile d'olive et de vinaigre balsamique, olives Basilic ciselé au moment du service Filmer, étiqueter, stocker à 0/+3°C Service en liaison froide, consommation dans les 24h
A5: Mozzarella | B5: 2.87 | C5: =B5/B$22*B$24 -> 4.5078534 | D5: Kg | E5: =IFERROR(INDEX(Correspondance!$D$2:$D$3000,MATCH(A5,Correspondance!$A$2:$A$3000,0)),0) -> 7.5 | F5: =C5*E5 -> 33.808901
A6: Huile d'olive | B6: 0.382 | C6: =B6/B$22*B$24 -> 0.6 | D6: L | E6: =IFERROR(INDEX(Correspondance!$D$2:$D$3000,MATCH(A6,Correspondance!$A$2:$A$3000,0)),0) -> 7.5 | F6: =C6*E6 -> 4.5
A7: Vinaigre balsamique | B7: 0.143 | C7: =B7/B$22*B$24 -> 0.22460733 | D7: L | E7: =IFERROR(INDEX(Correspondance!$D$2:$D$3000,MATCH(A7,Correspondance!$A$2:$A$3000,0)),0) -> 3.5 | F7: =C7*E7 -> 0.78612565
A8: Olives noires dénoyautées | B8: 0.191 | C8: =B8/B$22*B$24 -> 0.3 | D8: Kg | E8: =IFERROR(INDEX(Correspondance!$D$2:$D$3000,MATCH(A8,Correspondance!$A$2:$A$3000,0)),0) -> 5.5 | F8: =C8*E8 -> 1.65
A9: Sel | B9: 0.038 | C9: =B9/B$22*B$24 -> 0.059685864 | D9: Kg | E9: =IFERROR(INDEX(Correspondance!$D$2:$D$3000,MATCH(A9,Correspondance!$A$2:$A$3000,0)),0) -> 2 | F9: =C9*E9 -> 0.11937173
A10: Poivre PM | C10: =B10/B$22*B$24 -> 0 | D10: Kg | E10: =IFERROR(INDEX(Correspondance!$D$2:$D$3000,MATCH(A10,Correspondance!$A$2:$A$3000,0)),0) -> 18 | F10: =C10*E10 -> 0
A11: Basilic frais PM | C11: =B11/B$22*B$24 -> 0 | D11: Kg | E11: =IFERROR(INDEX(Correspondance!$D$2:$D$3000,MATCH(A11,Correspondance!$A$2:$A$3000,0)),0) -> 32 | F11: =C11*E11 -> 0
A12: Origan PM | C12: =B12/B$22*B$24 -> 0 | D12: Kg | E12: =IFERROR(INDEX(Correspondance!$D$2:$D$3000,MATCH(A12,Correspondance!$A$2:$A$3000,0)),0) -> 14 | F12: =C12*E12 -> 0
C13: =B13/B$22*B$24 -> 0 | E13: =IFERROR(INDEX(Correspondance!$D$2:$D$3000,MATCH(A13,Correspondance!$A$2:$A$3000,0)),0) -> 0 | F13: =C13*E13 -> 0
C14: =B14/B$22*B$24 -> 0 | E14: =IFERROR(INDEX(Correspondance!$D$2:$D$3000,MATCH(A14,Correspondance!$A$2:$A$3000,0)),0) -> 0 | F14: =C14*E14 -> 0
C15: =B15/B$22*B$24 -> 0 | E15: =IFERROR(INDEX(Correspondance!$D$2:$D$3000,MATCH(A15,Correspondance!$A$2:$A$3000,0)),0) -> 0 | F15: =C15*E15 -> 0
C16: =B16/B$22*B$24 -> 0 | E16: =IFERROR(INDEX(Correspondance!$D$2:$D$3000,MATCH(A16,Correspondance!$A$2:$A$3000,0)),0) -> 0 | F16: =C16*E16 -> 0
C17: =B17/B$22*B$24 -> 0 | E17: =IFERROR(INDEX(Correspondance!$D$2:$D$3000,MATCH(A17,Correspondance!$A$2:$A$3000,0)),0) -> 0 | F17: =C17*E17 -> 0
C18: =B18/B$22*B$24 -> 0 | E18: =IFERROR(INDEX(Correspondance!$D$2:$D$3000,MATCH(A18,Correspondance!$A$2:$A$3000,0)),0) -> 0 | F18: =C18*E18 -> 0
F19: =SUM(F4:F18) -> 58.883246
A20: Prix unitaire portion | B20: =F19/B24 -> 0.53530224
A21: Poids total ou ingrédient principal | B21: =SUM(B3:B18) -> 8.404
A22: Nombre portions recette base | B22: =B21/B23 -> 70.033333
A23: Poids net portions | B23: 0.12 | C23: Possibilité de saisir le grammage
A24: Nombre portions à produire | B24: =Paramètres!$B$5 -> 110 | C24: Effectif EHPAD + FAM (feuille Paramètres) – possibilité de saisir un autre nombre

Sheet E-Tomate antiboise
A1: Tomate antiboise | E1: VP Théorique minimum | G1: Préparation froide Tomates farcies au thon mayonnaise Bac gastro + film, 0/+3°C
E2: Liaison froide 0/+3°C
A3: Produits | B3: Qté recette base | C3: Qté production | D3: U | E3: PU | F3: Total €
A4: Tomates rondes calibre 67/82 (1 par portion) | B4: 5.34 | C4: =B4/B$22*B$24 -> 8.3906295 | D4: Kg | E4: =IFERROR(INDEX(Correspondance!$D$2:$D$3000,MATCH(A4,Correspondance!$A$2:$A$3000,0)),0) -> 2.4 | F4: =C4*E4 -> 20.137511 | G4: Mode opératoire : Décontaminer et rincer les tomates, couper un chapeau, évider à la cuillère, saler l'intérieur et retourner sur grille 20 min Farce : émietter le thon, mélanger avec mayonnaise, œufs durs hachés, câpres, échalotes, citron, poivre, persil Rectifier l'assaisonnement, réserver la farce à 0/+3°C Garnir les tomates à la poche ou à la cuillère (60 g de farce par tomate), reposer le chapeau Dresser sur lit de salade frisée décontaminée Filmer, étiqueter, stocker à 0/+3°C Service en liaison froide, consommation dans les 24h Mayonnaise exclusivement à base d'ovoproduits pasteurisés
A5: Thon au naturel égoutté | B5: 2.43 | C5: =B5/B$22*B$24 -> 3.8182078 | D5: Kg | E5: =IFERROR(INDEX(Correspondance!$D$2:$D$3000,MATCH(A5,Correspondance!$A$2:$A$3000,0)),0) -> 9.5 | F5: =C5*E5 -> 36.272974
A6: Mayonnaise (ovoproduit pasteurisé) | B6: 1.16 | C6: =B6/B$22*B$24 -> 1.8226836 | D6: Kg | E6: =IFERROR(INDEX(Correspondance!$D$2:$D$3000,MATCH(A6,Correspondance!$A$2:$A$3000,0)),0) -> 4.5 | F6: =C6*E6 -> 8.202076
A7: Œufs durs écalés pasteurisés | B7: 0.485 | C7: =B7/B$22*B$24 -> 0.76207028 | D7: Kg | E7: =IFERROR(INDEX(Correspondance!$D$2:$D$3000,MATCH(A7,Correspondance!$A$2:$A$3000,0)),0) -> 5.6 | F7: =C7*E7 -> 4.2675936
A8: Salade frisée | B8: 0.776 | C8: =B8/B$22*B$24 -> 1.2193124 | D8: Kg | E8: =IFERROR(INDEX(Correspondance!$D$2:$D$3000,MATCH(A8,Correspondance!$A$2:$A$3000,0)),0) -> 3.6 | F8: =C8*E8 -> 4.3895248
A9: Câpres | B9: 0.097 | C9: =B9/B$22*B$24 -> 0.15241406 | D9: Kg | E9: =IFERROR(INDEX(Correspondance!$D$2:$D$3000,MATCH(A9,Correspondance!$A$2:$A$3000,0)),0) -> 8 | F9: =C9*E9 -> 1.2193124
A10: Échalotes ciselées surgelées | B10: 0.097 | C10: =B10/B$22*B$24 -> 0.15241406 | D10: Kg | E10: =IFERROR(INDEX(Correspondance!$D$2:$D$3000,MATCH(A10,Correspondance!$A$2:$A$3000,0)),0) -> 4.5 | F10: =C10*E10 -> 0.68586325
A11: Jus de citron | B11: 0.097 | C11: =B11/B$22*B$24 -> 0.15241406 | D11: L | E11: =IFERROR(INDEX(Correspondance!$D$2:$D$3000,MATCH(A11,Correspondance!$A$2:$A$3000,0)),0) -> 2.5 | F11: =C11*E11 -> 0.38103514
A12: Sel | B12: 0.019 | C12: =B12/B$22*B$24 -> 0.0298543 | D12: Kg | E12: =IFERROR(INDEX(Correspondance!$D$2:$D$3000,MATCH(A12,Correspondance!$A$2:$A$3000,0)),0) -> 2 | F12: =C12*E12 -> 0.059708599
A13: Poivre PM | C13: =B13/B$22*B$24 -> 0 | D13: Kg | E13: =IFERROR(INDEX(Correspondance!$D$2:$D$3000,MATCH(A13,Correspondance!$A$2:$A$3000,0)),0) -> 18 | F13: =C13*E13 -> 0
A14: Persil haché PM | C14: =B14/B$22*B$24 -> 0 | D14: Kg | E14: =IFERROR(INDEX(Correspondance!$D$2:$D$3000,MATCH(A14,Correspondance!$A$2:$A$3000,0)),0) -> 8 | F14: =C14*E14 -> 0
C15: =B15/B$22*B$24 -> 0 | E15: =IFERROR(INDEX(Correspondance!$D$2:$D$3000,MATCH(A15,Correspondance!$A$2:$A$3000,0)),0) -> 0 | F15: =C15*E15 -> 0
C16: =B16/B$22*B$24 -> 0 | E16: =IFERROR(INDEX(Correspondance!$D$2:$D$3000,MATCH(A16,Correspondance!$A$2:$A$3000,0)),0) -> 0 | F16: =C16*E16 -> 0
C17: =B17/B$22*B$24 -> 0 | E17: =IFERROR(INDEX(Correspondance!$D$2:$D$3000,MATCH(A17,Correspondance!$A$2:$A$3000,0)),0) -> 0 | F17: =C17*E17 -> 0
C18: =B18/B$22*B$24 -> 0 | E18: =IFERROR(INDEX(Correspondance!$D$2:$D$3000,MATCH(A18,Correspondance!$A$2:$A$3000,0)),0) -> 0 | F18: =C18*E18 -> 0
F19: =SUM(F4:F18) -> 75.615599
A20: Prix unitaire portion | B20: =F19/B24 -> 0.68741453
A21: Poids total ou ingrédient principal | B21: =SUM(B3:B18) -> 10.501
A22: Nombre portions recette base | B22: =B21/B23 -> 70.006667
A23: Poids net portions | B23: 0.15 | C23: Possibilité de saisir le grammage
A24: Nombre portions à produire | B24: =Paramètres!$B$5 -> 110 | C24: Effectif EHPAD + FAM (feuille Paramètres) – possibilité de saisir un autre nombre

Sheet E-Tomate à la russe
A1: Tomate à la russe | E1: VP Théorique minimum | G1: Préparation froide Tomates farcies à la macédoine mayonnaise Bac gastro + film, 0/+3°C
E2: Liaison froide 0/+3°C
A3: Produits | B3: Qté recette base | C3: Qté production | D3: U | E3: PU | F3: Total €
A4: Tomates rondes calibre 67/82 (1 par portion) | B4: 5.29 | C4: =B4/B$22*B$24 -> 8.3152329 | D4: Kg | E4: =IFERROR(INDEX(Correspondance!$D$2:$D$3000,MATCH(A4,Correspondance!$A$2:$A$3000,0)),0) -> 2.4 | F4: =C4*E4 -> 19.956559 | G4: Mode opératoire : Décontaminer et rincer les tomates, couper un chapeau, évider, saler l'intérieur et retourner sur grille 20 min Égoutter et rincer la macédoine, laisser égoutter 30 min au froid Mélanger macédoine, mayonnaise citronnée, sel, poivre et persil Garnir les tomates (60 g de macédoine par tomate), décorer d'un quartier d'œuf dur, reposer le chapeau Dresser sur lit de salade frisée décontaminée Filmer, étiqueter, stocker à 0/+3°C Service en liaison froide, consommation dans les 24h Mayonnaise exclusivement à base d'ovoproduits pasteurisés
A5: Macédoine de légumes appertisée égouttée | B5: 2.88 | C5: =B5/B$22*B$24 -> 4.5270077 | D5: Kg | E5: =IFERROR(INDEX(Correspondance!$D$2:$D$3000,MATCH(A5,Correspondance!$A$2:$A$3000,0)),0) -> 2 | F5: =C5*E5 -> 9.0540154
A6: Mayonnaise (ovoproduit pasteurisé) | B6: 0.962 | C6: =B6/B$22*B$24 -> 1.5121463 | D6: Kg | E6: =IFERROR(INDEX(Correspondance!$D$2:$D$3000,MATCH(A6,Correspondance!$A$2:$A$3000,0)),0) -> 4.5 | F6: =C6*E6 -> 6.8046585
A7: Œufs durs écalés pasteurisés | B7: 0.481 | C7: =B7/B$22*B$24 -> 0.75607316 | D7: Kg | E7: =IFERROR(INDEX(Correspondance!$D$2:$D$3000,MATCH(A7,Correspondance!$A$2:$A$3000,0)),0) -> 5.6 | F7: =C7*E7 -> 4.2340097
A8: Salade frisée | B8: 0.769 | C8: =B8/B$22*B$24 -> 1.2087739 | D8: Kg | E8: =IFERROR(INDEX(Correspondance!$D$2:$D$3000,MATCH(A8,Correspondance!$A$2:$A$3000,0)),0) -> 3.6 | F8: =C8*E8 -> 4.3515862
A9: Jus de citron | B9: 0.096 | C9: =B9/B$22*B$24 -> 0.15090026 | D9: L | E9: =IFERROR(INDEX(Correspondance!$D$2:$D$3000,MATCH(A9,Correspondance!$A$2:$A$3000,0)),0) -> 2.5 | F9: =C9*E9 -> 0.37725064
A10: Sel | B10: 0.019 | C10: =B10/B$22*B$24 -> 0.029865676 | D10: Kg | E10: =IFERROR(INDEX(Correspondance!$D$2:$D$3000,MATCH(A10,Correspondance!$A$2:$A$3000,0)),0) -> 2 | F10: =C10*E10 -> 0.059731352
A11: Poivre PM | C11: =B11/B$22*B$24 -> 0 | D11: Kg | E11: =IFERROR(INDEX(Correspondance!$D$2:$D$3000,MATCH(A11,Correspondance!$A$2:$A$3000,0)),0) -> 18 | F11: =C11*E11 -> 0
A12: Persil haché PM | C12: =B12/B$22*B$24 -> 0 | D12: Kg | E12: =IFERROR(INDEX(Correspondance!$D$2:$D$3000,MATCH(A12,Correspondance!$A$2:$A$3000,0)),0) -> 8 | F12: =C12*E12 -> 0
C13: =B13/B$22*B$24 -> 0 | E13: =IFERROR(INDEX(Correspondance!$D$2:$D$3000,MATCH(A13,Correspondance!$A$2:$A$3000,0)),0) -> 0 | F13: =C13*E13 -> 0
C14: =B14/B$22*B$24 -> 0 | E14: =IFERROR(INDEX(Correspondance!$D$2:$D$3000,MATCH(A14,Correspondance!$A$2:$A$3000,0)),0) -> 0 | F14: =C14*E14 -> 0
C15: =B15/B$22*B$24 -> 0 | E15: =IFERROR(INDEX(Correspondance!$D$2:$D$3000,MATCH(A15,Correspondance!$A$2:$A$3000,0)),0) -> 0 | F15: =C15*E15 -> 0
C16: =B16/B$22*B$24 -> 0 | E16: =IFERROR(INDEX(Correspondance!$D$2:$D$3000,MATCH(A16,Correspondance!$A$2:$A$3000,0)),0) -> 0 | F16: =C16*E16 -> 0
C17: =B17/B$22*B$24 -> 0 | E17: =IFERROR(INDEX(Correspondance!$D$2:$D$3000,MATCH(A17,Correspondance!$A$2:$A$3000,0)),0) -> 0 | F17: =C17*E17 -> 0
C18: =B18/B$22*B$24 -> 0 | E18: =IFERROR(INDEX(Correspondance!$D$2:$D$3000,MATCH(A18,Correspondance!$A$2:$A$3000,0)),0) -> 0 | F18: =C18*E18 -> 0
F19: =SUM(F4:F18) -> 44.837811
A20: Prix unitaire portion | B20: =F19/B24 -> 0.40761646
A21: Poids total ou ingrédient principal | B21: =SUM(B3:B18) -> 10.497
A22: Nombre portions recette base | B22: =B21/B23 -> 69.98
A23: Poids net portions | B23: 0.15 | C23: Possibilité de saisir le grammage
A24: Nombre portions à produire | B24: =Paramètres!$B$5 -> 110 | C24: Effectif EHPAD + FAM (feuille Paramètres) – possibilité de saisir un autre nombre

Sheet E-Salade de pâtes
A1: Salade de pâtes | E1: VP Théorique minimum | G1: Pâtes cuites à l'eau puis refroidies en cellule Assemblage en liaison froide Bac gastro + film, 0/+3°C
E2: Liaison froide 0/+3°C
A3: Produits | B3: Qté recette base | C3: Qté production | D3: U | E3: PU | F3: Total €
A4: Pâtes torsades | B4: 2.76 | C4: =B4/B$22*B$24 -> 4.3400044 | D4: Kg | E4: =IFERROR(INDEX(Correspondance!$D$2:$D$3000,MATCH(A4,Correspondance!$A$2:$A$3000,0)),0) -> 1.6 | F4: =C4*E4 -> 6.944007 | G4: Mode opératoire : Cuire les pâtes à grande eau salée bouillante 9 à 11 min, égoutter, huiler légèrement Refroidir immédiatement en cellule (63°C à 10°C en moins de deux heures), réserver à 0/+3°C Décontaminer et tailler les tomates, égoutter le maïs, égoutter les olives Sauce : vinaigrette (moutarde, sel, poivre, vinaigre, huile) liée avec la mayonnaise Mélanger pâtes froides, jambon, emmental, maïs, tomates, cornichons, olives et sauce Rectifier l'assaisonnement, ciboulette Conditionner en bacs gastro filmés, étiqueter Stocker à 0/+3°C, service en liaison froide dans les 48h
A5: Tomates en cubes | B5: 1.65 | C5: =B5/B$22*B$24 -> 2.5945678 | D5: Kg | E5: =IFERROR(INDEX(Correspondance!$D$2:$D$3000,MATCH(A5,Correspondance!$A$2:$A$3000,0)),0) -> 1.5 | F5: =C5*E5 -> 3.8918518
A6: Jambon blanc en dés | B6: 1.1 | C6: =B6/B$22*B$24 -> 1.7297119 | D6: Kg | E6: =IFERROR(INDEX(Correspondance!$D$2:$D$3000,MATCH(A6,Correspondance!$A$2:$A$3000,0)),0) -> 8.5 | F6: =C6*E6 -> 14.702551
A7: Emmental en dés | B7: 0.882 | C7: =B7/B$22*B$24 -> 1.3869144 | D7: Kg | E7: =IFERROR(INDEX(Correspondance!$D$2:$D$3000,MATCH(A7,Correspondance!$A$2:$A$3000,0)),0) -> 8 | F7: =C7*E7 -> 11.095316
A8: Maïs doux appertisé égoutté | B8: 0.882 | C8: =B8/B$22*B$24 -> 1.3869144 | D8: Kg | E8: =IFERROR(INDEX(Correspondance!$D$2:$D$3000,MATCH(A8,Correspondance!$A$2:$A$3000,0)),0) -> 2.2 | F8: =C8*E8 -> 3.0512118
A9: Cornichons en rondelles | B9: 0.331 | C9: =B9/B$22*B$24 -> 0.52048603 | D9: Kg | E9: =IFERROR(INDEX(Correspondance!$D$2:$D$3000,MATCH(A9,Correspondance!$A$2:$A$3000,0)),0) -> 6 | F9: =C9*E9 -> 3.1229162
A10: Olives noires dénoyautées | B10: 0.221 | C10: =B10/B$22*B$24 -> 0.34751484 | D10: Kg | E10: =IFERROR(INDEX(Correspondance!$D$2:$D$3000,MATCH(A10,Correspondance!$A$2:$A$3000,0)),0) -> 5.5 | F10: =C10*E10 -> 1.9113316
A11: Mayonnaise (ovoproduit pasteurisé) | B11: 0.441 | C11: =B11/B$22*B$24 -> 0.69345722 | D11: Kg | E11: =IFERROR(INDEX(Correspondance!$D$2:$D$3000,MATCH(A11,Correspondance!$A$2:$A$3000,0)),0) -> 4.5 | F11: =C11*E11 -> 3.1205575
A12: Huile de tournesol | B12: 0.552 | C12: =B12/B$22*B$24 -> 0.86800088 | D12: L | E12: =IFERROR(INDEX(Correspondance!$D$2:$D$3000,MATCH(A12,Correspondance!$A$2:$A$3000,0)),0) -> 2.2 | F12: =C12*E12 -> 1.9096019
A13: Vinaigre de vin | B13: 0.165 | C13: =B13/B$22*B$24 -> 0.25945678 | D13: L | E13: =IFERROR(INDEX(Correspondance!$D$2:$D$3000,MATCH(A13,Correspondance!$A$2:$A$3000,0)),0) -> 1.5 | F13: =C13*E13 -> 0.38918518
A14: Moutarde | B14: 0.066 | C14: =B14/B$22*B$24 -> 0.10378271 | D14: Kg | E14: =IFERROR(INDEX(Correspondance!$D$2:$D$3000,MATCH(A14,Correspondance!$A$2:$A$3000,0)),0) -> 9 | F14: =C14*E14 -> 0.93404442
A15: Sel | B15: 0.044 | C15: =B15/B$22*B$24 -> 0.069188476 | D15: Kg | E15: =IFERROR(INDEX(Correspondance!$D$2:$D$3000,MATCH(A15,Correspondance!$A$2:$A$3000,0)),0) -> 2 | F15: =C15*E15 -> 0.13837695
A16: Poivre PM | C16: =B16/B$22*B$24 -> 0 | D16: Kg | E16: =IFERROR(INDEX(Correspondance!$D$2:$D$3000,MATCH(A16,Correspondance!$A$2:$A$3000,0)),0) -> 18 | F16: =C16*E16 -> 0
A17: Ciboulette ciselée PM | C17: =B17/B$22*B$24 -> 0 | D17: Kg | E17: =IFERROR(INDEX(Correspondance!$D$2:$D$3000,MATCH(A17,Correspondance!$A$2:$A$3000,0)),0) -> 13 | F17: =C17*E17 -> 0
C18: =B18/B$22*B$24 -> 0 | E18: =IFERROR(INDEX(Correspondance!$D$2:$D$3000,MATCH(A18,Correspondance!$A$2:$A$3000,0)),0) -> 0 | F18: =C18*E18 -> 0
F19: =SUM(F4:F18) -> 51.210951
A20: Prix unitaire portion | B20: =F19/B24 -> 0.4655541
A21: Poids total ou ingrédient principal | B21: =SUM(B3:B18) -> 9.094
A22: Nombre portions recette base | B22: =B21/B23 -> 69.953846
A23: Poids net portions | B23: 0.13 | C23: Possibilité de saisir le grammage
A24: Nombre portions à produire | B24: =Paramètres!$B$5 -> 110 | C24: Effectif EHPAD + FAM (feuille Paramètres) – possibilité de saisir un autre nombre

Sheet E-Salade de pâtes, poulet et pe
A1: Salade de pâtes, poulet et pesto sous vide basse température | E1: VP Théorique minimum | G1: Sous vide 65°C thermoplongeur ou four vapeur Poches sous vide, 2H00 Pâtes cuites à l'eau, assemblage froid
E2: > à 150
A3: Produits | B3: Qté recette base | C3: Qté production | D3: U | E3: PU | F3: Total €
A4: Filets de poulet | B4: 3.7 | C4: =B4/B$22*B$24 -> 5.8091787 | D4: Kg | E4: =IFERROR(INDEX(Correspondance!$D$2:$D$3000,MATCH(A4,Correspondance!$A$2:$A$3000,0)),0) -> 9 | F4: =C4*E4 -> 52.282609 | G4: Mode opératoire : Assaisonner les filets de poulet (sel, poivre, filet d'huile d'olive), conditionner en poches sous vide à plat (1,5 kg maximum par poche) Cuisson : 65°C thermoplongeur ou four vapeur 2H00, contrôle 65°C à cœur (pasteurisation suffisante pour public fragile) Refroidir en cellule (63°C à 10°C en moins de deux heures), étiqueter, DLC 5 jours maximum (J+5) Cuire les pâtes à grande eau salée 9 à 11 min, égoutter, huiler, refroidir en cellule Le jour du service : ouvrir les poches, émincer le poulet froid en lanières Décontaminer et couper les tomates cerises en deux, laver et essorer la roquette Mélanger pâtes, pesto, huile d'olive, poulet, tomates cerises, rectifier sel et poivre Conditionner en bacs gastro, parsemer de parmesan, pignons, roquette et basilic, filmer, étiqueter Stocker à 0/+3°C, service en liaison froide dans les 24h après ouverture des poches
A5: Pâtes penne | B5: 2.31 | C5: =B5/B$22*B$24 -> 3.6268116 | D5: Kg | E5: =IFERROR(INDEX(Correspondance!$D$2:$D$3000,MATCH(A5,Correspondance!$A$2:$A$3000,0)),0) -> 1.6 | F5: =C5*E5 -> 5.8028986
A6: Pesto au basilic | B6: 0.554 | C6: =B6/B$22*B$24 -> 0.86980676 | D6: Kg | E6: =IFERROR(INDEX(Correspondance!$D$2:$D$3000,MATCH(A6,Correspondance!$A$2:$A$3000,0)),0) -> 9 | F6: =C6*E6 -> 7.8282609
A7: Tomates cerises | B7: 1.39 | C7: =B7/B$22*B$24 -> 2.1823671 | D7: Kg | E7: =IFERROR(INDEX(Correspondance!$D$2:$D$3000,MATCH(A7,Correspondance!$A$2:$A$3000,0)),0) -> 4.5 | F7: =C7*E7 -> 9.8206522
A8: Roquette ou jeunes pousses | B8: 0.462 | C8: =B8/B$22*B$24 -> 0.72536232 | D8: Kg | E8: =IFERROR(INDEX(Correspondance!$D$2:$D$3000,MATCH(A8,Correspondance!$A$2:$A$3000,0)),0) -> 10 | F8: =C8*E8 -> 7.2536232
A9: Parmesan râpé | B9: 0.277 | C9: =B9/B$22*B$24 -> 0.43490338 | D9: Kg | E9: =IFERROR(INDEX(Correspondance!$D$2:$D$3000,MATCH(A9,Correspondance!$A$2:$A$3000,0)),0) -> 16 | F9: =C9*E9 -> 6.9584541
A10: Huile d'olive | B10: 0.277 | C10: =B10/B$22*B$24 -> 0.43490338 | D10: L | E10: =IFERROR(INDEX(Correspondance!$D$2:$D$3000,MATCH(A10,Correspondance!$A$2:$A$3000,0)),0) -> 7.5 | F10: =C10*E10 -> 3.2617754
A11: Pignons de pin | B11: 0.092 | C11: =B11/B$22*B$24 -> 0.14444444 | D11: Kg | E11: =IFERROR(INDEX(Correspondance!$D$2:$D$3000,MATCH(A11,Correspondance!$A$2:$A$3000,0)),0) -> 38 | F11: =C11*E11 -> 5.4888889
A12: Sel | B12: 0.046 | C12: =B12/B$22*B$24 -> 0.072222222 | D12: Kg | E12: =IFERROR(INDEX(Correspondance!$D$2:$D$3000,MATCH(A12,Correspondance!$A$2:$A$3000,0)),0) -> 2 | F12: =C12*E12 -> 0.14444444
A13: Poivre PM | C13: =B13/B$22*B$24 -> 0 | D13: Kg | E13: =IFERROR(INDEX(Correspondance!$D$2:$D$3000,MATCH(A13,Correspondance!$A$2:$A$3000,0)),0) -> 18 | F13: =C13*E13 -> 0
A14: Basilic frais PM | C14: =B14/B$22*B$24 -> 0 | D14: Kg | E14: =IFERROR(INDEX(Correspondance!$D$2:$D$3000,MATCH(A14,Correspondance!$A$2:$A$3000,0)),0) -> 32 | F14: =C14*E14 -> 0
C15: =B15/B$22*B$24 -> 0 | E15: =IFERROR(INDEX(Correspondance!$D$2:$D$3000,MATCH(A15,Correspondance!$A$2:$A$3000,0)),0) -> 0 | F15: =C15*E15 -> 0
C16: =B16/B$22*B$24 -> 0 | E16: =IFERROR(INDEX(Correspondance!$D$2:$D$3000,MATCH(A16,Correspondance!$A$2:$A$3000,0)),0) -> 0 | F16: =C16*E16 -> 0
C17: =B17/B$22*B$24 -> 0 | E17: =IFERROR(INDEX(Correspondance!$D$2:$D$3000,MATCH(A17,Correspondance!$A$2:$A$3000,0)),0) -> 0 | F17: =C17*E17 -> 0
C18: =B18/B$22*B$24 -> 0 | E18: =IFERROR(INDEX(Correspondance!$D$2:$D$3000,MATCH(A18,Correspondance!$A$2:$A$3000,0)),0) -> 0 | F18: =C18*E18 -> 0
F19: =SUM(F4:F18) -> 98.841606
A20: Prix unitaire portion | B20: =F19/B24 -> 0.89856006
A21: Poids total ou ingrédient principal | B21: =SUM(B3:B18) -> 9.108
A22: Nombre portions recette base | B22: =B21/B23 -> 70.061538
A23: Poids net portions | B23: 0.13 | C23: Possibilité de saisir le grammage
A24: Nombre portions à produire | B24: =Paramètres!$B$5 -> 110 | C24: Effectif EHPAD + FAM (feuille Paramètres) – possibilité de saisir un autre nombre

Sheet E-Asperges vinaigrette
A1: Asperges vinaigrette sous vide basse température | E1: VP Théorique minimum | G1: Sous vide 85°C four vapeur ou thermoplongeur Poches sous vide, 30 à 45 min Refroidissement cellule, DLC J+5
E2: > à 10 000
A3: Produits | B3: Qté recette base | C3: Qté production | D3: U | E3: PU | F3: Total €
A4: Asperges blanches ou vertes (fraîches épluchées ou surgelées) | B4: 6.5 | C4: =B4/B$22*B$24 -> 10.216939 | D4: Kg | E4: =IFERROR(INDEX(Correspondance!$D$2:$D$3000,MATCH(A4,Correspondance!$A$2:$A$3000,0)),0) -> 9 | F4: =C4*E4 -> 91.952455 | G4: Mode opératoire : Asperges fraîches : éplucher, couper le pied, laver ; asperges surgelées : utiliser sans décongélation Ranger à plat en poches sous vide (1,5 kg maximum), saler, mettre sous vide Cuisson : 85°C vapeur ou thermoplongeur 30 à 45 min selon le calibre (vertes : 30 min), contrôle de tendreté Refroidir en cellule (63°C à 10°C en moins de deux heures), étiqueter, DLC 5 jours maximum (J+5) Le jour du service : ouvrir les poches, égoutter sur grille Vinaigrette : moutarde, sel, poivre, vinaigre, monter à l'huile, ajouter les échalotes Dresser 4 à 5 asperges par portion en bacs gastro, napper de vinaigrette, parsemer d'œuf dur haché et de ciboulette Filmer, stocker à 0/+3°C, service en liaison froide dans les 24h
A5: Huile de tournesol | B5: 0.464 | C5: =B5/B$22*B$24 -> 0.72933229 | D5: L | E5: =IFERROR(INDEX(Correspondance!$D$2:$D$3000,MATCH(A5,Correspondance!$A$2:$A$3000,0)),0) -> 2.2 | F5: =C5*E5 -> 1.604531
A6: Vinaigre de vin | B6: 0.139 | C6: =B6/B$22*B$24 -> 0.21848532 | D6: L | E6: =IFERROR(INDEX(Correspondance!$D$2:$D$3000,MATCH(A6,Correspondance!$A$2:$A$3000,0)),0) -> 1.5 | F6: =C6*E6 -> 0.32772798
A7: Moutarde | B7: 0.093 | C7: =B7/B$22*B$24 -> 0.14618083 | D7: Kg | E7: =IFERROR(INDEX(Correspondance!$D$2:$D$3000,MATCH(A7,Correspondance!$A$2:$A$3000,0)),0) -> 9 | F7: =C7*E7 -> 1.3156274
A8: Œufs durs écalés pasteurisés | B8: 0.372 | C8: =B8/B$22*B$24 -> 0.5847233 | D8: Kg | E8: =IFERROR(INDEX(Correspondance!$D$2:$D$3000,MATCH(A8,Correspondance!$A$2:$A$3000,0)),0) -> 5.6 | F8: =C8*E8 -> 3.2744505
A9: Échalotes ciselées surgelées | B9: 0.093 | C9: =B9/B$22*B$24 -> 0.14618083 | D9: Kg | E9: =IFERROR(INDEX(Correspondance!$D$2:$D$3000,MATCH(A9,Correspondance!$A$2:$A$3000,0)),0) -> 4.5 | F9: =C9*E9 -> 0.65781372
A10: Sel | B10: 0.037 | C10: =B10/B$22*B$24 -> 0.058157963 | D10: Kg | E10: =IFERROR(INDEX(Correspondance!$D$2:$D$3000,MATCH(A10,Correspondance!$A$2:$A$3000,0)),0) -> 2 | F10: =C10*E10 -> 0.11631593
A11: Poivre PM | C11: =B11/B$22*B$24 -> 0 | D11: Kg | E11: =IFERROR(INDEX(Correspondance!$D$2:$D$3000,MATCH(A11,Correspondance!$A$2:$A$3000,0)),0) -> 18 | F11: =C11*E11 -> 0
A12: Ciboulette ciselée PM | C12: =B12/B$22*B$24 -> 0 | D12: Kg | E12: =IFERROR(INDEX(Correspondance!$D$2:$D$3000,MATCH(A12,Correspondance!$A$2:$A$3000,0)),0) -> 13 | F12: =C12*E12 -> 0
C13: =B13/B$22*B$24 -> 0 | E13: =IFERROR(INDEX(Correspondance!$D$2:$D$3000,MATCH(A13,Correspondance!$A$2:$A$3000,0)),0) -> 0 | F13: =C13*E13 -> 0
C14: =B14/B$22*B$24 -> 0 | E14: =IFERROR(INDEX(Correspondance!$D$2:$D$3000,MATCH(A14,Correspondance!$A$2:$A$3000,0)),0) -> 0 | F14: =C14*E14 -> 0
C15: =B15/B$22*B$24 -> 0 | E15: =IFERROR(INDEX(Correspondance!$D$2:$D$3000,MATCH(A15,Correspondance!$A$2:$A$3000,0)),0) -> 0 | F15: =C15*E15 -> 0
C16: =B16/B$22*B$24 -> 0 | E16: =IFERROR(INDEX(Correspondance!$D$2:$D$3000,MATCH(A16,Correspondance!$A$2:$A$3000,0)),0) -> 0 | F16: =C16*E16 -> 0
C17: =B17/B$22*B$24 -> 0 | E17: =IFERROR(INDEX(Correspondance!$D$2:$D$3000,MATCH(A17,Correspondance!$A$2:$A$3000,0)),0) -> 0 | F17: =C17*E17 -> 0
C18: =B18/B$22*B$24 -> 0 | E18: =IFERROR(INDEX(Correspondance!$D$2:$D$3000,MATCH(A18,Correspondance!$A$2:$A$3000,0)),0) -> 0 | F18: =C18*E18 -> 0
F19: =SUM(F4:F18) -> 99.248922
A20: Prix unitaire portion | B20: =F19/B24 -> 0.90226293
A21: Poids total ou ingrédient principal | B21: =SUM(B3:B18) -> 7.698
A22: Nombre portions recette base | B22: =B21/B23 -> 69.981818
A23: Poids net portions | B23: 0.11 | C23: Possibilité de saisir le grammage
A24: Nombre portions à produire | B24: =Paramètres!$B$5 -> 110 | C24: Effectif EHPAD + FAM (feuille Paramètres) – possibilité de saisir un autre nombre

Sheet E-Pâté aux olives
A1: Pâté aux olives | E1: VP Théorique minimum | G1: Préparation froide Tranchage le jour même Bac gastro + film, 0/+3°C
E2: Liaison froide 0/+3°C
A3: Produits | B3: Qté recette base | C3: Qté production | D3: U | E3: PU | F3: Total €
A4: Pâté aux olives (tranche de 50 g) | B4: 3.19 | C4: =B4/B$22*B$24 -> 5.0101731 | D4: Kg | E4: =IFERROR(INDEX(Correspondance!$D$2:$D$3000,MATCH(A4,Correspondance!$A$2:$A$3000,0)),0) -> 8 | F4: =C4*E4 -> 40.081385 | G4: Mode opératoire : Contrôler la DLC et la T° à réception, stocker à 0/+3°C Déconditionner le pâté, trancher au couteau ou à la trancheuse (tranche de 50 g) le jour même Décontaminer, rincer et essorer la salade, laver les tomates cerises Dresser 1 tranche de pâté par assiette, cornichons, beurre portion, salade et tomates cerises Filmer, étiqueter, stocker à 0/+3°C Service en liaison froide, consommation dans les 24h après ouverture
A5: Cornichons | B5: 0.455 | C5: =B5/B$22*B$24 -> 0.71461717 | D5: Kg | E5: =IFERROR(INDEX(Correspondance!$D$2:$D$3000,MATCH(A5,Correspondance!$A$2:$A$3000,0)),0) -> 6.5 | F5: =C5*E5 -> 4.6450116
A6: Salade frisée | B6: 0.911 | C6: =B6/B$22*B$24 -> 1.4308049 | D6: Kg | E6: =IFERROR(INDEX(Correspondance!$D$2:$D$3000,MATCH(A6,Correspondance!$A$2:$A$3000,0)),0) -> 3.6 | F6: =C6*E6 -> 5.1508977
A7: Beurre portions 10 g | B7: 0.455 | C7: =B7/B$22*B$24 -> 0.71461717 | D7: Kg | E7: =IFERROR(INDEX(Correspondance!$D$2:$D$3000,MATCH(A7,Correspondance!$A$2:$A$3000,0)),0) -> 10.5 | F7: =C7*E7 -> 7.5034803
A8: Tomates cerises | B8: 0.455 | C8: =B8/B$22*B$24 -> 0.71461717 | D8: Kg | E8: =IFERROR(INDEX(Correspondance!$D$2:$D$3000,MATCH(A8,Correspondance!$A$2:$A$3000,0)),0) -> 4.5 | F8: =C8*E8 -> 3.2157773
A9: Moutarde | B9: 0.137 | C9: =B9/B$22*B$24 -> 0.21517044 | D9: Kg | E9: =IFERROR(INDEX(Correspondance!$D$2:$D$3000,MATCH(A9,Correspondance!$A$2:$A$3000,0)),0) -> 9 | F9: =C9*E9 -> 1.936534
C10: =B10/B$22*B$24 -> 0 | E10: =IFERROR(INDEX(Correspondance!$D$2:$D$3000,MATCH(A10,Correspondance!$A$2:$A$3000,0)),0) -> 0 | F10: =C10*E10 -> 0
C11: =B11/B$22*B$24 -> 0 | E11: =IFERROR(INDEX(Correspondance!$D$2:$D$3000,MATCH(A11,Correspondance!$A$2:$A$3000,0)),0) -> 0 | F11: =C11*E11 -> 0
C12: =B12/B$22*B$24 -> 0 | E12: =IFERROR(INDEX(Correspondance!$D$2:$D$3000,MATCH(A12,Correspondance!$A$2:$A$3000,0)),0) -> 0 | F12: =C12*E12 -> 0
C13: =B13/B$22*B$24 -> 0 | E13: =IFERROR(INDEX(Correspondance!$D$2:$D$3000,MATCH(A13,Correspondance!$A$2:$A$3000,0)),0) -> 0 | F13: =C13*E13 -> 0
C14: =B14/B$22*B$24 -> 0 | E14: =IFERROR(INDEX(Correspondance!$D$2:$D$3000,MATCH(A14,Correspondance!$A$2:$A$3000,0)),0) -> 0 | F14: =C14*E14 -> 0
C15: =B15/B$22*B$24 -> 0 | E15: =IFERROR(INDEX(Correspondance!$D$2:$D$3000,MATCH(A15,Correspondance!$A$2:$A$3000,0)),0) -> 0 | F15: =C15*E15 -> 0
C16: =B16/B$22*B$24 -> 0 | E16: =IFERROR(INDEX(Correspondance!$D$2:$D$3000,MATCH(A16,Correspondance!$A$2:$A$3000,0)),0) -> 0 | F16: =C16*E16 -> 0
C17: =B17/B$22*B$24 -> 0 | E17: =IFERROR(INDEX(Correspondance!$D$2:$D$3000,MATCH(A17,Correspondance!$A$2:$A$3000,0)),0) -> 0 | F17: =C17*E17 -> 0
C18: =B18/B$22*B$24 -> 0 | E18: =IFERROR(INDEX(Correspondance!$D$2:$D$3000,MATCH(A18,Correspondance!$A$2:$A$3000,0)),0) -> 0 | F18: =C18*E18 -> 0
F19: =SUM(F4:F18) -> 62.533086
A20: Prix unitaire portion | B20: =F19/B24 -> 0.5684826
A21: Poids total ou ingrédient principal | B21: =SUM(B3:B18) -> 5.603
A22: Nombre portions recette base | B22: =B21/B23 -> 70.0375
A23: Poids net portions | B23: 0.08 | C23: Possibilité de saisir le grammage
A24: Nombre portions à produire | B24: =Paramètres!$B$5 -> 110 | C24: Effectif EHPAD + FAM (feuille Paramètres) – possibilité de saisir un autre nombre

Sheet E-Jambon cru
A1: Jambon cru | E1: VP Théorique minimum | G1: Préparation froide Dressage le jour même Bac gastro + film, 0/+3°C
E2: Liaison froide 0/+3°C
A3: Produits | B3: Qté recette base | C3: Qté production | D3: U | E3: PU | F3: Total €
A4: Jambon cru tranché (2 tranches de 20 g) | B4: 2.95 | C4: =B4/B$22*B$24 -> 4.6348866 | D4: Kg | E4: =IFERROR(INDEX(Correspondance!$D$2:$D$3000,MATCH(A4,Correspondance!$A$2:$A$3000,0)),0) -> 22 | F4: =C4*E4 -> 101.96751 | G4: Mode opératoire : Contrôler la DLC et la T° à réception, stocker à 0/+3°C Déconditionner le jambon cru au plus près du service, séparer les tranches Décontaminer, rincer et essorer la salade, laver les tomates cerises Dresser 2 tranches de jambon cru par assiette, beurre portion, cornichons, salade et tomates cerises, filet d'huile d'olive, poivre Filmer, étiqueter, stocker à 0/+3°C Service en liaison froide, consommation dans les 24h après ouverture du conditionnement
A5: Beurre portions 10 g | B5: 0.589 | C5: =B5/B$22*B$24 -> 0.92540618 | D5: Kg | E5: =IFERROR(INDEX(Correspondance!$D$2:$D$3000,MATCH(A5,Correspondance!$A$2:$A$3000,0)),0) -> 10.5 | F5: =C5*E5 -> 9.7167649
A6: Cornichons | B6: 0.491 | C6: =B6/B$22*B$24 -> 0.77143367 | D6: Kg | E6: =IFERROR(INDEX(Correspondance!$D$2:$D$3000,MATCH(A6,Correspondance!$A$2:$A$3000,0)),0) -> 6.5 | F6: =C6*E6 -> 5.0143189
A7: Salade frisée | B7: 0.982 | C7: =B7/B$22*B$24 -> 1.5428673 | D7: Kg | E7: =IFERROR(INDEX(Correspondance!$D$2:$D$3000,MATCH(A7,Correspondance!$A$2:$A$3000,0)),0) -> 3.6 | F7: =C7*E7 -> 5.5543224
A8: Tomates cerises | B8: 0.491 | C8: =B8/B$22*B$24 -> 0.77143367 | D8: Kg | E8: =IFERROR(INDEX(Correspondance!$D$2:$D$3000,MATCH(A8,Correspondance!$A$2:$A$3000,0)),0) -> 4.5 | F8: =C8*E8 -> 3.4714515
A9: Huile d'olive | B9: 0.098 | C9: =B9/B$22*B$24 -> 0.1539725 | D9: L | E9: =IFERROR(INDEX(Correspondance!$D$2:$D$3000,MATCH(A9,Correspondance!$A$2:$A$3000,0)),0) -> 7.5 | F9: =C9*E9 -> 1.1547938
A10: Poivre PM | C10: =B10/B$22*B$24 -> 0 | D10: Kg | E10: =IFERROR(INDEX(Correspondance!$D$2:$D$3000,MATCH(A10,Correspondance!$A$2:$A$3000,0)),0) -> 18 | F10: =C10*E10 -> 0
C11: =B11/B$22*B$24 -> 0 | E11: =IFERROR(INDEX(Correspondance!$D$2:$D$3000,MATCH(A11,Correspondance!$A$2:$A$3000,0)),0) -> 0 | F11: =C11*E11 -> 0
C12: =B12/B$22*B$24 -> 0 | E12: =IFERROR(INDEX(Correspondance!$D$2:$D$3000,MATCH(A12,Correspondance!$A$2:$A$3000,0)),0) -> 0 | F12: =C12*E12 -> 0
C13: =B13/B$22*B$24 -> 0 | E13: =IFERROR(INDEX(Correspondance!$D$2:$D$3000,MATCH(A13,Correspondance!$A$2:$A$3000,0)),0) -> 0 | F13: =C13*E13 -> 0
C14: =B14/B$22*B$24 -> 0 | E14: =IFERROR(INDEX(Correspondance!$D$2:$D$3000,MATCH(A14,Correspondance!$A$2:$A$3000,0)),0) -> 0 | F14: =C14*E14 -> 0
C15: =B15/B$22*B$24 -> 0 | E15: =IFERROR(INDEX(Correspondance!$D$2:$D$3000,MATCH(A15,Correspondance!$A$2:$A$3000,0)),0) -> 0 | F15: =C15*E15 -> 0
C16: =B16/B$22*B$24 -> 0 | E16: =IFERROR(INDEX(Correspondance!$D$2:$D$3000,MATCH(A16,Correspondance!$A$2:$A$3000,0)),0) -> 0 | F16: =C16*E16 -> 0
C17: =B17/B$22*B$24 -> 0 | E17: =IFERROR(INDEX(Correspondance!$D$2:$D$3000,MATCH(A17,Correspondance!$A$2:$A$3000,0)),0) -> 0 | F17: =C17*E17 -> 0
C18: =B18/B$22*B$24 -> 0 | E18: =IFERROR(INDEX(Correspondance!$D$2:$D$3000,MATCH(A18,Correspondance!$A$2:$A$3000,0)),0) -> 0 | F18: =C18*E18 -> 0
F19: =SUM(F4:F18) -> 126.87916
A20: Prix unitaire portion | B20: =F19/B24 -> 1.1534469
A21: Poids total ou ingrédient principal | B21: =SUM(B3:B18) -> 5.601
A22: Nombre portions recette base | B22: =B21/B23 -> 70.0125
A23: Poids net portions | B23: 0.08 | C23: Possibilité de saisir le grammage
A24: Nombre portions à produire | B24: =Paramètres!$B$5 -> 110 | C24: Effectif EHPAD + FAM (feuille Paramètres) – possibilité de saisir un autre nombre

Sheet E-Pâté de campagne
A1: Pâté de campagne | E1: VP Théorique minimum | G1: Préparation froide Tranchage le jour même Bac gastro + film, 0/+3°C
E2: Liaison froide 0/+3°C
A3: Produits | B3: Qté recette base | C3: Qté production | D3: U | E3: PU | F3: Total €
A4: Pâté de campagne (tranche de 50 g) | B4: 3.29 | C4: =B4/B$22*B$24 -> 5.1736955 | D4: Kg | E4: =IFERROR(INDEX(Correspondance!$D$2:$D$3000,MATCH(A4,Correspondance!$A$2:$A$3000,0)),0) -> 7.5 | F4: =C4*E4 -> 38.802716 | G4: Mode opératoire : Contrôler la DLC et la T° à réception, stocker à 0/+3°C Déconditionner le pâté, trancher à la trancheuse ou au couteau (tranche de 50 g) le jour même Décontaminer, rincer et essorer la salade Dresser 1 tranche de pâté par assiette, cornichons, oignons au vinaigre, beurre portion, salade Filmer, étiqueter, stocker à 0/+3°C Service en liaison froide, consommation dans les 24h après ouverture
A5: Cornichons | B5: 0.471 | C5: =B5/B$22*B$24 -> 0.74067191 | D5: Kg | E5: =IFERROR(INDEX(Correspondance!$D$2:$D$3000,MATCH(A5,Correspondance!$A$2:$A$3000,0)),0) -> 6.5 | F5: =C5*E5 -> 4.8143674
A6: Oignons grelots au vinaigre | B6: 0.282 | C6: =B6/B$22*B$24 -> 0.44345961 | D6: Kg | E6: =IFERROR(INDEX(Correspondance!$D$2:$D$3000,MATCH(A6,Correspondance!$A$2:$A$3000,0)),0) -> 6 | F6: =C6*E6 -> 2.6607577
A7: Salade frisée | B7: 0.941 | C7: =B7/B$22*B$24 -> 1.4797713 | D7: Kg | E7: =IFERROR(INDEX(Correspondance!$D$2:$D$3000,MATCH(A7,Correspondance!$A$2:$A$3000,0)),0) -> 3.6 | F7: =C7*E7 -> 5.3271766
A8: Beurre portions 10 g | B8: 0.471 | C8: =B8/B$22*B$24 -> 0.74067191 | D8: Kg | E8: =IFERROR(INDEX(Correspondance!$D$2:$D$3000,MATCH(A8,Correspondance!$A$2:$A$3000,0)),0) -> 10.5 | F8: =C8*E8 -> 7.777055
A9: Moutarde | B9: 0.141 | C9: =B9/B$22*B$24 -> 0.22172981 | D9: Kg | E9: =IFERROR(INDEX(Correspondance!$D$2:$D$3000,MATCH(A9,Correspondance!$A$2:$A$3000,0)),0) -> 9 | F9: =C9*E9 -> 1.9955683
C10: =B10/B$22*B$24 -> 0 | E10: =IFERROR(INDEX(Correspondance!$D$2:$D$3000,MATCH(A10,Correspondance!$A$2:$A$3000,0)),0) -> 0 | F10: =C10*E10 -> 0
C11: =B11/B$22*B$24 -> 0 | E11: =IFERROR(INDEX(Correspondance!$D$2:$D$3000,MATCH(A11,Correspondance!$A$2:$A$3000,0)),0) -> 0 | F11: =C11*E11 -> 0
C12: =B12/B$22*B$24 -> 0 | E12: =IFERROR(INDEX(Correspondance!$D$2:$D$3000,MATCH(A12,Correspondance!$A$2:$A$3000,0)),0) -> 0 | F12: =C12*E12 -> 0
C13: =B13/B$22*B$24 -> 0 | E13: =IFERROR(INDEX(Correspondance!$D$2:$D$3000,MATCH(A13,Correspondance!$A$2:$A$3000,0)),0) -> 0 | F13: =C13*E13 -> 0
C14: =B14/B$22*B$24 -> 0 | E14: =IFERROR(INDEX(Correspondance!$D$2:$D$3000,MATCH(A14,Correspondance!$A$2:$A$3000,0)),0) -> 0 | F14: =C14*E14 -> 0
C15: =B15/B$22*B$24 -> 0 | E15: =IFERROR(INDEX(Correspondance!$D$2:$D$3000,MATCH(A15,Correspondance!$A$2:$A$3000,0)),0) -> 0 | F15: =C15*E15 -> 0
C16: =B16/B$22*B$24 -> 0 | E16: =IFERROR(INDEX(Correspondance!$D$2:$D$3000,MATCH(A16,Correspondance!$A$2:$A$3000,0)),0) -> 0 | F16: =C16*E16 -> 0
C17: =B17/B$22*B$24 -> 0 | E17: =IFERROR(INDEX(Correspondance!$D$2:$D$3000,MATCH(A17,Correspondance!$A$2:$A$3000,0)),0) -> 0 | F17: =C17*E17 -> 0
C18: =B18/B$22*B$24 -> 0 | E18: =IFERROR(INDEX(Correspondance!$D$2:$D$3000,MATCH(A18,Correspondance!$A$2:$A$3000,0)),0) -> 0 | F18: =C18*E18 -> 0
F19: =SUM(F4:F18) -> 61.377641
A20: Prix unitaire portion | B20: =F19/B24 -> 0.55797856
A21: Poids total ou ingrédient principal | B21: =SUM(B3:B18) -> 5.596
A22: Nombre portions recette base | B22: =B21/B23 -> 69.95
A23: Poids net portions | B23: 0.08 | C23: Possibilité de saisir le grammage
A24: Nombre portions à produire | B24: =Paramètres!$B$5 -> 110 | C24: Effectif EHPAD + FAM (feuille Paramètres) – possibilité de saisir un autre nombre

Sheet E-Salade de chou-fleur
A1: Salade de chou-fleur | E1: VP Théorique minimum | G1: Cuisson vapeur 100°C four mixte Bacs gastro perforés, 8 à 10 min Refroidissement cellule puis assemblage froid
E2: 63°C à cœur
A3: Produits | B3: Qté recette base | C3: Qté production | D3: U | E3: PU | F3: Total €
A4: Chou-fleur fleurettes surgelé | B4: 6.49 | C4: =B4/B$22*B$24 -> 10.203872 | D4: Kg | E4: =IFERROR(INDEX(Correspondance!$D$2:$D$3000,MATCH(A4,Correspondance!$A$2:$A$3000,0)),0) -> 2.2 | F4: =C4*E4 -> 22.448519 | G4: Mode opératoire : Répartir le chou-fleur surgelé sans décongélation en bacs gastro perforés (3 kg maximum par bac) Cuisson vapeur 100°C four mixte 8 à 10 min, le chou-fleur doit rester légèrement croquant Refroidir immédiatement en cellule (63°C à 10°C en moins de deux heures), réserver à 0/+3°C Vinaigrette : moutarde, sel, poivre, vinaigre, monter à l'huile, ajouter les échalotes Mélanger le chou-fleur froid et la vinaigrette, laisser mariner 1 heure à 0/+3°C Conditionner en bacs gastro, parsemer d'œuf dur haché et de persil, filmer, étiqueter Service en liaison froide, consommation dans les 48h
A5: Huile de tournesol | B5: 0.464 | C5: =B5/B$22*B$24 -> 0.72952183 | D5: L | E5: =IFERROR(INDEX(Correspondance!$D$2:$D$3000,MATCH(A5,Correspondance!$A$2:$A$3000,0)),0) -> 2.2 | F5: =C5*E5 -> 1.604948
A6: Vinaigre de vin | B6: 0.139 | C6: =B6/B$22*B$24 -> 0.2185421 | D6: L | E6: =IFERROR(INDEX(Correspondance!$D$2:$D$3000,MATCH(A6,Correspondance!$A$2:$A$3000,0)),0) -> 1.5 | F6: =C6*E6 -> 0.32781315
A7: Moutarde | B7: 0.093 | C7: =B7/B$22*B$24 -> 0.14621881 | D7: Kg | E7: =IFERROR(INDEX(Correspondance!$D$2:$D$3000,MATCH(A7,Correspondance!$A$2:$A$3000,0)),0) -> 9 | F7: =C7*E7 -> 1.3159693
